Workbook
Name _Abrechnungstarif_LEG: Eingaben!$C$61
Name _Abzug_Funktion_GH: Eingaben!$C$90
Name _Abzug_Funktion_Notstrom: Eingaben!$C$102
Name _Amortisationszeit: Berechnungen!$BR$53
Name _Amortisationszeit_Batterie: Berechnungen!$CD$53
Name _Amortisationszeit_PVA_Batterie: Berechnungen!$BX$53
Name _Anlagekategorie: Eingaben!$B$16
Name _Anlagenlebensdauer: Eingaben!$C$20
Name _Anlagenleistung: Eingaben!$C$17
Name _Anteil_LEG: Eingaben!$C$58
Name _Anzahl_Verbraucher: Eingaben!$C$42
Name _Batterie: Eingaben!$C$26
Name _Bemerkungen: Eingaben!$B$11
Name _Berechnungsart_Unterhaltskosten: Eingaben!$B$111
Name _Betreiber: Eingaben!$B$4
Name _Dach_angebaut: Listen!$C$5
Name _Dach_integriert: Listen!$C$4
Name _Debug_Modus: Eingaben!$O$2
Name _Degradation: Eingaben!$C$23
Name _Degradation_Speicher_Jahr: Eingaben!$C$31
Name _direkteFörderung: Eingaben!$C$81
Name _durchschnittlich_Energie_eingelagert: Berechnungen!$O$54
Name _Durchschnittliche_Betriebskosten_LEG: Berechnungen!$AZ$54
Name _Durchschnittliche_Betriebskosten_ZEV: Berechnungen!$AY$54
Name _Durchschnittliche_Eigenkapitalkosten: Berechnungen!$BH$54
Name _Durchschnittliche_Eigenkapitalkosten_Batterie: Berechnungen!$BK$54
Name _durchschnittliche_Einsparung_Leistung: Berechnungen!$Y$54
Name _durchschnittliche_Einsparung_Leistung_Batterie: Berechnungen!$AD$54
Name _Durchschnittliche_Kost_Ersatz_Batterie: Berechnungen!$BA$54
Name _durchschnittliche_Kosten_Energie_Speicher: Berechnungen!$AE$54
Name _Durchschnittliche_Umsatzsteuer: Berechnungen!$BB$54
Name _Durchschnittliche_Unterhaltskosten: Berechnungen!$AX$54
Name _Durchschnittliche_Unterhaltskosten_Batterie: Berechnungen!$BA$54
Name _Durchschnittliche_Vergütung_Rücklieferung: Berechnungen!$S$54
Name _Durchschnittliche_Vorsteuer_Batterieersatz: Berechnungen!$BD$54
Name _Durchschnittliche_Vorsteuer_Unterhalt: Berechnungen!$BC$54
Name _Durchschnittlicher_Abrechnungsgebühren_ZEV: Berechnungen!$AB$54
Name _Durchschnittlicher_Energieertrag: Berechnungen!$K$54
Name _Durchschnittlicher_Speichermenge: Berechnungen!$Q$54
Name _Durchschnittlicher_Verkauf_Batteriestrom: Berechnungen!$AC$54
Name _durchschnittlicher_Verkauf_LEG: Berechnungen!$U$54
Name _Durchschnittlicher_Verkauf_Solarstrom: Berechnungen!$W$54
Name _Durchschnittlicher_Zins_FK_Batterie: Berechnungen!$BL$54
Name _Durchschnittlicher_Zins_FK1: Berechnungen!$BI$54
Name _Durchschnittlicher_Zins_FK2: Berechnungen!$BJ$54
Name _Eigenkapital: Eingaben!$C$95
Name _Eigenkapital_Batterie: Eingaben!$C$107
Name _Eigenkapitalrendite: Bericht!$B$18
Name _Eigennutzungsgrad: Eingaben!$C$45
Name _Eigennutzungsgrad_Batterie: Eingaben!$C$32
Name _Einmalvergütung: Eingaben!$C$76
Name _Erhöhung_Eigennutzungsgrad_Speicher: Eingaben!$C$33
Name _ersetzterBezugstarifZEV: Eingaben!$C$47
Name _f_Ersatztarif: Eingaben!#REF!
Name _Fassade_angebaut: Listen!$C$7
Name _Fassade_integriert: Listen!$C$6
Name _Fassadenbonus: Eingaben!$C$77
Name _Förderung_Batterie: Eingaben!$C$83
Name _freistehend: Listen!$C$9
Name _Fremdkapital_Batterie: Eingaben!$C$108

Sheet Bericht
A1: Projektangaben | K1: =_xlfn.TRANSLATE(A1,"de", "en") -> Project information
A2: Projektbezeichnung: | B2: =_Projektbezeichnung&", "&_Standort -> , | K2: =_xlfn.TRANSLATE(A2,"de", "en") -> Project name:
K3: =_xlfn.TRANSLATE(A3,"de", "en")
A4: Projektnummer: | B4: =IF(_Projektnummer<>"",_Projektnummer,"") | F4: Projektleiter: | G4: =IF(_Projektleiter<>"",_Projektleiter,"") | K4: =_xlfn.TRANSLATE(A4,"de", "en") -> Project number:
A5: Betreiber / Investor: | B5: =IF(_Betreiber<>"",_Betreiber,"") | F5: MWSt. Pflicht | G5: =_MWStPflicht -> MWSt. pflichtig | K5: =_xlfn.TRANSLATE(A5,"de", "en") -> Operator / Investor:
K6: =_xlfn.TRANSLATE(A6,"de", "en")
A7: Bemerkungen: | B7: =IF(_Bemerkungen<>"",_Bemerkungen,"") | K7: =_xlfn.TRANSLATE(A7,"de", "en") -> Remarks:
A8: Netzbetreiber: | B8: =IF(Eingaben!B10<>"",Eingaben!B10,"") | K8: =_xlfn.TRANSLATE(A8,"de", "en") -> Common carrier:
K9: =_xlfn.TRANSLATE(A9,"de", "en")
A10: Wirtschaftlichkeitsberechnung | I10: ="Version Swissolar: " & _Version -> Version Swissolar: V2.4 | K10: =_xlfn.TRANSLATE(A10,"de", "en") -> Profitability calculation
K11: =_xlfn.TRANSLATE(A11,"de", "en")
A12: Kennzahlen PV- Anlage | F12: Kennzahlen PV- Anlage und Batteriespeicher | K12: =_xlfn.TRANSLATE(A12,"de", "en") -> Key figures for PV systems | N12: =_xlfn.TRANSLATE(F12,"de","en") -> Key figures for PV systems and battery storage systems
G13: PVA und Batterie | H13: nur Batterie | K13: =_xlfn.TRANSLATE(A13,"de", "en") | N13: =_xlfn.TRANSLATE(F13,"de","en") | O13: =_xlfn.TRANSLATE(G13,"de","en") -> PVA and battery | P13: =_xlfn.TRANSLATE(H13,"de","en") -> Battery only
A14: kWh-Kosten (Gestehungskosten) | B14: =IF(_Anlagenleistung=0,"--",-1*(_Summe_Betrieb_Unterhalt+_Summe_MWSt_Umsatz+_Summe_MWSt_Betrieb_Unterhalt+_Summe_Eigenkapital+_Summe_FK1+_Summe_FK2)/_Gesamtenergieertrag) -> 0.30068889 | C14: CHF/kWh | F14: kWh-Kosten (Gestehungskosten) | G14: =IF(_Speicherkapazität=0,"--",-1*(_Summe_Betrieb_Unterhalt+_Summe_Betrieb_Unterhalt_Batterie+_Summe_MWSt_Umsatz+_Summe_MWSt_Betrieb_Unterhalt+_Summe_MWSt_Betrieb_Unterhalt_Batterie+_Summe_Eigenkapital+_Summe_Eigenkapital_Batterie+_Summe_FK1+_Summe_FK2+_Summe_FK1_Batterie)/_Gesamtenergieertrag) -> -- | H14: =IF(_Speicherkapazität=0,"--",-1*(_Summe_Betrieb_Unterhalt_Batterie+_Summe_MWSt_Betrieb_Unterhalt_Batterie+_Summe_Eigenkapital_Batterie+_Summe_FK1_Batterie)/_Gesamtspeichermenge) -> -- | I14: CHF/kWh | K14: =_xlfn.TRANSLATE(A14,"de", "en") -> kWh costs (production costs) | N14: =_xlfn.TRANSLATE(F14,"de","en") -> kWh costs (production costs)
A15: Payback (dyn. Amortisationsrechnung) | B15: =IF(_Amortisationszeit>0,_Amortisationszeit,"--") -> -- | C15: Jahre | F15: Payback (dyn. Amortisationsrechnung) | G15: =IF(_Amortisationszeit_PVA_Batterie>0,_Amortisationszeit_PVA_Batterie,"--") -> -- | H15: =IF(_Amortisationszeit_Batterie>0,_Amortisationszeit_Batterie,"--") -> -- | I15: Jahre | K15: =_xlfn.TRANSLATE(A15,"de", "en") -> Payback (dyn. amortization calculation) | N15: =_xlfn.TRANSLATE(F15,"de","en") -> Payback (dyn. amortization calculation)
A16: Kapitalbarwert (NPV mit Annuität) | B16: =IF(_Anlagenleistung>0,_NPV,"--") -> -18880.846 | C16: CHF | F16: Kapitalbarwert (NPV mit Annuität) | G16: =_NPV_PVA_Batterie -> -18880.846 | H16: =_NPV_Batterie -> 0 | I16: CHF | K16: =_xlfn.TRANSLATE(A16,"de", "en") -> Net present value (NPV with annuity) | N16: =_xlfn.TRANSLATE(F16,"de","en") -> Net present value (NPV with annuity)
A17: Projektrendite (Project IRR) | B17: =IF(ISNUMBER(IRR(Berechnungen!BN7:BN52)*100),IF(IRR(Berechnungen!BN7:BN52)*100>0,IRR(Berechnungen!BN7:BN52)*100,"--"),"--") -> -- | C17: % | F17: Projektrendite (Project IRR) | G17: =IF(ISNUMBER(IRR(Berechnungen!BT7:BT52)*100),IF(IRR(Berechnungen!BT7:BT52)*100>0,IRR(Berechnungen!BT7:BT52)*100,"--"),"--") -> -- | H17: =IF(ISNUMBER(IRR(Berechnungen!BZ7:BZ52)),IF(IRR(Berechnungen!BZ7:BZ52)*100>0,IRR(Berechnungen!BZ7:BZ52)*100,"--"),"--") -> -- | I17: % | K17: =_xlfn.TRANSLATE(A17,"de", "en") -> Project ROI (Project IRR) | N17: =_xlfn.TRANSLATE(F17,"de","en") -> Project ROI (Project IRR)
A18: Eigenkapitalrendite (Equity IRR) | B18: =IF(IRR(Berechnungen!BM7:BM52)*100>0,IRR(Berechnungen!BM7:BM52)*100,"--") -> #NUM! | C18: % | F18: Eigenkapitalrendite (Equity IRR) | G18: =IF(IRR(Berechnungen!BS7:BS52)*100>0,IRR(Berechnungen!BS7:BS52)*100,"--") -> #NUM! | H18: =IF(IRR(Berechnungen!BY7:BY52)*100>0,IRR(Berechnungen!BY7:BY52)*100,"--") -> #NUM! | I18: % | K18: =_xlfn.TRANSLATE(A18,"de", "en") -> Return on equity (IRR) | N18: =_xlfn.TRANSLATE(F18,"de","en") -> Return on equity (IRR)
K19: =_xlfn.TRANSLATE(A19,"de", "en") | N19: =_xlfn.TRANSLATE(F19,"de","en")
A20: Durchschnittswerte PV- Anlage | F20: Durchschnittswerte Batteriespeicher | K20: =_xlfn.TRANSLATE(A20,"de", "en") -> Average values PV system | N20: =_xlfn.TRANSLATE(F20,"de","en") -> Average values battery storage
A21: Ø Jahresenergieertrag | C21: =_Durchschnittlicher_Energieertrag -> 4239 | D21: kWh/Jahr | F21: Ø eingelagerte Energie | H21: =_durchschnittlich_Energie_eingelagert -> #DIV/0! | I21: kWh/Jahr | K21: =_xlfn.TRANSLATE(A21,"de", "en") -> Ø Annual energy yield | N21: =_xlfn.TRANSLATE(F21,"de","en") -> Ø stored energy
A22: ="davon Ø "&(IF(_ZEV="ja","Eigenverbrauch ZEV oder vZEV","Eigenverbrauch")) -> davon Ø Eigenverbrauch ZEV oder vZEV | C22: =_Eigennutzungsgrad/100*_Durchschnittlicher_Energieertrag -> 1410.3333 | D22: kWh/Jahr | F22: ="Ø "&IF(_ZEV=_NEIN,"Einsparung Bezug",IF(_ZEV=_JA,"Stromverkauf ZEV","Fehler")) -> Ø Stromverkauf ZEV | H22: =_Durchschnittlicher_Verkauf_Batteriestrom -> #DIV/0! | I22: CHF/Jahr | K22: =_xlfn.TRANSLATE(A22,"de", "en") -> of which Ø self-consumption ZEV or vZEV | N22: =_xlfn.TRANSLATE(F22,"de","en") -> Ø Electricity sales ZEV
A23: davon Ø Abnahmevergütung | C23: =(1-_Eigennutzungsgrad/100-_Anteil_LEG/100)*_Durchschnittlicher_Energieertrag -> -4.7062354e-13 | D23: kWh/Jahr | F23: ="Ø "&IF(_ZEV=_NEIN,"Einsparung Leistung",IF(_ZEV=_JA,"ZEV Verkauf Batterieleistung","Fehler")) -> Ø ZEV Verkauf Batterieleistung | H23: =_durchschnittliche_Einsparung_Leistung_Batterie -> #DIV/0! | I23: CHF/Jahr | K23: =_xlfn.TRANSLATE(A23,"de", "en") -> of which Ø Purchase remuneration | N23: =_xlfn.TRANSLATE(F23,"de","en") -> Ø ZEV Sale Battery Power
A24: davon Ø an LEG | C24: =_Anteil_LEG/100*_Durchschnittlicher_Energieertrag -> 2828.6667 | D24: kWh/Jahr | F24: Ø Kosten eingelagerte Energie (zum Tarif Abnahmevergütung) | H24: =_durchschnittliche_Kosten_Energie_Speicher -> #DIV/0! | I24: CHF/Jahr | K24: =_xlfn.TRANSLATE(A24,"de", "en") -> of which Ø to LEG | N24: =_xlfn.TRANSLATE(F24,"de","en") -> Ø Costs of stored energy (at the tariff for purchase remuneration)
A25: Ø Abnahmevergütung | C25: =_Durchschnittliche_Vergütung_Rücklieferung -> -4.0447043e-14 | D25: CHF/Jahr | F25: Ø Unterhaltsaufwand und Ersatz | H25: =_Durchschnittliche_Kost_Ersatz_Batterie -> #DIV/0! | I25: CHF/Jahr | K25: =_xlfn.TRANSLATE(A25,"de", "en") -> Ø Purchase remuneration | N25: =_xlfn.TRANSLATE(F25,"de","en") -> Ø Maintenance costs and replacement
A26: ="Ø "&IF(_ZEV=_NEIN,"Einsparung Bezug",IF(_ZEV=_JA,"Stromverkauf ZEV","Fehler")) -> Ø Stromverkauf ZEV | C26: =_Durchschnittlicher_Verkauf_Solarstrom -> 351.50611 | D26: CHF/Jahr | F26: Ø MWST-Vorsteuer (Unterhalt und Ersatz Batteriespeicher) | H26: =_Durchschnittliche_Vorsteuer_Batterieersatz -> #DIV/0! | I26: CHF/Jahr | K26: =_xlfn.TRANSLATE(A26,"de", "en") -> Ø Electricity sales ZEV | N26: =_xlfn.TRANSLATE(F26,"de","en") -> Ø VAT input tax (maintenance and replacement of battery storage)
A27: ="Ø "&IF(_ZEV=_NEIN,"Einsparung Leistung",IF(_ZEV=_JA,"ZEV Verkauf Leistung","Fehler")) -> Ø ZEV Verkauf Leistung | C27: =_durchschnittliche_Einsparung_Leistung -> 0 | D27: CHF/Jahr | F27: Ø Eigenkapitalkosten | H27: =_Durchschnittliche_Eigenkapitalkosten_Batterie -> #DIV/0! | I27: CHF/Jahr | K27: =_xlfn.TRANSLATE(A27,"de", "en") -> Ø ZEV Sales Performance | N27: =_xlfn.TRANSLATE(F27,"de","en") -> Ø Cost of equity
A28: =IF(_ZEV=_NEIN,"",IF(_ZEV=_JA,"Ø ZEV Abrechnungsgebühren","Fehler")) -> Ø ZEV Abrechnungsgebühren | C28: =IF(_ZEV="NEIN","",_Durchschnittlicher_Abrechnungsgebühren_ZEV) -> 0 | D28: =IF(_ZEV="NEIN","","CHF/Jahr") -> CHF/Jahr | F28: Ø Fremdkapitalkosten | H28: =_Durchschnittlicher_Zins_FK_Batterie -> #DIV/0! | I28: CHF/Jahr | K28: =_xlfn.TRANSLATE(A28,"de", "en") -> Ø ZEV Billing Fees | N28: =_xlfn.TRANSLATE(F28,"de","en") -> Ø Borrowing costs
A29: =IF(_LEG=_NEIN,"",IF(_LEG=_JA,"Ø Stromverkauf LEG (inkl. Abrechnungsgebühr)","Fehler")) -> Ø Stromverkauf LEG (inkl. Abrechnungsgebühr) | C29: =IF(_LEG="NEIN","",_durchschnittlicher_Verkauf_LEG) -> 293.75257 | D29: =IF(_LEG="NEIN","","CHF/Jahr") -> CHF/Jahr | F29: Ø Nettoertrag Batteriespeicher | H29: =SUM(H22:H28) -> #DIV/0! | I29: CHF/Jahr | K29: =_xlfn.TRANSLATE(A29,"de", "en") -> Ø Electricity sale LEG (incl. billing fee) | N29: =_xlfn.TRANSLATE(F29,"de","en") -> Ø Net yield battery storage
A30: =IF(_ZEV=_NEIN,"",IF(_ZEV=_JA,"Ø Betriebs- und Abrechnungskosten ZEV","Fehler")) -> Ø Betriebs- und Abrechnungskosten ZEV | C30: =IF(_ZEV="NEIN","",_Durchschnittliche_Betriebskosten_ZEV) -> 0 | D30: =IF(_ZEV="NEIN","","CHF/Jahr") -> CHF/Jahr | K30: =_xlfn.TRANSLATE(A30,"de", "en") -> Ø Operating and billing costs ZEV | N30: =_xlfn.TRANSLATE(F30,"de","en")
A31: =IF(_LEG=_NEIN,"",IF(_LEG=_JA,"Ø Betriebs- und Abrechnungskosten LEG","Fehler")) -> Ø Betriebs- und Abrechnungskosten LEG | C31: =IF(_LEG="NEIN","",_Durchschnittliche_Betriebskosten_LEG) -> 0 | D31: =IF(_LEG="NEIN","","CHF/Jahr") -> CHF/Jahr | K31: =_xlfn.TRANSLATE(A31,"de", "en") -> Ø Operating and billing costs LEG | N31: =_xlfn.TRANSLATE(F31,"de","en")
A32: Ø Unterhaltsaufwand | C32: =_Durchschnittliche_Unterhaltskosten -> -830.41735 | D32: CHF/Jahr | K32: =_xlfn.TRANSLATE(A32,"de", "en") -> Ø Maintenance costs | N32: =_xlfn.TRANSLATE(F32,"de","en")
A33: Ø MWST-Umsatzsteuer (Abnahmevergütung) | C33: =_Durchschnittliche_Umsatzsteuer -> 3.2762105e-15 | D33: CHF/Jahr | K33: =_xlfn.TRANSLATE(A33,"de", "en") -> Ø VAT (purchase remuneration) | N33: =_xlfn.TRANSLATE(F33,"de","en")
A34: Ø MWST-Vorsteuer (Unterhaltskosten) | C34: =_Durchschnittliche_Vorsteuer_Unterhalt -> 67.263805 | D34: CHF/Jahr | K34: =_xlfn.TRANSLATE(A34,"de", "en") -> Ø VAT input tax (maintenance costs) | N34: =_xlfn.TRANSLATE(F34,"de","en")
A35: Ø Eigenkapitalkosten | C35: =_Durchschnittliche_Eigenkapitalkosten -> -511.46667 | D35: CHF/Jahr | K35: =_xlfn.TRANSLATE(A35,"de", "en") -> Ø Cost of equity | N35: =_xlfn.TRANSLATE(F35,"de","en")
A36: Ø Fremdkapitalkosten | C36: =_Durchschnittlicher_Zins_FK1+_Durchschnittlicher_Zins_FK2 -> 0 | D36: CHF/Jahr | K36: =_xlfn.TRANSLATE(A36,"de", "en") -> Ø Borrowing costs | N36: =_xlfn.TRANSLATE(F36,"de","en")
A37: Ø Nettoertrag PV- Anlage | C37: =SUM(C25:C36) -> -629.36154 | D37: CHF/Jahr | F37: Teuerungsrate (für Tarife und Unterhaltskosten) | H37: =_Teuerungsrate -> 0.5 | I37: %/Jahr | K37: =_xlfn.TRANSLATE(A37,"de", "en") -> Ø Net yield of PV system | N37: =_xlfn.TRANSLATE(F37,"de","en") -> Inflation rate (for tariffs and maintenance costs)
K38: =_xlfn.TRANSLATE(A38,"de", "en") | N38: =_xlfn.TRANSLATE(F38,"de","en")
A39: Anlagedaten | K39: =_xlfn.TRANSLATE(A39,"de", "en") -> System data | N39: =_xlfn.TRANSLATE(F39,"de","en")
A40: Anlagekategorie | B40: =_Anlagekategorie -> Dach integriert | K40: =_xlfn.TRANSLATE(A40,"de", "en") -> Investment category | N40: =_xlfn.TRANSLATE(F40,"de","en")
A41: Inbetriebnahmejahr | B41: =_IBNJahr -> 2025 | F41: Anlagelebensdauer | G41: =_Anlagenlebensdauer -> 30 | H41: Jahre | K41: =_xlfn.TRANSLATE(A41,"de", "en") -> Year of commissioning | N41: =_xlfn.TRANSLATE(F41,"de","en") -> System life
A42: Anlagenennleistung (STC) | B42: =_Anlagenleistung -> 4.5 | C42: kW | F42: Fläche PV- Anlage | G42: =IF(_PV_Fläche<>0,_PV_Fläche,"") -> 18.75 | H42: m2 | K42: =_xlfn.TRANSLATE(A42,"de", "en") -> Plant Rated Power (STC) | N42: =_xlfn.TRANSLATE(F42,"de","en") -> Area of PV system
A43: spez. Jahresenergieertrag | B43: =_spez_Jahresenergieertrag -> 1000 | C43: kWh/kW | F43: Degradation | G43: =_Degradation -> 0.4 | H43: %/Jahr (der Anfangsleistung) | K43: =_xlfn.TRANSLATE(A43,"de", "en") -> spec. Annual energy yield | N43: =_xlfn.TRANSLATE(F43,"de","en") -> Degradation
K44: =_xlfn.TRANSLATE(A44,"de", "en") | N44: =_xlfn.TRANSLATE(F44,"de","en")
A45: Jahresenergieverbrauch | B45: =_Gesamtverbrauch -> 4500 | C45: kWh | F45: Kapazität Batteriespeicher | G45: =_Speicherkapazität -> 0 | H45: kWh | K45: =_xlfn.TRANSLATE(A45,"de", "en") -> Annual energy consumption | N45: =_xlfn.TRANSLATE(F45,"de","en") -> Battery storage capacity
A46: direkter Eigenverbrauchsanteil PV- Anlage | B46: =_Eigennutzungsgrad -> 33.270424 | C46: % | F46: Lebensdauer Batteriespeicher | G46: =_Lebensdauer_Speicher -> 15 | H46: Jahre | K46: =_xlfn.TRANSLATE(A46,"de", "en") -> Direct self-consumption share of PV system | N46: =_xlfn.TRANSLATE(F46,"de","en") -> Battery storage service life
A47: Eigenverbrauchsanteil mit Batteriespeicher | B47: =_Eigennutzungsgrad_Batterie -> 0 | C47: % | F47: Degradation Batteriespeicher | G47: =_Degradation_Speicher_Jahr -> 1.3333333 | H47: % / Jahr | K47: =_xlfn.TRANSLATE(A47,"de", "en") -> Self-consumption share with battery storage | N47: =_xlfn.TRANSLATE(F47,"de","en") -> Degradation of battery storage systems
K48: =_xlfn.TRANSLATE(A48,"de", "en") | N48: =_xlfn.TRANSLATE(F48,"de","en")
A49: Investitionskosten und Förderung | K49: =_xlfn.TRANSLATE(A49,"de", "en") -> Investment costs and funding | N49: =_xlfn.TRANSLATE(F49,"de","en")
A50: ="Investition PV- Anlage "&Eingaben!E86 -> Investition PV- Anlage (exkl. MWSt.) | B50: =_Investitionssumme -> 15344 | F50: ="Investition Batteriespeicher "&Eingaben!E86 -> Investition Batteriespeicher (exkl. MWSt.) | G50: =_Investitionssumme_Batterie -> 0 | K50: =_xlfn.TRANSLATE(A50,"de", "en") -> Investment PV system (excl. VAT) | N50: =_xlfn.TRANSLATE(F50,"de","en") -> Investment in battery storage (excl. VAT)
A51: ="Investition ZEV "&Eingaben!E86 -> Investition ZEV (exkl. MWSt.) | B51: =_Investition_ZEV -> 0 | F51: ="Sonstige Aufwände Batterie "&Eingaben!E86 -> Sonstige Aufwände Batterie (exkl. MWSt.) | G51: =_sonstige_Aufwände_Batterie -> 0 | K51: =_xlfn.TRANSLATE(A51,"de", "en") -> Investment ZEV (excl. VAT) | N51: =_xlfn.TRANSLATE(F51,"de","en") -> Other expenses battery (excl. VAT)
A52: ="sonstige Investitionen PVA "&Eingaben!E86 -> sonstige Investitionen PVA (exkl. MWSt.) | B52: =_sonstige_Aufwände -> 0 | K52: =_xlfn.TRANSLATE(A52,"de", "en") -> Other investments PVA (excl. VAT) | N52: =_xlfn.TRANSLATE(F52,"de","en")
A53: ="Abzug Funktion Gebäudehülle "&Eingaben!E86 -> Abzug Funktion Gebäudehülle (exkl. MWSt.) | B53: =_Abzug_Funktion_GH -> 0 | F53: Wert Funktion Notstrom | G53: =_Abzug_Funktion_Notstrom -> 0 | K53: =_xlfn.TRANSLATE(A53,"de", "en") -> Deduction function building envelope (excl. VAT) | N53: =_xlfn.TRANSLATE(F53,"de","en") -> Value Function Emergency Power
A54: MWSt. Investitionskosten PVA | B54: =_Vorsteuerabzug_Investitionskosten -> 0 | F54: MWSt. Investitionskosten Batterie | G54: =_Vorabzug_Investitionskosten_Batterie -> 0 | K54: =_xlfn.TRANSLATE(A54,"de", "en") -> VAT investment costs PVA | N54: =_xlfn.TRANSLATE(F54,"de","en") -> VAT investment costs battery
A55: Investition PVA für Wirtschaftlichkeit | B55: =_relevante_Investitionskosten -> 15344 | F55: Investition Batterie für Wirtschaftlichkeit | G55: =_relevante_Investitionskosten_Batterie -> 0 | K55: =_xlfn.TRANSLATE(A55,"de", "en") -> PVA investment for profitability | N55: =_xlfn.TRANSLATE(F55,"de","en") -> Investing in a battery for economic efficiency
K56: =_xlfn.TRANSLATE(A56,"de", "en") | N56: =_xlfn.TRANSLATE(F56,"de","en")
A57: Funktion Gebäudehülle | B57: =_Kosten_Funktion_GH -> 0 | K57: =_xlfn.TRANSLATE(A57,"de", "en") -> Building envelope function | N57: =_xlfn.TRANSLATE(F57,"de","en")
K58: =_xlfn.TRANSLATE(A58,"de", "en") | N58: =_xlfn.TRANSLATE(F58,"de","en")
A59: direkte Förderung | B59: =_direkteFörderung -> 0 | K59: =_xlfn.TRANSLATE(A59,"de", "en") -> Direct funding | N59: =_xlfn.TRANSLATE(F59,"de","en")
A60: Einmalvergütung (EIV) | B60: =_Einmalvergütung -> 0 | K60: =_xlfn.TRANSLATE(A60,"de", "en") -> One-off remuneration (EIV) | N60: =_xlfn.TRANSLATE(F60,"de","en")
A61: Fassadenbonus (FB) | B61: =_Fassadenbonus -> 0 | K61: =_xlfn.TRANSLATE(A61,"de", "en") -> Façade Bonus (FB) | N61: =_xlfn.TRANSLATE(F61,"de","en")
A62: Höhenbonus (HB) | B62: =_Höhenbonus -> 0 | K62: =_xlfn.TRANSLATE(A62,"de", "en") -> Altitude bonus (HB) | N62: =_xlfn.TRANSLATE(F62,"de","en")
A63: Parkflächenbonus (PB) | B63: =_Parkflächenbonus -> 0 | F63: Förderung Batteriespeicher | G63: =_Förderung_Batterie -> 0 | K63: =_xlfn.TRANSLATE(A63,"de", "en") -> Parking bonus (PB) | N63: =_xlfn.TRANSLATE(F63,"de","en") -> Funding for battery storage
A64: Total Fördergelder | B64: =SUM(B59:C63) -> 0 | F64: Total Fördergelder Batterie | G64: =SUM(G63) -> 0 | K64: =_xlfn.TRANSLATE(A64,"de", "en") -> Total Funding | N64: =_xlfn.TRANSLATE(F64,"de","en") -> Total Subsidies Battery
K65: =_xlfn.TRANSLATE(A65,"de", "en") | N65: =_xlfn.TRANSLATE(F65,"de","en")
A66: Auszahlungsfrist EIV und Boni | B66: =_ZahlungsfristEIVFB -> 1 | K66: =_xlfn.TRANSLATE(A66,"de", "en") -> Withdrawal period EIV and bonuses | N66: =_xlfn.TRANSLATE(F66,"de","en")
K67: =_xlfn.TRANSLATE(A67,"de", "en") | N67: =_xlfn.TRANSLATE(F67,"de","en")
A68: Steuereinsparungen | B68: =_Steuereinsparung -> 0 | K68: =_xlfn.TRANSLATE(A68,"de", "en") -> Tax savings | N68: =_xlfn.TRANSLATE(F68,"de","en")
K69: =_xlfn.TRANSLATE(A69,"de", "en") | N69: =_xlfn.TRANSLATE(F69,"de","en")
A70: Investition PVA netto | B70: =_Investition_netto -> 15344 | F70: Investition Batterie netto | G70: =_Investition_netto_Batterie -> 0 | K70: =_xlfn.TRANSLATE(A70,"de", "en") -> PVA net investment | N70: =_xlfn.TRANSLATE(F70,"de","en") -> Net battery investment
K71: =_xlfn.TRANSLATE(A71,"de", "en") | N71: =_xlfn.TRANSLATE(F71,"de","en")
A72: Kapitalstruktur | K72: =_xlfn.TRANSLATE(A72,"de", "en") -> Capital | N72: =_xlfn.TRANSLATE(F72,"de","en")
F73: Zinssatz: | H73: Laufzeit: | K73: =_xlfn.TRANSLATE(A73,"de", "en") | N73: =_xlfn.TRANSLATE(F73,"de","en") -> Interest rate:
A74: Eigenkapital PVA | B74: =_Eigenkapital -> 15344 | F74: =_Zins_Eigenkapital -> 0 | G74: % | H74: =_Anlagenlebensdauer -> 30 | I74: Jahre | K74: =_xlfn.TRANSLATE(A74,"de", "en") -> Equity PVA | N74: =_xlfn.TRANSLATE(F74,"de","en") -> 0
A75: Fremdkapital 1 PVA | B75: =_Fremdkapital1 -> 0 | F75: =_Zins_Fremdkapital1 -> 0 | G75: % | H75: =_Laufzeit_Fremdkapital1 -> 0 | I75: Jahre | K75: =_xlfn.TRANSLATE(A75,"de", "en") -> Debt 1 PVA | N75: =_xlfn.TRANSLATE(F75,"de","en") -> 0
A76: Fremdkapital 2 PVA | B76: =_Fremdkapital2 -> 0 | F76: =_Zins_Fremdkapital2 -> 0 | G76: % | H76: =_Laufzeit_Fremdkapital2 -> 0 | I76: Jahre | K76: =_xlfn.TRANSLATE(A76,"de", "en") -> Debt capital 2 PVA | N76: =_xlfn.TRANSLATE(F76,"de","en") -> 0
A77: Eigenkapital Batterie | B77: =_Eigenkapital_Batterie -> 0 | F77: =_Zins_Eigenkapital_Batterie -> 0 | G77: % | H77: =_Lebensdauer_Speicher -> 15 | I77: Jahre | K77: =_xlfn.TRANSLATE(A77,"de", "en") -> Equity Battery | N77: =_xlfn.TRANSLATE(F77,"de","en") -> 0
A78: Fremdkapital Batterie | B78: =_Fremdkapital_Batterie -> 0 | F78: =_Zins_Fremdkapital_Batterie -> 0 | G78: % | H78: =_Laufzeit_Fremdkapital_Batterie -> 0 | I78: Jahre | K78: =_xlfn.TRANSLATE(A78,"de", "en") -> Debt Capital Battery | N78: =_xlfn.TRANSLATE(F78,"de","en") -> 0
K79: =_xlfn.TRANSLATE(A79,"de", "en") | N79: =_xlfn.TRANSLATE(F79,"de","en")
A80: Betriebs- und Unterhaltsaufwand (alle Angaben inkl. MWSt.) | F80: ="Stromtarife " -> Stromtarife | K80: =_xlfn.TRANSLATE(A80,"de", "en") -> Operating and maintenance expenses (all figures incl. VAT) | N80: =_xlfn.TRANSLATE(F80,"de","en") -> Electricity tariffs
B81: Unterhaltskosten und Periodizität | K81: =_xlfn.TRANSLATE(A81,"de", "en") | N81: =_xlfn.TRANSLATE(F81,"de","en")
A82: Ø Unterhaltskosten PV- Anlage | B82: =IF(_Berechnungsart_Unterhaltskosten=_Unterhalt_Preis_pro_kWh,_spez_Unterhaltskosten,_Unterhaltskosten_Durchschnittlich) -> 0.19589935 | C82: CHF/kWh | F82: Abnahmevergütung | K82: =_xlfn.TRANSLATE(A82,"de", "en") -> Ø Maintenance costs of PV system | N82: =_xlfn.TRANSLATE(F82,"de","en") -> Purchase Fee
A83: Kontrollgänge | B83: =Eingaben!C114 -> 830.688 | C83: =Eingaben!F114 -> 5 | D83: Jahre | F83: ="Abnahmevergütung Energie "&Eingaben!E71 -> Abnahmevergütung Energie (inkl. MWSt.) | H83: =_Rückliefertarif_Energie -> 0.06 | I83: CHF/kWh | K83: =_xlfn.TRANSLATE(A83,"de", "en") -> Inspection rounds | N83: =_xlfn.TRANSLATE(F83,"de","en") -> Purchase Remuneration Energy (incl. VAT)
A84: Audits / Sicherheitsnachweise | B84: =Eingaben!C115 -> 0 | C84: =Eingaben!F115 -> 20 | D84: Jahre | F84: ="Herkunftsnachweis (HKN) "&Eingaben!E72 -> Herkunftsnachweis (HKN) (inkl. MWSt.) | H84: =_Herkunftsnachweis -> 0.02 | I84: CHF/kWh | K84: =_xlfn.TRANSLATE(A84,"de", "en") -> Audits / Safety Certificates | N84: =_xlfn.TRANSLATE(F84,"de","en") -> Guarantee of Origin (HKN) (incl. VAT)
A85: Überwachung | B85: =Eingaben!C116 -> 69 | C85: =Eingaben!F116 -> 1 | D85: Jahre | F85: ="Abnahmevergütung "&Eingaben!E72 -> Abnahmevergütung (inkl. MWSt.) | H85: =_Rückliefertarif -> 0.08 | I85: CHF/kWh | K85: =_xlfn.TRANSLATE(A85,"de", "en") -> Surveillance | N85: =_xlfn.TRANSLATE(F85,"de","en") -> Purchase remuneration (incl. VAT)
A86: Administration | B86: =Eingaben!C117 -> 99 | C86: =Eingaben!F117 -> 1 | D86: Jahre | K86: =_xlfn.TRANSLATE(A86,"de", "en") -> Administration | N86: =_xlfn.TRANSLATE(F86,"de","en")
A87: Datenverbindung | B87: =Eingaben!C118 -> 120 | C87: =Eingaben!F118 -> 1 | D87: Jahre | F87: ="Eigenverbrauch "&IF(_ZEV=_NEIN,"",IF(_ZEV=_JA,"in ZEV ","Fehler")) -> Eigenverbrauch in ZEV | K87: =_xlfn.TRANSLATE(A87,"de", "en") -> Data | N87: =_xlfn.TRANSLATE(F87,"de","en") -> Self-consumption in ZEV
A88: Versicherung | B88: =Eingaben!C119 -> 49.1008 | C88: =Eingaben!F119 -> 1 | D88: Jahre | F88: =IF(Eingaben!B49="","","Tariffestlegung basierend auf Stromprodukt: " & Eingaben!B49) | K88: =_xlfn.TRANSLATE(A88,"de", "en") -> Insurance | N88: =_xlfn.TRANSLATE(F88,"de","en")
A89: Reparaturen | B89: =Eingaben!C120 -> 1215.344 | C89: =Eingaben!F120 -> 8 | D89: Jahre | F89: =IF(_ZEV=_NEIN,"ersetzter Bezugstarif ",IF(_ZEV=_JA,"PV- Stromtarif ZEV ","Fehler"))&CHAR(10)&Eingaben!E47 -> PV- Stromtarif ZEV (exkl. MWSt.) | H89: =_ersetzterBezugstarifZEV -> 0.232 | I89: CHF/kWh | K89: =_xlfn.TRANSLATE(A89,"de", "en") -> Repairs | N89: =_xlfn.TRANSLATE(F89,"de","en") -> PV electricity tariff ZEV (excl. VAT)
A90: Reinigung Anlage | B90: =Eingaben!C121 -> 1056.25 | C90: =Eingaben!F121 -> 8 | D90: Jahre | F90: =IF(_ZEV=_NEIN,"ersetzter Leistungstarif ",IF(_ZEV=_JA,"PV- Leistungstarif ZEV ","Fehler"))&CHAR(10)&Eingaben!E47 -> PV- Leistungstarif ZEV (exkl. MWSt.) | H90: =_Leistungskosten_ZEV -> 1.5 | I90: CHF/kW/Monat | K90: =_xlfn.TRANSLATE(A90,"de", "en") -> Cleaning plant | N90: =_xlfn.TRANSLATE(F90,"de","en") -> PV power tariff ZEV (excl. VAT)
A91: Grünbewuchs Pflege | B91: =Eingaben!C122 -> 0 | C91: =Eingaben!F122 -> 1 | D91: Jahre | F91: ="Abrechnungskosten ZEV "&CHAR(10)&Eingaben!E50 -> Abrechnungskosten ZEV (exkl. MWSt.) | H91: =_Tarif_Abrechnung_ZEV -> 0 | I91: CHF/kWh | K91: =_xlfn.TRANSLATE(A91,"de", "en") -> Green Vegetation Care | N91: =_xlfn.TRANSLATE(F91,"de","en") -> Billing costs ZEV (excl. VAT)
A92: Transformator | B92: =Eingaben!C123 -> 0 | C92: =Eingaben!F123 -> 1 | D92: Jahre | F92: ="Grundkosten Abrechnung ZEV Teilnehmer "&CHAR(10)&Eingaben!E51 -> Grundkosten Abrechnung ZEV Teilnehmer (exkl. MWSt.) | H92: =_Grundkosten_Abrechnung_ZEV -> 8 | I92: CHF/Monat | K92: =_xlfn.TRANSLATE(A92,"de", "en") -> Transformer | N92: =_xlfn.TRANSLATE(F92,"de","en") -> Basic costs for ZEV participants (excl. VAT)
A93: Dach- / Raummiete | B93: =Eingaben!C124 -> 0 | C93: =Eingaben!F124 -> 1 | D93: Jahre | K93: =_xlfn.TRANSLATE(A93,"de", "en") -> Roof / room rental | N93: =_xlfn.TRANSLATE(F93,"de","en")
A94: Wechselrichteraustausch | B94: =Eingaben!C125 -> 1175 | C94: =Eingaben!F125 -> 16 | D94: Jahre | F94: Lokale Elektrizitätsgemeinschaft LEG | K94: =_xlfn.TRANSLATE(A94,"de", "en") -> Inverter replacement | N94: =_xlfn.TRANSLATE(F94,"de","en") -> Local Electricity Community LEG
F95: ="Nutzung der Netzebnenen "&Eingaben!C57 -> Nutzung der Netzebnenen NE 5 & 7 | K95: =_xlfn.TRANSLATE(A95,"de", "en") | N95: =_xlfn.TRANSLATE(F95,"de","en") -> Use of the NE 5 & 7 network levels
A96: Ø Unterhaltskosten Batteriespeicher | B96: =_Unterhaltskosten_Durschschnittlich_Batterie -> 0 | C96: CHF/kWh | F96: ="PV- Stromtarif LEG "&Eingaben!E60 -> PV- Stromtarif LEG (exkl. MWSt.) | H96: =_Tarif_LEG -> 0.096666667 | I96: CHF/kWh | K96: =_xlfn.TRANSLATE(A96,"de", "en") -> Ø Maintenance costs of battery storage | N96: =_xlfn.TRANSLATE(F96,"de","en") -> PV electricity tariff LEG (excl. VAT)
A97: Unterhaltskosten Batteriespeicher | B97: =Eingaben!C129 -> 0 | C97: =Eingaben!F129 -> 1 | D97: Jahre | F97: ="Abrechnungskosten LEG "&Eingaben!E61 -> Abrechnungskosten LEG (exkl. MWSt.) | H97: =_Abrechnungstarif_LEG -> 0.015 | I97: CHF/kWh | K97: =_xlfn.TRANSLATE(A97,"de", "en") -> Battery storage maintenance costs | N97: =_xlfn.TRANSLATE(F97,"de","en") -> Billing costs LEG (excl. VAT)
A98: Ersatz Batteriespeicher | B98: =Eingaben!C130 -> 0 | C98: =Eingaben!F130 -> 16 | D98: Jahre | F98: ="Tarif LEG Total "&Eingaben!E62 -> Tarif LEG Total (exkl. MWSt.) | H98: =_Tarif_LEG -> 0.096666667 | I98: CHF/kWh | K98: =_xlfn.TRANSLATE(A98,"de", "en") -> Replacement battery storage system | N98: =_xlfn.TRANSLATE(F98,"de","en") -> Tariff LEG Total (excl. VAT)
K99: =_xlfn.TRANSLATE(A99,"de", "en") | N99: =_xlfn.TRANSLATE(F99,"de","en")
A100: Betriebskosten ZEV (Admin und Abrechnung) | B100: =Eingaben!C53 -> 0 | C100: 1 | D100: Jahre | K100: =_xlfn.TRANSLATE(A100,"de", "en") -> Operating costs ZEV (admin and billing) | N100: =_xlfn.TRANSLATE(F100,"de","en")
...

Sheet Details
A1: Projektangaben
A2: Projektbezeichnung: | B2: =_Projektbezeichnung&", "&_Standort -> ,
A3: Projektnummer: | B3: =IF(ISNUMBER(_Projektnummer),_Projektnummer,"") | E3: Projektleiter: | G3: =IF(_Projektleiter<>"",_Projektleiter,"")
A4: Betreiber: | B4: =IF(_Betreiber<>"",_Betreiber,"") | E4: MWSt. Pflicht | G4: =_MWStPflicht -> MWSt. pflichtig
A6: Geldflussplan PV- Anlage (ohne Batteriespeicher) | E6: =_xlfn.TRANSLATE(A6,"de","en") -> Cash flow plan PV system (without battery storage)
A32: Sensitivitätsanalyse der Projektrendite ohne Batteriespeicher | E32: =_xlfn.TRANSLATE(A32,"de","en") -> Sensitivity analysis of the project return on investment without battery storage
D33: Abnahmevergütung
D34: =Eingaben!BB40 -> 0.8 | E34: =Eingaben!BC40 -> 0.9 | F34: =Eingaben!BD40 -> 1 | G34: =Eingaben!BE40 -> 1.1 | H34: =Eingaben!BF40 -> 1.2
A35: =_xlfn.TRANSLATE(A36,"de","en") -> Investment PV system | D35: =Eingaben!BB42*100 -> 6.4 | E35: =Eingaben!BC42*100 -> 7.2 | F35: =Eingaben!BD42*100 -> 8 | G35: =Eingaben!BE42*100 -> 8.8 | H35: =Eingaben!BF42*100 -> 9.6
A36: Investitionskosten PV- Anlage | B36: =Eingaben!AZ43 -> 1.2 | C36: =Eingaben!BA43 -> 18412.8 | D36: =IF(ISNUMBER(Eingaben!BB43/100),Eingaben!BB43/100,"--") -> -- | E36: =IF(ISNUMBER(Eingaben!BC43/100),Eingaben!BC43/100,"--") -> -- | F36: =IF(ISNUMBER(Eingaben!BD43/100),Eingaben!BD43/100,"--") -> -- | G36: =IF(ISNUMBER(Eingaben!BE43/100),Eingaben!BE43/100,"--") -> -- | H36: =IF(ISNUMBER(Eingaben!BF43/100),Eingaben!BF43/100,"--") -> --
B37: =Eingaben!AZ44 -> 1.1 | C37: =Eingaben!BA44 -> 16878.4 | D37: =IF(ISNUMBER(Eingaben!BB44/100),Eingaben!BB44/100,"--") -> -- | E37: =IF(ISNUMBER(Eingaben!BC44/100),Eingaben!BC44/100,"--") -> -- | F37: =IF(ISNUMBER(Eingaben!BD44/100),Eingaben!BD44/100,"--") -> -- | G37: =IF(ISNUMBER(Eingaben!BE44/100),Eingaben!BE44/100,"--") -> -- | H37: =IF(ISNUMBER(Eingaben!BF44/100),Eingaben!BF44/100,"--") -> --
B38: =Eingaben!AZ45 -> 1 | C38: =Eingaben!BA45 -> 15344 | D38: =IF(ISNUMBER(Eingaben!BB45/100),Eingaben!BB45/100,"--") -> -- | E38: =IF(ISNUMBER(Eingaben!BC45/100),Eingaben!BC45/100,"--") -> -- | F38: =IF(ISNUMBER(Eingaben!BD45/100),Eingaben!BD45/100,"--") -> -- | G38: =IF(ISNUMBER(Eingaben!BE45/100),Eingaben!BE45/100,"--") -> -- | H38: =IF(ISNUMBER(Eingaben!BF45/100),Eingaben!BF45/100,"--") -> --
B39: =Eingaben!AZ46 -> 0.9 | C39: =Eingaben!BA46 -> 13809.6 | D39: =IF(ISNUMBER(Eingaben!BB46/100),Eingaben!BB46/100,"--") -> -- | E39: =IF(ISNUMBER(Eingaben!BC46/100),Eingaben!BC46/100,"--") -> -- | F39: =IF(ISNUMBER(Eingaben!BD46/100),Eingaben!BD46/100,"--") -> -- | G39: =IF(ISNUMBER(Eingaben!BE46/100),Eingaben!BE46/100,"--") -> -- | H39: =IF(ISNUMBER(Eingaben!BF46/100),Eingaben!BF46/100,"--") -> --
B40: =Eingaben!AZ47 -> 0.8 | C40: =Eingaben!BA47 -> 12275.2 | D40: =IF(ISNUMBER(Eingaben!BB47/100),Eingaben!BB47/100,"--") -> -- | E40: =IF(ISNUMBER(Eingaben!BC47/100),Eingaben!BC47/100,"--") -> -- | F40: =IF(ISNUMBER(Eingaben!BD47/100),Eingaben!BD47/100,"--") -> -- | G40: =IF(ISNUMBER(Eingaben!BE47/100),Eingaben!BE47/100,"--") -> -- | H40: =IF(ISNUMBER(Eingaben!BF47/100),Eingaben!BF47/100,"--") -> --
D42: Teuerung auf Energie und Unterhaltskosten
A43: =_xlfn.TRANSLATE(A44,"de","en") -> Lifetime | D43: =Eingaben!BB19/100 -> 0 | E43: =Eingaben!BC19/100 -> 0.005 | F43: =Eingaben!BD19/100 -> 0.01 | G43: =Eingaben!BE19/100 -> 0.02 | H43: =Eingaben!BF19/100 -> 0.03
A44: Lebensdauer | B44: =Eingaben!BA20 -> 25 | D44: =IF(ISNUMBER(Eingaben!BB20/100),Eingaben!BB20/100,"--") -> -- | E44: =IF(ISNUMBER(Eingaben!BC20/100),Eingaben!BC20/100,"--") -> -- | F44: =IF(ISNUMBER(Eingaben!BD20/100),Eingaben!BD20/100,"--") -> -- | G44: =IF(ISNUMBER(Eingaben!BE20/100),Eingaben!BE20/100,"--") -> -- | H44: =IF(ISNUMBER(Eingaben!BF20/100),Eingaben!BF20/100,"--") -> --
B45: =Eingaben!BA21 -> 30 | D45: =IF(ISNUMBER(Eingaben!BB21/100),Eingaben!BB21/100,"--") -> -- | E45: =IF(ISNUMBER(Eingaben!BC21/100),Eingaben!BC21/100,"--") -> -- | F45: =IF(ISNUMBER(Eingaben!BD21/100),Eingaben!BD21/100,"--") -> -- | G45: =IF(ISNUMBER(Eingaben!BE21/100),Eingaben!BE21/100,"--") -> -- | H45: =IF(ISNUMBER(Eingaben!BF21/100),Eingaben!BF21/100,"--") -> --
B46: =Eingaben!BA22 -> 35 | D46: =IF(ISNUMBER(Eingaben!BB22/100),Eingaben!BB22/100,"--") -> -- | E46: =IF(ISNUMBER(Eingaben!BC22/100),Eingaben!BC22/100,"--") -> -- | F46: =IF(ISNUMBER(Eingaben!BD22/100),Eingaben!BD22/100,"--") -> -- | G46: =IF(ISNUMBER(Eingaben!BE22/100),Eingaben!BE22/100,"--") -> -- | H46: =IF(ISNUMBER(Eingaben!BF22/100),Eingaben!BF22/100,"--") -> --
B47: =Eingaben!BA23 -> 40 | D47: =IF(ISNUMBER(Eingaben!BB23/100),Eingaben!BB23/100,"--") -> -- | E47: =IF(ISNUMBER(Eingaben!BC23/100),Eingaben!BC23/100,"--") -> -- | F47: =IF(ISNUMBER(Eingaben!BD23/100),Eingaben!BD23/100,"--") -> -- | G47: =IF(ISNUMBER(Eingaben!BE23/100),Eingaben!BE23/100,"--") -> -- | H47: =IF(ISNUMBER(Eingaben!BF23/100),Eingaben!BF23/100,"--") -> --
D49: =IF(_ZEV=_NEIN,"ersetzter Bezugstarif ",IF(_ZEV=_JA,"PV- Stromtarif ZEV ","Fehler"))&CHAR(10)&Eingaben!E47 -> PV- Stromtarif ZEV (exkl. MWSt.)
D50: =Eingaben!BB29 -> 0.8 | E50: =Eingaben!BC29 -> 0.9 | F50: =Eingaben!BD29 -> 1 | G50: =Eingaben!BE29 -> 1.1 | H50: =Eingaben!BF29 -> 1.2
A51: =_xlfn.TRANSLATE(A52,"de","en") -> Self-consumption without battery storage | D51: =Eingaben!BB30*100 -> 18.56 | E51: =Eingaben!BC30*100 -> 20.88 | F51: =Eingaben!BD30*100 -> 23.2 | G51: =Eingaben!BE30*100 -> 25.52 | H51: =Eingaben!BF30*100 -> 27.84
A52: Eigenverbrauch ohne Batteriespeicher | B52: =Eingaben!BA31/100 -> 0.23270424 | D52: =IF(ISNUMBER(Eingaben!BB31/100),Eingaben!BB31/100,"--") -> -- | E52: =IF(ISNUMBER(Eingaben!BC31/100),Eingaben!BC31/100,"--") -> -- | F52: =IF(ISNUMBER(Eingaben!BD31/100),Eingaben!BD31/100,"--") -> -- | G52: =IF(ISNUMBER(Eingaben!BE31/100),Eingaben!BE31/100,"--") -> -- | H52: =IF(ISNUMBER(Eingaben!BF31/100),Eingaben!BF31/100,"--") -> --
B53: =Eingaben!BA32/100 -> 0.28270424 | D53: =IF(ISNUMBER(Eingaben!BB32/100),Eingaben!BB32/100,"--") -> -- | E53: =IF(ISNUMBER(Eingaben!BC32/100),Eingaben!BC32/100,"--") -> -- | F53: =IF(ISNUMBER(Eingaben!BD32/100),Eingaben!BD32/100,"--") -> -- | G53: =IF(ISNUMBER(Eingaben!BE32/100),Eingaben!BE32/100,"--") -> -- | H53: =IF(ISNUMBER(Eingaben!BF32/100),Eingaben!BF32/100,"--") -> --
B54: =Eingaben!BA33/100 -> 0.33270424 | D54: =IF(ISNUMBER(Eingaben!BB33/100),Eingaben!BB33/100,"--") -> -- | E54: =IF(ISNUMBER(Eingaben!BC33/100),Eingaben!BC33/100,"--") -> -- | F54: =IF(ISNUMBER(Eingaben!BD33/100),Eingaben!BD33/100,"--") -> -- | G54: =IF(ISNUMBER(Eingaben!BE33/100),Eingaben!BE33/100,"--") -> -- | H54: =IF(ISNUMBER(Eingaben!BF33/100),Eingaben!BF33/100,"--") -> --
B55: =Eingaben!BA34/100 -> 0.38270424 | D55: =IF(ISNUMBER(Eingaben!BB34/100),Eingaben!BB34/100,"--") -> -- | E55: =IF(ISNUMBER(Eingaben!BC34/100),Eingaben!BC34/100,"--") -> -- | F55: =IF(ISNUMBER(Eingaben!BD34/100),Eingaben!BD34/100,"--") -> -- | G55: =IF(ISNUMBER(Eingaben!BE34/100),Eingaben!BE34/100,"--") -> -- | H55: =IF(ISNUMBER(Eingaben!BF34/100),Eingaben!BF34/100,"--") -> --
B56: =Eingaben!BA35/100 -> 0.43270424 | D56: =IF(ISNUMBER(Eingaben!BB35/100),Eingaben!BB35/100,"--") -> -- | E56: =IF(ISNUMBER(Eingaben!BC35/100),Eingaben!BC35/100,"--") -> -- | F56: =IF(ISNUMBER(Eingaben!BD35/100),Eingaben!BD35/100,"--") -> -- | G56: =IF(ISNUMBER(Eingaben!BE35/100),Eingaben!BE35/100,"--") -> -- | H56: =IF(ISNUMBER(Eingaben!BF35/100),Eingaben!BF35/100,"--") -> --
A58: Sensitivitätsanalyse der Projektrendite PV- Anlage mit Batteriespeicher | E58: =_xlfn.TRANSLATE(A58,"de","en") -> Sensitivity analysis of the project return on PV system with battery storage
D59: =IF(_ZEV=_NEIN,"ersetzter Bezugstarif ",IF(_ZEV=_JA,"PV- Stromtarif ZEV ","Fehler"))&CHAR(10)&Eingaben!E47 -> PV- Stromtarif ZEV (exkl. MWSt.)
D60: =Eingaben!BB55 -> 0.8 | E60: =Eingaben!BC55 -> 0.9 | F60: =Eingaben!BD55 -> 1 | G60: =Eingaben!BE55 -> 1.1 | H60: =Eingaben!BF55 -> 1.2
A61: =_xlfn.TRANSLATE(A62,"de","en") -> Investment Battery storage | D61: =Eingaben!BB56*100 -> 18.56 | E61: =Eingaben!BC56*100 -> 20.88 | F61: =Eingaben!BD56*100 -> 23.2 | G61: =Eingaben!BE56*100 -> 25.52 | H61: =Eingaben!BF56*100 -> 27.84
A62: Investitionskosten Batteriespeicher | B62: =Eingaben!AZ57 -> 1.2 | C62: =Eingaben!BA57 -> 0 | D62: =IF(ISNUMBER(Eingaben!BB57/100),Eingaben!BB57/100,"--") -> -- | E62: =IF(ISNUMBER(Eingaben!BC57/100),Eingaben!BC57/100,"--") -> -- | F62: =IF(ISNUMBER(Eingaben!BD57/100),Eingaben!BD57/100,"--") -> -- | G62: =IF(ISNUMBER(Eingaben!BE57/100),Eingaben!BE57/100,"--") -> -- | H62: =IF(ISNUMBER(Eingaben!BF57/100),Eingaben!BF57/100,"--") -> --
B63: =Eingaben!AZ58 -> 1.1 | C63: =Eingaben!BA58 -> 0 | D63: =IF(ISNUMBER(Eingaben!BB58/100),Eingaben!BB58/100,"--") -> -- | E63: =IF(ISNUMBER(Eingaben!BC58/100),Eingaben!BC58/100,"--") -> -- | F63: =IF(ISNUMBER(Eingaben!BD58/100),Eingaben!BD58/100,"--") -> -- | G63: =IF(ISNUMBER(Eingaben!BE58/100),Eingaben!BE58/100,"--") -> -- | H63: =IF(ISNUMBER(Eingaben!BF58/100),Eingaben!BF58/100,"--") -> --
B64: =Eingaben!AZ59 -> 1 | C64: =Eingaben!BA59 -> 0 | D64: =IF(ISNUMBER(Eingaben!BB59/100),Eingaben!BB59/100,"--") -> -- | E64: =IF(ISNUMBER(Eingaben!BC59/100),Eingaben!BC59/100,"--") -> -- | F64: =IF(ISNUMBER(Eingaben!BD59/100),Eingaben!BD59/100,"--") -> -- | G64: =IF(ISNUMBER(Eingaben!BE59/100),Eingaben!BE59/100,"--") -> -- | H64: =IF(ISNUMBER(Eingaben!BF59/100),Eingaben!BF59/100,"--") -> --
B65: =Eingaben!AZ60 -> 0.9 | C65: =Eingaben!BA60 -> 0 | D65: =IF(ISNUMBER(Eingaben!BB60/100),Eingaben!BB60/100,"--") -> -- | E65: =IF(ISNUMBER(Eingaben!BC60/100),Eingaben!BC60/100,"--") -> -- | F65: =IF(ISNUMBER(Eingaben!BD60/100),Eingaben!BD60/100,"--") -> -- | G65: =IF(ISNUMBER(Eingaben!BE60/100),Eingaben!BE60/100,"--") -> -- | H65: =IF(ISNUMBER(Eingaben!BF60/100),Eingaben!BF60/100,"--") -> --
B66: =Eingaben!AZ61 -> 0.8 | C66: =Eingaben!BA61 -> 0 | D66: =IF(ISNUMBER(Eingaben!BB61/100),Eingaben!BB61/100,"--") -> -- | E66: =IF(ISNUMBER(Eingaben!BC61/100),Eingaben!BC61/100,"--") -> -- | F66: =IF(ISNUMBER(Eingaben!BD61/100),Eingaben!BD61/100,"--") -> -- | G66: =IF(ISNUMBER(Eingaben!BE61/100),Eingaben!BE61/100,"--") -> -- | H66: =IF(ISNUMBER(Eingaben!BF61/100),Eingaben!BF61/100,"--") -> --
A68: Sensitivitätsanalyse der Projektrendite nur Batteriespeicher | E68: =_xlfn.TRANSLATE(A68,"de","en") -> Sensitivity analysis of the project return on battery storage only
D69: =IF(_ZEV=_NEIN,"ersetzter Bezugstarif ",IF(_ZEV=_JA,"PV- Stromtarif ZEV ","Fehler"))&CHAR(10)&Eingaben!E47 -> PV- Stromtarif ZEV (exkl. MWSt.)
D70: =Eingaben!BB64 -> 0.8 | E70: =Eingaben!BC64 -> 0.9 | F70: =Eingaben!BD64 -> 1 | G70: =Eingaben!BE64 -> 1.1 | H70: =Eingaben!BF64 -> 1.2
A71: =_xlfn.TRANSLATE(A72,"de","en") -> Investment Battery storage | D71: =Eingaben!BB65*100 -> 18.56 | E71: =Eingaben!BC65*100 -> 20.88 | F71: =Eingaben!BD65*100 -> 23.2 | G71: =Eingaben!BE65*100 -> 25.52 | H71: =Eingaben!BF65*100 -> 27.84
A72: Investitionskosten Batteriespeicher | B72: =Eingaben!AZ66 -> 1.2 | C72: =Eingaben!BA66 -> 0 | D72: =IF(ISNUMBER(Eingaben!BB66/100),Eingaben!BB66/100,"--") -> -- | E72: =IF(ISNUMBER(Eingaben!BC66/100),Eingaben!BC66/100,"--") -> -- | F72: =IF(ISNUMBER(Eingaben!BD66/100),Eingaben!BD66/100,"--") -> -- | G72: =IF(ISNUMBER(Eingaben!BE66/100),Eingaben!BE66/100,"--") -> -- | H72: =IF(ISNUMBER(Eingaben!BF66/100),Eingaben!BF66/100,"--") -> --
B73: =Eingaben!AZ67 -> 1.1 | C73: =Eingaben!BA67 -> 0 | D73: =IF(ISNUMBER(Eingaben!BB67/100),Eingaben!BB67/100,"--") -> -- | E73: =IF(ISNUMBER(Eingaben!BC67/100),Eingaben!BC67/100,"--") -> -- | F73: =IF(ISNUMBER(Eingaben!BD67/100),Eingaben!BD67/100,"--") -> -- | G73: =IF(ISNUMBER(Eingaben!BE67/100),Eingaben!BE67/100,"--") -> -- | H73: =IF(ISNUMBER(Eingaben!BF67/100),Eingaben!BF67/100,"--") -> --
B74: =Eingaben!AZ68 -> 1 | C74: =Eingaben!BA68 -> 0 | D74: =IF(ISNUMBER(Eingaben!BB68/100),Eingaben!BB68/100,"--") -> -- | E74: =IF(ISNUMBER(Eingaben!BC68/100),Eingaben!BC68/100,"--") -> -- | F74: =IF(ISNUMBER(Eingaben!BD68/100),Eingaben!BD68/100,"--") -> -- | G74: =IF(ISNUMBER(Eingaben!BE68/100),Eingaben!BE68/100,"--") -> -- | H74: =IF(ISNUMBER(Eingaben!BF68/100),Eingaben!BF68/100,"--") -> --
B75: =Eingaben!AZ69 -> 0.9 | C75: =Eingaben!BA69 -> 0 | D75: =IF(ISNUMBER(Eingaben!BB69/100),Eingaben!BB69/100,"--") -> -- | E75: =IF(ISNUMBER(Eingaben!BC69/100),Eingaben!BC69/100,"--") -> -- | F75: =IF(ISNUMBER(Eingaben!BD69/100),Eingaben!BD69/100,"--") -> -- | G75: =IF(ISNUMBER(Eingaben!BE69/100),Eingaben!BE69/100,"--") -> -- | H75: =IF(ISNUMBER(Eingaben!BF69/100),Eingaben!BF69/100,"--") -> --
B76: =Eingaben!AZ70 -> 0.8 | C76: =Eingaben!BA70 -> 0 | D76: =IF(ISNUMBER(Eingaben!BB70/100),Eingaben!BB70/100,"--") -> -- | E76: =IF(ISNUMBER(Eingaben!BC70/100),Eingaben!BC70/100,"--") -> -- | F76: =IF(ISNUMBER(Eingaben!BD70/100),Eingaben!BD70/100,"--") -> -- | G76: =IF(ISNUMBER(Eingaben!BE70/100),Eingaben!BE70/100,"--") -> -- | H76: =IF(ISNUMBER(Eingaben!BF70/100),Eingaben!BF70/100,"--") -> --

Sheet Eingaben
A1: Eingaben Wirtschaftlichkeitsberechnung | B1: Mindestens notwendige Definitionen für eine Berechnung | I1: HS Defaultwert 1 | J1: HS Defaultwert 2 | K1: HS Minimalwert | L1: HS Maximalwert | N1: gewähltes Beispiel | O1: =_xlfn.TRANSLATE(N1,"de","en") -> Example chosen | Q1: =Listen!G4 -> Beispiel 1 | T1: =Listen!G5 -> Beispiel 2 | W1: =Listen!G6 -> Beispiel 3 | Z1: =Listen!G7 -> Beispiel 4 | AC1: =Listen!G8 -> Beispiel 5 | AF1: =Listen!G9 -> Beispiel 6 | AI1: =Listen!G10 -> Beispiel 7 | AL1: =Listen!G11 -> Beispiel 8 | AQ1: =_xlfn.TRANSLATE(A1,"de","en") -> Inputs Profitability Calculation | AY1: HS Sensitivitätsanalyse
A2: =IF(_Debug_Modus=_JA,"DEBUG MODUS AKTIV","") | I2: =_xlfn.TRANSLATE(I1,"de","en") -> HS Default Value 1 | J2: =_xlfn.TRANSLATE(J1,"de","en") -> HS Default Value 2 | K2: =_xlfn.TRANSLATE(K1,"de","en") -> HS Minimum Value | L2: =_xlfn.TRANSLATE(L1,"de","en") -> HS Maximum Value | N2: Aktivierung Debug Modus mit Beispielen | O2: NEIN | R2: =Q1 -> Beispiel 1 | U2: =T1 -> Beispiel 2 | X2: =W1 -> Beispiel 3 | AA2: =Z1 -> Beispiel 4 | AD2: =AC1 -> Beispiel 5 | AG2: =AF1 -> Beispiel 6 | AJ2: =AI1 -> Beispiel 7 | AM2: =AL1 -> Beispiel 8 | AQ2: =_xlfn.TRANSLATE(A2,"de","en")
A3: Projektangaben | I3: =_xlfn.TRANSLATE(A3,"de","en") -> Project information | N3: Auswahl vom Beispiel | O3: Beispiel 4 | S3: =R2 -> Beispiel 1 | V3: =U2 -> Beispiel 2 | Y3: =X2 -> Beispiel 3 | AB3: =AA2 -> Beispiel 4 | AE3: =AD2 -> Beispiel 5 | AH3: =AG2 -> Beispiel 6 | AK3: =AJ2 -> Beispiel 7 | AN3: =AM2 -> Beispiel 8 | AQ3: =_xlfn.TRANSLATE(A3,"de","en") -> Project information
A4: Betreiber / Investor | I4: =_xlfn.TRANSLATE(A4,"de","en") -> Operator / Investor | N4: =_xlfn.TRANSLATE(N3,"de","en") -> Selection of the example | AQ4: =_xlfn.TRANSLATE(A4,"de","en") -> Operator / Investor
A5: MWSt. pflichtig | B5: MWSt. pflichtig | F5: 8.1 | G5: % MWSt. | I5: =_xlfn.TRANSLATE(A5,"de","en") -> Subject to VAT | AQ5: =_xlfn.TRANSLATE(A5,"de","en") -> Subject to VAT
A6: Standort | I6: =_xlfn.TRANSLATE(A6,"de","en") -> Location | AQ6: =_xlfn.TRANSLATE(A6,"de","en") -> Location
A7: Projektbezeichnung | I7: =_xlfn.TRANSLATE(A7,"de","en") -> Project name | AQ7: =_xlfn.TRANSLATE(A7,"de","en") -> Project name
A8: Projektnummer | I8: =_xlfn.TRANSLATE(A8,"de","en") -> Project number | AQ8: =_xlfn.TRANSLATE(A8,"de","en") -> Project number
A9: Projektleiter | I9: =_xlfn.TRANSLATE(A9,"de","en") -> Project manager | AQ9: =_xlfn.TRANSLATE(A9,"de","en") -> Project manager
A10: Netzbetreiber | I10: =_xlfn.TRANSLATE(A10,"de","en") -> Common carrier | AQ10: =_xlfn.TRANSLATE(A10,"de","en") -> Common carrier
A11: Bemerkungen | I11: =_xlfn.TRANSLATE(A11,"de","en") -> Remarks | Q11: Dachsanierung Schrägdach 10 kWp mit Speicher, ohne ZEV, ohne LEG | T11: Dachsanierung Schrägdach 10 kWp ohne Speicher, ohne ZEV, ohne LEG | W11: Flachdach 90 kWp mit Speicher, ohne ZEV, ohne LEG | Z11: Flachdach 90 kWp ohne Speicher, mit ZEV, ohne LEG | AC11: Flachdach 90 kWp mit Speicher, mit ZEV, mit LEG | AQ11: =_xlfn.TRANSLATE(A11,"de","en") -> Remarks
A12: Teuerungsrate (inflation rate) | B12: 0.5 | C12: =IF(B12="",I12,B12) -> 0.5 | D12: %/Jahr | E12: (Wird angewendet auf alle jährlichen Einnahmen und Ausgaben) (Applies to all annual income and expenses) | I12: 0.5 | AQ12: =_xlfn.TRANSLATE(A12,"de","en") -> Inflation rate
AQ13: =_xlfn.TRANSLATE(A13,"de","en")
B14: Eingabewert | C14: Rechenwert | AQ14: =_xlfn.TRANSLATE(A14,"de","en") | AU14: Beschreibung des vorgeschlagenen Rechenwertes | AW14: =_xlfn.TRANSLATE(AU14,"de","en") -> Description of the proposed calculation value
A15: Anlagedaten PVA | E15: Hilfsberechnung über Modulleistung | H15: =_xlfn.TRANSLATE(E15,"De","En") -> Auxiliary calculation via module power | N15: =IF(_xlfn.XLOOKUP($O$3,$Q$1:$AN$1,Q15:AN15,"-",0,1)<>"",_xlfn.XLOOKUP($O$3,$Q$1:$AN$1,Q15:AN15,"-",0,1),"") | O15: =IF(_xlfn.XLOOKUP($O$3,$Q$2:$AN$2,Q15:AN15,"-",0,1)<>"",_xlfn.XLOOKUP($O$3,$Q$2:$AN$2,Q15:AN15,"-",0,1),"") | P15: =IF(_xlfn.XLOOKUP($O$3,$Q$3:$AN$3,Q15:AN15,"-",0,1)<>"",_xlfn.XLOOKUP($O$3,$Q$3:$AN$3,Q15:AN15,"-",0,1),"") | AQ15: =_xlfn.TRANSLATE(A15,"de","en") -> System data PVA | AW15: =_xlfn.TRANSLATE(AU15,"de","en") | AY15: Sensitivitätsanalyse Laufzeit und Teuerung [%]
A16: Anlagekategorie | B16: Dach integriert | E16: Anzahl (number) | F16: Leistung (Wp) | G16: (Resultat wird als Rechenwert für die Anlagenleistung übernommen) | N16: =IF(_xlfn.XLOOKUP($O$3,$Q$1:$AN$1,Q16:AN16,"-",0,1)<>"",_xlfn.XLOOKUP($O$3,$Q$1:$AN$1,Q16:AN16,"-",0,1),"") -> Dach Angebaut | O16: =IF(_xlfn.XLOOKUP($O$3,$Q$2:$AN$2,Q16:AN16,"-",0,1)<>"",_xlfn.XLOOKUP($O$3,$Q$2:$AN$2,Q16:AN16,"-",0,1),"") | P16: =IF(_xlfn.XLOOKUP($O$3,$Q$3:$AN$3,Q16:AN16,"-",0,1)<>"",_xlfn.XLOOKUP($O$3,$Q$3:$AN$3,Q16:AN16,"-",0,1),"") | Q16: Dach Angebaut | T16: Dach Integriert | W16: Dach Angebaut | Z16: Dach Angebaut | AC16: Dach Angebaut | AQ16: =_xlfn.TRANSLATE(A16,"de","en") -> Investment category | AW16: =_xlfn.TRANSLATE(AU16,"de","en")
A17: Anlagenennleistung | C17: =IF(B17="",IF(AND(_Debug_Modus=_JA,N17<>""),N17,I17),B17) -> 4.5 | D17: kWp | E17: 10 | F17: 450 | G17: =E17*F17/1000 -> 4.5 | I17: =G17 -> 4.5 | N17: =IF(_xlfn.XLOOKUP($O$3,$Q$1:$AN$1,Q17:AN17,"-",0,1)<>"",_xlfn.XLOOKUP($O$3,$Q$1:$AN$1,Q17:AN17,"-",0,1),"") -> 90.16 | O17: =IF(_xlfn.XLOOKUP($O$3,$Q$2:$AN$2,Q17:AN17,"-",0,1)<>"",_xlfn.XLOOKUP($O$3,$Q$2:$AN$2,Q17:AN17,"-",0,1),"") | P17: =IF(_xlfn.XLOOKUP($O$3,$Q$3:$AN$3,Q17:AN17,"-",0,1)<>"",_xlfn.XLOOKUP($O$3,$Q$3:$AN$3,Q17:AN17,"-",0,1),"") | Q17: 10.01 | T17: 10.01 | W17: 90.16 | Z17: 90.16 | AC17: 90.16 | AQ17: =_xlfn.TRANSLATE(A17,"de","en") -> Nominal plant capacity | AW17: =_xlfn.TRANSLATE(AU17,"de","en") | AY17: Projektrendite ohne Batterie in %
A18: Fläche PV- Anlage | C18: =IF(B18="",IF(AND(_Debug_Modus=_JA,N18<>""),N18,I18),B18) -> 18.75 | D18: m2 | I18: =_Anlagenleistung/0.24 -> 18.75 | N18: =IF(_xlfn.XLOOKUP($O$3,$Q$1:$AN$1,Q18:AN18,"-",0,1)<>"",_xlfn.XLOOKUP($O$3,$Q$1:$AN$1,Q18:AN18,"-",0,1),"") | O18: =IF(_xlfn.XLOOKUP($O$3,$Q$2:$AN$2,Q18:AN18,"-",0,1)<>"",_xlfn.XLOOKUP($O$3,$Q$2:$AN$2,Q18:AN18,"-",0,1),"") | P18: =IF(_xlfn.XLOOKUP($O$3,$Q$3:$AN$3,Q18:AN18,"-",0,1)<>"",_xlfn.XLOOKUP($O$3,$Q$3:$AN$3,Q18:AN18,"-",0,1),"") | T18: 50 | AQ18: =_xlfn.TRANSLATE(A18,"de","en") -> Area of PV system | AU18: Fläche wird berechnet mit 240 W/m2 | AW18: =_xlfn.TRANSLATE(AU18,"de","en") -> Area is calculated as 240 W/m2 | BB18: Teuerung auf Energie und Unterhaltskosten [%]
A19: Inbetriebnahmejahr | C19: =IF(IF(B19="",IF(AND(_Debug_Modus=_JA,N19<>""),N19,I19),B19)<K19,K19,IF(IF(B19="",IF(AND(_Debug_Modus=_JA,N19<>""),N19,I19),B19)>L19,L19,IF(B19="",IF(AND(_Debug_Modus=_JA,N19<>""),N19,I19),B19))) -> 2025 | I19: =YEAR(TODAY()) -> 2025 | K19: 2022 | L19: 2100 | N19: =IF(_xlfn.XLOOKUP($O$3,$Q$1:$AN$1,Q19:AN19,"-",0,1)<>"",_xlfn.XLOOKUP($O$3,$Q$1:$AN$1,Q19:AN19,"-",0,1),"") | O19: =IF(_xlfn.XLOOKUP($O$3,$Q$2:$AN$2,Q19:AN19,"-",0,1)<>"",_xlfn.XLOOKUP($O$3,$Q$2:$AN$2,Q19:AN19,"-",0,1),"") | P19: =IF(_xlfn.XLOOKUP($O$3,$Q$3:$AN$3,Q19:AN19,"-",0,1)<>"",_xlfn.XLOOKUP($O$3,$Q$3:$AN$3,Q19:AN19,"-",0,1),"") | AQ19: =_xlfn.TRANSLATE(A19,"de","en") -> Year of commissioning | AU19: immer aktuelles Jahr | AW19: =_xlfn.TRANSLATE(AU19,"de","en") -> always current year | BA19: =_Projektrendite -> -- | BB19: 0 | BC19: 0.5 | BD19: 1 | BE19: 2 | BF19: 3
A20: Anlagenlebensdauer | C20: =IF(IF(B20="",IF(AND(_Debug_Modus=_JA,N20<>""),N20,I20),B20)<K20,K20,IF(IF(B20="",IF(AND(_Debug_Modus=_JA,N20<>""),N20,I20),B20)>L20,L20,IF(B20="",IF(AND(_Debug_Modus=_JA,N20<>""),N20,I20),B20))) -> 30 | D20: Jahre | I20: 30 | K20: 0 | L20: 45 | N20: =IF(_xlfn.XLOOKUP($O$3,$Q$1:$AN$1,Q20:AN20,"-",0,1)<>"",_xlfn.XLOOKUP($O$3,$Q$1:$AN$1,Q20:AN20,"-",0,1),"") -> 25 | O20: =IF(_xlfn.XLOOKUP($O$3,$Q$2:$AN$2,Q20:AN20,"-",0,1)<>"",_xlfn.XLOOKUP($O$3,$Q$2:$AN$2,Q20:AN20,"-",0,1),"") | P20: =IF(_xlfn.XLOOKUP($O$3,$Q$3:$AN$3,Q20:AN20,"-",0,1)<>"",_xlfn.XLOOKUP($O$3,$Q$3:$AN$3,Q20:AN20,"-",0,1),"") | T20: 30 | W20: 25 | Z20: 25 | AC20: 25 | AQ20: =_xlfn.TRANSLATE(A20,"de","en") -> System service life | AU20: Fixe Annahme von 30 Jahren gemäss Erfahrungswerten | AW20: =_xlfn.TRANSLATE(AU20,"de","en") -> Fixed assumption of 30 years according to empirical values | AY20: Laufzeit [Jahre] | BA20: 25 | BB20: -- | BC20: -- | BD20: -- | BE20: -- | BF20: --
A21: spez. Jahresenergieertrag | C21: =IF(B21="",IF(AND(_Debug_Modus=_JA,N21<>""),N21,I21),B21) -> 1000 | D21: kWh/kWp | E21: (Im 1. Betriebsjahr) | I21: =IF(OR(_Anlagekategorie=_Fassade_angebaut,_Anlagekategorie=_Fassade_integriert),800,1000) -> 1000 | N21: =IF(_xlfn.XLOOKUP($O$3,$Q$1:$AN$1,Q21:AN21,"-",0,1)<>"",_xlfn.XLOOKUP($O$3,$Q$1:$AN$1,Q21:AN21,"-",0,1),"") -> 950 | O21: =IF(_xlfn.XLOOKUP($O$3,$Q$2:$AN$2,Q21:AN21,"-",0,1)<>"",_xlfn.XLOOKUP($O$3,$Q$2:$AN$2,Q21:AN21,"-",0,1),"") | P21: =IF(_xlfn.XLOOKUP($O$3,$Q$3:$AN$3,Q21:AN21,"-",0,1)<>"",_xlfn.XLOOKUP($O$3,$Q$3:$AN$3,Q21:AN21,"-",0,1),"") | Q21: 950 | T21: 950 | W21: 950 | Z21: 950 | AC21: 950 | AQ21: =_xlfn.TRANSLATE(A21,"de","en") -> spec. Annual energy yield | AU21: durchschnittlicher spez. Jahresertrag von 1'000 kWh/kWp ohne Berücksichtigung von Standort, Ausrichtung, Neigung und Verschattung | AW21: =_xlfn.TRANSLATE(AU21,"de","en") -> Average Spec. Annual yield of 1,000 kWh/kWp without taking into account location, orientation, inclination and shading | BA21: 30 | BB21: -- | BC21: -- | BD21: -- | BE21: -- | BF21: --
A22: Jahresenergieertrag | C22: =_Anlagenleistung*_spez_Jahresenergieertrag -> 4500 | D22: kWh | E22: (Im 1. Betriebsjahr) | AQ22: =_xlfn.TRANSLATE(A22,"de","en") -> Annual energy yield | AW22: =_xlfn.TRANSLATE(AU22,"de","en") | BA22: 35 | BB22: -- | BC22: -- | BD22: -- | BE22: -- | BF22: --
A23: Degradation | C23: =IF(B23="",IF(AND(_Debug_Modus=_JA,N23<>""),N23,I23),B23) -> 0.4 | D23: %/Jahr | I23: 0.4 | N23: =IF(_xlfn.XLOOKUP($O$3,$Q$1:$AN$1,Q23:AN23,"-",0,1)<>"",_xlfn.XLOOKUP($O$3,$Q$1:$AN$1,Q23:AN23,"-",0,1),"") -> 0.5 | O23: =IF(_xlfn.XLOOKUP($O$3,$Q$2:$AN$2,Q23:AN23,"-",0,1)<>"",_xlfn.XLOOKUP($O$3,$Q$2:$AN$2,Q23:AN23,"-",0,1),"") | P23: =IF(_xlfn.XLOOKUP($O$3,$Q$3:$AN$3,Q23:AN23,"-",0,1)<>"",_xlfn.XLOOKUP($O$3,$Q$3:$AN$3,Q23:AN23,"-",0,1),"") | Q23: 0.6 | T23: 0.6 | W23: 0.5 | Z23: 0.5 | AC23: 0.5 | AQ23: =_xlfn.TRANSLATE(A23,"de","en") -> Degradation | AU23: Entspricht einer Degradation von 10 % in 25 Jahren und liegt im Bereich der Angaben der Modulhersteller (Leistungsgarantie) | AW23: =_xlfn.TRANSLATE(AU23,"de","en") -> Corresponds to a degradation of 10 % in 25 years and is within the range of the specifications of the module manufacturers (performance guarantee) | BA23: 40 | BB23: -- | BC23: -- | BD23: -- | BE23: -- | BF23: --
N24: =IF(_xlfn.XLOOKUP($O$3,$Q$1:$AN$1,Q24:AN24,"-",0,1)<>"",_xlfn.XLOOKUP($O$3,$Q$1:$AN$1,Q24:AN24,"-",0,1),"") | O24: =IF(_xlfn.XLOOKUP($O$3,$Q$2:$AN$2,Q24:AN24,"-",0,1)<>"",_xlfn.XLOOKUP($O$3,$Q$2:$AN$2,Q24:AN24,"-",0,1),"") | P24: =IF(_xlfn.XLOOKUP($O$3,$Q$3:$AN$3,Q24:AN24,"-",0,1)<>"",_xlfn.XLOOKUP($O$3,$Q$3:$AN$3,Q24:AN24,"-",0,1),"") | AQ24: =_xlfn.TRANSLATE(A24,"de","en") | AW24: =_xlfn.TRANSLATE(AU24,"de","en")
A25: Anlagedaten Batteriespeicher | N25: =IF(_xlfn.XLOOKUP($O$3,$Q$1:$AN$1,Q25:AN25,"-",0,1)<>"",_xlfn.XLOOKUP($O$3,$Q$1:$AN$1,Q25:AN25,"-",0,1),"") | O25: =IF(_xlfn.XLOOKUP($O$3,$Q$2:$AN$2,Q25:AN25,"-",0,1)<>"",_xlfn.XLOOKUP($O$3,$Q$2:$AN$2,Q25:AN25,"-",0,1),"") | P25: =IF(_xlfn.XLOOKUP($O$3,$Q$3:$AN$3,Q25:AN25,"-",0,1)<>"",_xlfn.XLOOKUP($O$3,$Q$3:$AN$3,Q25:AN25,"-",0,1),"") | AQ25: =_xlfn.TRANSLATE(A25,"de","en") -> System data battery storage system | AW25: =_xlfn.TRANSLATE(AU25,"de","en") | AY25: Sensitivitätsanalyse Eigenverbrauch und Zuschlag Tarif externer Energiebezug
A26: Batteriespeicher vorhanden | B26: NEIN | C26: =IF(_Debug_Modus=_JA,N26,IF(B26="",I26,B26)) -> NEIN | I26: =_JA -> JA | J26: =_NEIN -> NEIN | N26: =IF(_xlfn.XLOOKUP($O$3,$Q$1:$AN$1,Q26:AN26,"-",0,1)<>"",_xlfn.XLOOKUP($O$3,$Q$1:$AN$1,Q26:AN26,"-",0,1),"") -> NEIN | O26: =IF(_xlfn.XLOOKUP($O$3,$Q$2:$AN$2,Q26:AN26,"-",0,1)<>"",_xlfn.XLOOKUP($O$3,$Q$2:$AN$2,Q26:AN26,"-",0,1),"") | P26: =IF(_xlfn.XLOOKUP($O$3,$Q$3:$AN$3,Q26:AN26,"-",0,1)<>"",_xlfn.XLOOKUP($O$3,$Q$3:$AN$3,Q26:AN26,"-",0,1),"") | Q26: JA | T26: NEIN | W26: JA | Z26: NEIN | AC26: JA | AQ26: =_xlfn.TRANSLATE(A26,"de","en") -> Battery storage available | AW26: =_xlfn.TRANSLATE(AU26,"de","en")
A27: Speichertechnologie | B27: Lithium-Ionen LFP | N27: =IF(_xlfn.XLOOKUP($O$3,$Q$1:$AN$1,Q27:AN27,"-",0,1)<>"",_xlfn.XLOOKUP($O$3,$Q$1:$AN$1,Q27:AN27,"-",0,1),"") | O27: =IF(_xlfn.XLOOKUP($O$3,$Q$2:$AN$2,Q27:AN27,"-",0,1)<>"",_xlfn.XLOOKUP($O$3,$Q$2:$AN$2,Q27:AN27,"-",0,1),"") | P27: =IF(_xlfn.XLOOKUP($O$3,$Q$3:$AN$3,Q27:AN27,"-",0,1)<>"",_xlfn.XLOOKUP($O$3,$Q$3:$AN$3,Q27:AN27,"-",0,1),"") | Q27: Lithium-Ionen LFP | W27: Lithium-Ionen LFP | AQ27: =_xlfn.TRANSLATE(A27,"de","en") -> Storage Technology | AW27: =_xlfn.TRANSLATE(AU27,"de","en")
A28: Speicherkapazität | C28: =IF(_Batterie=_NEIN,0,IF(IF(B28="",IF(AND(_Debug_Modus=_JA,N28<>""),N28,I28),B28)<K28,K28,IF(IF(B28="",IF(AND(_Debug_Modus=_JA,N28<>""),N28,I28),B28)>L28,L28,IF(B28="",IF(AND(_Debug_Modus=_JA,N28<>""),N28,I28),B28)))) -> 0 | D28: kWh | E28: (Nutzkapazität im Inbetriebnahmejahr) | I28: =IF(_Anlagenleistung*_spez_Jahresenergieertrag/1000<_Gesamtverbrauch/1000,_Anlagenleistung*_spez_Jahresenergieertrag/1000,_Gesamtverbrauch/1000) -> 4.5 | K28: 0 | L28: 100000 | N28: =IF(_xlfn.XLOOKUP($O$3,$Q$1:$AN$1,Q28:AN28,"-",0,1)<>"",_xlfn.XLOOKUP($O$3,$Q$1:$AN$1,Q28:AN28,"-",0,1),"") | O28: =IF(_xlfn.XLOOKUP($O$3,$Q$2:$AN$2,Q28:AN28,"-",0,1)<>"",_xlfn.XLOOKUP($O$3,$Q$2:$AN$2,Q28:AN28,"-",0,1),"") | P28: =IF(_xlfn.XLOOKUP($O$3,$Q$3:$AN$3,Q28:AN28,"-",0,1)<>"",_xlfn.XLOOKUP($O$3,$Q$3:$AN$3,Q28:AN28,"-",0,1),"") | Q28: 10 | W28: 105 | AQ28: =_xlfn.TRANSLATE(A28,"de","en") -> Storage capacity | AU28: Der kleinere Wert von 1/1'000 der Jahresproduktion oder 1/1'000 des Jahresenergiebedarfs | AW28: =_xlfn.TRANSLATE(AU28,"de","en") -> The smaller value of 1/1,000 of the annual production or 1/1,000 of the annual energy demand | AY28: Projektrendite ohne Batterie in % | BB28: ersetzter Bezugstarif / PV- Stromtarif ZEV [CHF/kWh]
A29: Wirkungsgrad des Speichers | C29: =IF(IF(B29="",IF(AND(_Debug_Modus=_JA,N29<>""),N29,I29),B29)<K29,K29,IF(IF(B29="",IF(AND(_Debug_Modus=_JA,N29<>""),N29,I29),B29)>L29,L29,IF(B29="",IF(AND(_Debug_Modus=_JA,N29<>""),N29,I29),B29))) -> 90 | D29: % | E29: (typische Werte von Lithium- Ionen Speicher liegen zwischen 85 - 95%) | I29: 90 | K29: 0 | L29: 100 | N29: =IF(_xlfn.XLOOKUP($O$3,$Q$1:$AN$1,Q29:AN29,"-",0,1)<>"",_xlfn.XLOOKUP($O$3,$Q$1:$AN$1,Q29:AN29,"-",0,1),"") | O29: =IF(_xlfn.XLOOKUP($O$3,$Q$2:$AN$2,Q29:AN29,"-",0,1)<>"",_xlfn.XLOOKUP($O$3,$Q$2:$AN$2,Q29:AN29,"-",0,1),"") | P29: =IF(_xlfn.XLOOKUP($O$3,$Q$3:$AN$3,Q29:AN29,"-",0,1)<>"",_xlfn.XLOOKUP($O$3,$Q$3:$AN$3,Q29:AN29,"-",0,1),"") | W29: 88 | AQ29: =_xlfn.TRANSLATE(A29,"de","en") -> Efficiency of the storage system | AU29: Es wird ein Wert in der Mitte des typischen Bereiches verwendet | AW29: =_xlfn.TRANSLATE(AU29,"de","en") -> A value in the middle of the typical range is used | BB29: 0.8 | BC29: 0.9 | BD29: 1 | BE29: 1.1 | BF29: 1.2
A30: Speicherlebensdauer | C30: =IF(IF(B30="",IF(AND(_Debug_Modus=_JA,N30<>""),N30,I30),B30)<K30,K30,IF(IF(B30="",IF(AND(_Debug_Modus=_JA,N30<>""),N30,I30),B30)>L30,L30,IF(B30="",IF(AND(_Debug_Modus=_JA,N30<>""),N30,I30),B30))) -> 15 | E30: (typische Werte von Lithium- Ionen Speicher liegen zwischen 10 - 20 Jahren) | I30: 15 | K30: 0 | L30: =_Anlagenlebensdauer -> 30 | N30: =IF(_xlfn.XLOOKUP($O$3,$Q$1:$AN$1,Q30:AN30,"-",0,1)<>"",_xlfn.XLOOKUP($O$3,$Q$1:$AN$1,Q30:AN30,"-",0,1),"") | O30: =IF(_xlfn.XLOOKUP($O$3,$Q$2:$AN$2,Q30:AN30,"-",0,1)<>"",_xlfn.XLOOKUP($O$3,$Q$2:$AN$2,Q30:AN30,"-",0,1),"") | P30: =IF(_xlfn.XLOOKUP($O$3,$Q$3:$AN$3,Q30:AN30,"-",0,1)<>"",_xlfn.XLOOKUP($O$3,$Q$3:$AN$3,Q30:AN30,"-",0,1),"") | W30: 14 | AQ30: =_xlfn.TRANSLATE(A30,"de","en") -> Storage life | AU30: Es wird ein Wert in der Mitte des typischen Bereiches verwendet | AW30: =_xlfn.TRANSLATE(AU30,"de","en") -> A value in the middle of the typical range is used | BA30: =_Projektrendite -> -- | BB30: =$BD30*BB29 -> 0.1856 | BC30: =$BD30*BC29 -> 0.2088 | BD30: =IF(B47="",IF(AND(_Debug_Modus=_JA,N47<>""),N47,I47),B47) -> 0.232 | BE30: =$BD30*BE29 -> 0.2552 | BF30: =$BD30*BF29 -> 0.2784
A31: Degradation | C31: =IF(IF(B31="",IF(AND(_Debug_Modus=_JA,N31<>""),N31,I31),B31)<K31,K31,IF(IF(B31="",IF(AND(_Debug_Modus=_JA,N31<>""),N31,I31),B31)>L31,L31,IF(B31="",IF(AND(_Debug_Modus=_JA,N31<>""),N31,I31),B31))) -> 1.3333333 | D31: % / Jahr | E31: (Meist wird von 20% Degradation während der Lebensdauer ausgegangen) | I31: =20/I30 -> 1.3333333 | K31: 0 | L31: 10 | N31: =IF(_xlfn.XLOOKUP($O$3,$Q$1:$AN$1,Q31:AN31,"-",0,1)<>"",_xlfn.XLOOKUP($O$3,$Q$1:$AN$1,Q31:AN31,"-",0,1),"") | O31: =IF(_xlfn.XLOOKUP($O$3,$Q$2:$AN$2,Q31:AN31,"-",0,1)<>"",_xlfn.XLOOKUP($O$3,$Q$2:$AN$2,Q31:AN31,"-",0,1),"") | P31: =IF(_xlfn.XLOOKUP($O$3,$Q$3:$AN$3,Q31:AN31,"-",0,1)<>"",_xlfn.XLOOKUP($O$3,$Q$3:$AN$3,Q31:AN31,"-",0,1),"") | W31: 1 | AQ31: =_xlfn.TRANSLATE(A31,"de","en") -> Degradation | AU31: Es wird mit einer Reduktion der Batteriekapazität von 20% innerhalb der Lebensdauer gerechnet | AW31: =_xlfn.TRANSLATE(AU31,"de","en") -> A reduction in battery capacity of 20% is expected within the service life | AY31: Eigenverbrauch [%] | BA31: =IF(BA32-5>0,BA32-5,0) -> 23.270424 | BB31: -- | BC31: -- | BD31: -- | BE31: -- | BF31: --
A32: Eigenverbrauchsanteil mit Batterie | C32: =IF(_Batterie=_NEIN,0,IF(IF(B32="",IF(AND(_Debug_Modus=_JA,N32<>""),N32,I32),B32)<K32,K32,IF(IF(B32="",IF(AND(_Debug_Modus=_JA,N32<>""),N32,I32),B32)>L32,L32,IF(B32="",IF(AND(_Debug_Modus=_JA,N32<>""),N32,I32),B32)))) -> 0 | D32: % | I32: =IF(_Eigennutzungsgrad+20>100,100,_Eigennutzungsgrad+20) -> 53.270424 | K32: 0 | L32: 100 | N32: =IF(_xlfn.XLOOKUP($O$3,$Q$1:$AN$1,Q32:AN32,"-",0,1)<>"",_xlfn.XLOOKUP($O$3,$Q$1:$AN$1,Q32:AN32,"-",0,1),"") | O32: =IF(_xlfn.XLOOKUP($O$3,$Q$2:$AN$2,Q32:AN32,"-",0,1)<>"",_xlfn.XLOOKUP($O$3,$Q$2:$AN$2,Q32:AN32,"-",0,1),"") | P32: =IF(_xlfn.XLOOKUP($O$3,$Q$3:$AN$3,Q32:AN32,"-",0,1)<>"",_xlfn.XLOOKUP($O$3,$Q$3:$AN$3,Q32:AN32,"-",0,1),"") | Q32: 45 | W32: 70 | AQ32: =_xlfn.TRANSLATE(A32,"de","en") -> Self-consumption share with battery | AU32: Es wird mit einer durchschnittlichen Erhöhung des Eigenverbrauchsanteils um 20% gerechnet, was im Wohnbereich ein zu erwartender Wert ist | AW32: =_xlfn.TRANSLATE(AU32,"de","en") -> An average increase in the share of self-consumption of 20% is expected, which is an expected value in the residential area | BA32: =IF(BA33-5>0,BA33-5,0) -> 28.270424 | BB32: -- | BC32: -- | BD32: -- | BE32: -- | BF32: --
A33: Erhöhung Eigenverbrauchsanteil mit Batterie | C33: =IF(IF(B33="",IF(AND(_Debug_Modus=_JA,N33<>""),N33,I33),B33)<K33,K33,IF(IF(B33="",IF(AND(_Debug_Modus=_JA,N33<>""),N33,I33),B33)>L33,L33,IF(B33="",IF(AND(_Debug_Modus=_JA,N33<>""),N33,I33),B33))) -> 0 | D33: % | I33: =C32-_Eigennutzungsgrad -> -33.270424 | K33: 0 | L33: 100 | N33: =IF(_xlfn.XLOOKUP($O$3,$Q$1:$AN$1,Q33:AN33,"-",0,1)<>"",_xlfn.XLOOKUP($O$3,$Q$1:$AN$1,Q33:AN33,"-",0,1),"") | O33: =IF(_xlfn.XLOOKUP($O$3,$Q$2:$AN$2,Q33:AN33,"-",0,1)<>"",_xlfn.XLOOKUP($O$3,$Q$2:$AN$2,Q33:AN33,"-",0,1),"") | P33: =IF(_xlfn.XLOOKUP($O$3,$Q$3:$AN$3,Q33:AN33,"-",0,1)<>"",_xlfn.XLOOKUP($O$3,$Q$3:$AN$3,Q33:AN33,"-",0,1),"") | AQ33: =_xlfn.TRANSLATE(A33,"de","en") -> Increase in self-consumption share with battery | AU33: Wird berechnet aus der Differenz zwischen Eigenverbrauchsanteils mit Batterie und Eigenverbrauchsanteil am Ort der Produktion | AW33: =_xlfn.TRANSLATE(AU33,"de","en") -> Calculated from the difference between the self-consumption share with the battery and the self-consumption share at the place of production | BA33: =IF(IF(B45="",IF(AND(_Debug_Modus=_JA,N45<>""),N45,I45),B45)<K45,K45,IF(IF(B45="",IF(AND(_Debug_Modus=_JA,N45<>""),N45,I45),B45)>L45,L45,IF(B45="",IF(AND(_Debug_Modus=_JA,N45<>""),N45,I45),B45))) -> 33.270424 | BB33: -- | BC33: -- | BD33: -- | BE33: -- | BF33: --
A34: Reduktion der Summe der Leistungsspitzen pro Jahr | C34: =IF(_Batterie=_NEIN,0,IF(IF(B34="",IF(AND(_Debug_Modus=_JA,N34<>""),N34,I34),B34)<K34,K34,IF(IF(B34="",IF(AND(_Debug_Modus=_JA,N34<>""),N34,I34),B34)>L34,L34,IF(B34="",IF(AND(_Debug_Modus=_JA,N34<>""),N34,I34),B34)))) -> 0 | D34: % | E34: (Durch Batteriespeicher reduzierte, abrechnungsrelevante Leistungsspitzen pro Monat über ein Jahr aufsummiert) | I34: 30 | K34: 0 | L34: =100-_Reduktion_Leistungsspitzen -> 100 | N34: =IF(_xlfn.XLOOKUP($O$3,$Q$1:$AN$1,Q34:AN34,"-",0,1)<>"",_xlfn.XLOOKUP($O$3,$Q$1:$AN$1,Q34:AN34,"-",0,1),"") | O34: =IF(_xlfn.XLOOKUP($O$3,$Q$2:$AN$2,Q34:AN34,"-",0,1)<>"",_xlfn.XLOOKUP($O$3,$Q$2:$AN$2,Q34:AN34,"-",0,1),"") | P34: =IF(_xlfn.XLOOKUP($O$3,$Q$3:$AN$3,Q34:AN34,"-",0,1)<>"",_xlfn.XLOOKUP($O$3,$Q$3:$AN$3,Q34:AN34,"-",0,1),"") | Q34: 50 | W34: 40 | AQ34: =_xlfn.TRANSLATE(A34,"de","en") -> Reduction of the sum of power peaks per year | AU34: Es wird mit einer durchschnittlichen Reduktion der Summe der monatlichen Leistungsspitzen für ein Jahr von 30% gerechnet | AW34: =_xlfn.TRANSLATE(AU34,"de","en") -> An average reduction in the sum of monthly performance peaks for one year of 30% is expected | BA34: =IF(BA33+5<=100,BA33+5,100) -> 38.270424 | BB34: -- | BC34: -- | BD34: -- | BE34: -- | BF34: --
AQ35: =_xlfn.TRANSLATE(A35,"de","en") | AW35: =_xlfn.TRANSLATE(AU35,"de","en") | BA35: =IF(BA34+5<=100,BA34+5,100) -> 43.270424 | BB35: -- | BC35: -- | BD35: -- | BE35: -- | BF35: --
A36: Verbrauchsdaten | N36: =IF(_xlfn.XLOOKUP($O$3,$Q$1:$AN$1,Q36:AN36,"-",0,1)<>"",_xlfn.XLOOKUP($O$3,$Q$1:$AN$1,Q36:AN36,"-",0,1),"") | O36: =IF(_xlfn.XLOOKUP($O$3,$Q$2:$AN$2,Q36:AN36,"-",0,1)<>"",_xlfn.XLOOKUP($O$3,$Q$2:$AN$2,Q36:AN36,"-",0,1),"") | P36: =IF(_xlfn.XLOOKUP($O$3,$Q$3:$AN$3,Q36:AN36,"-",0,1)<>"",_xlfn.XLOOKUP($O$3,$Q$3:$AN$3,Q36:AN36,"-",0,1),"") | AQ36: =_xlfn.TRANSLATE(A36,"de","en") -> Consumption | AW36: =_xlfn.TRANSLATE(AU36,"de","en")
A37: Jahresenergieverbrauch | C37: =IF(B37="",IF(AND(_Debug_Modus=_JA,N37<>""),N37,I37),B37) -> 4500 | D37: kWh | E37: (Jahresenergieverbrauch aller Solarstromkonsumenten exkl LEG) | I37: =_Anlagenleistung*_spez_Jahresenergieertrag -> 4500 | N37: =IF(_xlfn.XLOOKUP($O$3,$Q$1:$AN$1,Q37:AN37,"-",0,1)<>"",_xlfn.XLOOKUP($O$3,$Q$1:$AN$1,Q37:AN37,"-",0,1),"") -> 150000 | O37: =IF(_xlfn.XLOOKUP($O$3,$Q$2:$AN$2,Q37:AN37,"-",0,1)<>"",_xlfn.XLOOKUP($O$3,$Q$2:$AN$2,Q37:AN37,"-",0,1),"") | P37: =IF(_xlfn.XLOOKUP($O$3,$Q$3:$AN$3,Q37:AN37,"-",0,1)<>"",_xlfn.XLOOKUP($O$3,$Q$3:$AN$3,Q37:AN37,"-",0,1),"") | Q37: 5000 | T37: 5000 | W37: 70000 | Z37: 150000 | AC37: 150000 | AQ37: =_xlfn.TRANSLATE(A37,"de","en") -> Annual energy consumption | AU37: Es wird von einem Deckungsgrad von 100% ausgegangen, d.h. der Gesamtverbrauch entspricht der Gesamtproduktion | AW37: =_xlfn.TRANSLATE(AU37,"de","en") -> A coverage ratio of 100% is assumed, i.e. total consumption corresponds to total production | AY37: Sensitivitätsanalyse Kosten
A38: Summe der Leistungsspitzen aller Monate | C38: =IF(B38="",IF(AND(_Debug_Modus=_JA,N38<>""),N38,I38),B38) -> 61.643836 | D38: kW | E38: (Abrechnungsrelevante Leistungsspitzen pro Monat über ein Jahr aufsummiert) | I38: =_Gesamtverbrauch/(365*24)*10*12 -> 61.643836 | N38: =IF(_xlfn.XLOOKUP($O$3,$Q$1:$AN$1,Q38:AN38,"-",0,1)<>"",_xlfn.XLOOKUP($O$3,$Q$1:$AN$1,Q38:AN38,"-",0,1),"") -> 2000 | O38: =IF(_xlfn.XLOOKUP($O$3,$Q$2:$AN$2,Q38:AN38,"-",0,1)<>"",_xlfn.XLOOKUP($O$3,$Q$2:$AN$2,Q38:AN38,"-",0,1),"") | P38: =IF(_xlfn.XLOOKUP($O$3,$Q$3:$AN$3,Q38:AN38,"-",0,1)<>"",_xlfn.XLOOKUP($O$3,$Q$3:$AN$3,Q38:AN38,"-",0,1),"") | Q38: 60 | T38: 60 | W38: 1000 | Z38: 2000 | AC38: 2000 | AQ38: =_xlfn.TRANSLATE(A38,"de","en") -> Sum of power peaks of all months | AU38: Es wird der mittlere stündliche Energiebedarf ermittelt und mit dem Faktor 10 multipliziert. Dieser Wert wird für jeden Monat als Leistungsspitze angenommen | AW38: =_xlfn.TRANSLATE(AU38,"de","en") -> The average hourly energy requirement is determined and multiplied by a factor of 10. This value is assumed to be the performance peak for each month
AQ39: =_xlfn.TRANSLATE(A39,"de","en") | AW39: =_xlfn.TRANSLATE(AU39,"de","en") | AY39: Projektrendite ohne Batterie in % | BB39: Abnahmevergütung [CHF/kWh]
N40: =IF(_xlfn.XLOOKUP($O$3,$Q$1:$AN$1,Q40:AN40,"-",0,1)<>"",_xlfn.XLOOKUP($O$3,$Q$1:$AN$1,Q40:AN40,"-",0,1),"") | O40: =IF(_xlfn.XLOOKUP($O$3,$Q$2:$AN$2,Q40:AN40,"-",0,1)<>"",_xlfn.XLOOKUP($O$3,$Q$2:$AN$2,Q40:AN40,"-",0,1),"") | P40: =IF(_xlfn.XLOOKUP($O$3,$Q$3:$AN$3,Q40:AN40,"-",0,1)<>"",_xlfn.XLOOKUP($O$3,$Q$3:$AN$3,Q40:AN40,"-",0,1),"") | AQ40: =_xlfn.TRANSLATE(A40,"de","en") | AW40: =_xlfn.TRANSLATE(AU40,"de","en") | BB40: 0.8 | BC40: 0.9 | BD40: 1 | BE40: 1.1 | BF40: 1.2
A41: ZEV oder vZEV | B41: JA | C41: =IF(_Debug_Modus=_JA,N41,IF(B41="",I41,B41)) -> JA | E41: (Das Praxismodell VNB kann ohne ZEV gerechnet werden) | I41: =_JA -> JA | J41: =_NEIN -> NEIN | N41: =IF(_xlfn.XLOOKUP($O$3,$Q$1:$AN$1,Q41:AN41,"-",0,1)<>"",_xlfn.XLOOKUP($O$3,$Q$1:$AN$1,Q41:AN41,"-",0,1),"") -> JA | O41: =IF(_xlfn.XLOOKUP($O$3,$Q$2:$AN$2,Q41:AN41,"-",0,1)<>"",_xlfn.XLOOKUP($O$3,$Q$2:$AN$2,Q41:AN41,"-",0,1),"") | P41: =IF(_xlfn.XLOOKUP($O$3,$Q$3:$AN$3,Q41:AN41,"-",0,1)<>"",_xlfn.XLOOKUP($O$3,$Q$3:$AN$3,Q41:AN41,"-",0,1),"") | Q41: NEIN | T41: NEIN | W41: NEIN | Z41: JA | AC41: JA | AQ41: =_xlfn.TRANSLATE(A41,"de","en") -> ZEV or vZEV | AW41: =_xlfn.TRANSLATE(AU41,"de","en")
A42: Anzahl separat gemessene Teilnehmer ZEV | C42: =IF(B42="",IF(AND(_Debug_Modus=_JA,N42<>""),N42,I42),B42) -> 0 | D42: Teilnehmer | E42: (Anzahl der Verbraucher, welche am Eigenverbrauch am Ort der Produktion teilnehmen) | I42: =ROUNDDOWN(_Gesamtverbrauch/5000,0) -> 0 | N42: =IF(_xlfn.XLOOKUP($O$3,$Q$1:$AN$1,Q42:AN42,"-",0,1)<>"",_xlfn.XLOOKUP($O$3,$Q$1:$AN$1,Q42:AN42,"-",0,1),"") -> 40 | O42: =IF(_xlfn.XLOOKUP($O$3,$Q$2:$AN$2,Q42:AN42,"-",0,1)<>"",_xlfn.XLOOKUP($O$3,$Q$2:$AN$2,Q42:AN42,"-",0,1),"") | P42: =IF(_xlfn.XLOOKUP($O$3,$Q$3:$AN$3,Q42:AN42,"-",0,1)<>"",_xlfn.XLOOKUP($O$3,$Q$3:$AN$3,Q42:AN42,"-",0,1),"") | Q42: 1 | T42: 1 | W42: 1 | Z42: 40 | AC42: 40 | AQ42: =_xlfn.TRANSLATE(A42,"de","en") -> Number of separately measured participants ZEV | AU42: Es wird pro 5'000 kWh ein Verbraucher angenommen. | AW42: =_xlfn.TRANSLATE(AU42,"de","en") -> One consumer per 5,000 kWh is assumed. | BA42: =_Projektrendite -> -- | BB42: =$BD42*BB40 -> 0.064 | BC42: =$BD42*BC40 -> 0.072 | BD42: =I73 -> 0.08 | BE42: =$BD42*BE40 -> 0.088 | BF42: =$BD42*BF40 -> 0.096
A43: Eigenverbrauch am Ort der Produktion | E43: (Es wird mit einem mittleren gewichteten Eigenverbrauchstarif gerechnet) | AQ43: =_xlfn.TRANSLATE(A43,"de","en") -> Self-consumption at the point of production | AW43: =_xlfn.TRANSLATE(AU43,"de","en") | AY43: Investitions-kosten PV- Anlage [CHF] | AZ43: 1.2 | BA43: =$BA$45*AZ43 -> 18412.8 | BB43: -- | BC43: -- | BD43: -- | BE43: -- | BF43: --
A44: Reduktion der Leistungsspitzen pro Jahr | C44: =IF(IF(B44="",IF(AND(_Debug_Modus=_JA,N44<>""),N44,I44),B44)<K44,K44,IF(IF(B44="",IF(AND(_Debug_Modus=_JA,N44<>""),N44,I44),B44)>L44,L44,IF(B44="",IF(AND(_Debug_Modus=_JA,N44<>""),N44,I44),B44))) -> 0 | D44: % | E44: (Reduktion der abrechnungsrelevanten Leistungsspitzen pro Monat über ein Jahr aufsummiert) | I44: 0 | K44: 0 | L44: 100 | N44: =IF(_xlfn.XLOOKUP($O$3,$Q$1:$AN$1,Q44:AN44,"-",0,1)<>"",_xlfn.XLOOKUP($O$3,$Q$1:$AN$1,Q44:AN44,"-",0,1),"") -> 2 | O44: =IF(_xlfn.XLOOKUP($O$3,$Q$2:$AN$2,Q44:AN44,"-",0,1)<>"",_xlfn.XLOOKUP($O$3,$Q$2:$AN$2,Q44:AN44,"-",0,1),"") | P44: =IF(_xlfn.XLOOKUP($O$3,$Q$3:$AN$3,Q44:AN44,"-",0,1)<>"",_xlfn.XLOOKUP($O$3,$Q$3:$AN$3,Q44:AN44,"-",0,1),"") | Q44: 2 | T44: 2 | W44: 2 | Z44: 2 | AC44: 2 | AQ44: =_xlfn.TRANSLATE(A44,"de","en") -> Reduction of power peaks per year | AU44: Es wird von einer mittleren Reduktion der Leistungsspitze von 0% ausgegangen (orientiert an einem Deckungsgrad von ca. 10%) | AW44: =_xlfn.TRANSLATE(AU44,"de","en") -> An average reduction in the peak benefit of 0% is assumed (based on a coverage ratio of approx. 10%) | AZ44: 1.1 | BA44: =$BA$45*AZ44 -> 16878.4 | BB44: -- | BC44: -- | BD44: -- | BE44: -- | BF44: --
A45: ="Eigenverbrauchsanteil"&IF(_ZEV=_JA," ZEV oder vZEV","")&" in %" -> Eigenverbrauchsanteil ZEV oder vZEV in % | C45: =IF(IF(B45="",IF(AND(_Debug_Modus=_JA,N45<>""),N45,I45),B45)<K45,K45,IF(IF(B45="",IF(AND(_Debug_Modus=_JA,N45<>""),N45,I45),B45)>L45,L45,IF(B45="",IF(AND(_Debug_Modus=_JA,N45<>""),N45,I45),B45))) -> 33.270424 | D45: % | E45: (konstant über die Lebensdauer) | I45: =IF(ISNUMBER(320.67*(_Anlagenleistung*_spez_Jahresenergieertrag/_Gesamtverbrauch*100)^-0.492),320.67*(_Anlagenleistung*_spez_Jahresenergieertrag/_Gesamtverbrauch*100)^-0.492,0) -> 33.270424 | K45: 0 | L45: 100 | N45: =IF(_xlfn.XLOOKUP($O$3,$Q$1:$AN$1,Q45:AN45,"-",0,1)<>"",_xlfn.XLOOKUP($O$3,$Q$1:$AN$1,Q45:AN45,"-",0,1),"") -> 55 | O45: =IF(_xlfn.XLOOKUP($O$3,$Q$2:$AN$2,Q45:AN45,"-",0,1)<>"",_xlfn.XLOOKUP($O$3,$Q$2:$AN$2,Q45:AN45,"-",0,1),"") | P45: =IF(_xlfn.XLOOKUP($O$3,$Q$3:$AN$3,Q45:AN45,"-",0,1)<>"",_xlfn.XLOOKUP($O$3,$Q$3:$AN$3,Q45:AN45,"-",0,1),"") | Q45: 25 | T45: 25 | W45: 30 | Z45: 55 | AC45: 55 | AQ45: =_xlfn.TRANSLATE(A45,"de","en") -> Self-consumption share ZEV or vZEV in % | AU45: Der Wert wird anhand einer Fittingkurve für ein Wohnhausprofil aus dem Deckungsgrad berechnet | AW45: =_xlfn.TRANSLATE(AU45,"de","en") -> The value is calculated on the basis of a fitting curve for a residential building profile from the coverage ratio | AZ45: 1 | BA45: =IF(B86="",IF(AND(_Debug_Modus=_JA,N86<>""),N86,I86),B86) -> 15344 | BB45: -- | BC45: -- | BD45: -- | BE45: -- | BF45: --
A46: ="Eigenverbrauchsanteil"&IF(_ZEV="JA"," ZEV oder vZEV","")& " in kWh" -> Eigenverbrauchsanteil ZEV oder vZEV in kWh | C46: =_Eigennutzungsgrad/100*_Durchschnittlicher_Energieertrag -> 1410.3333 | D46: kWh/Jahr | E46: (Ø Eigenverbrauch pro Jahr über Anlagenlebensdauer) | AQ46: =_xlfn.TRANSLATE(A46,"de","en") -> Self-consumption share ZEV or vZEV in kWh | AW46: =_xlfn.TRANSLATE(AU46,"de","en") | AZ46: 0.9 | BA46: =$BA$45*AZ46 -> 13809.6 | BB46: -- | BC46: -- | BD46: -- | BE46: -- | BF46: --
A47: =IF(_ZEV=_NEIN,"ersetzter Bezugstarif",IF(_ZEV=_JA,"PV- Stromtarif ZEV","Definiere die Eigenverbrauchsart beim Verbrauch")) -> PV- Stromtarif ZEV | C47: =IF(B47="",IF(AND(_Debug_Modus=_JA,N47<>""),N47,I47),B47) -> 0.232 | D47: CHF/kWh | E47: =IF(_MWStPflicht=_MWStpflichtig,"(exkl. MWSt.)","(inkl. MWSt.)") -> (exkl. MWSt.) | F47: =HYPERLINK("https://www.strompreis.elcom.admin.ch/","(für Praxismodell Stromtarif VNB abzgl. Dienstleistungsgebühren) aktuelle Stromtarife: https://www.strompreis.elcom.admin.ch/") -> (für Praxismodell Stromtarif VNB abzgl. Dienstleistungsgebühren) aktuelle Stromtarife: https://www.strompreis.elcom.admin.ch/ | I47: =IF(_ZEV=_NEIN,0.29,0.29*0.8-_Tarif_Abrechnung_ZEV) -> 0.232 | N47: =IF(_xlfn.XLOOKUP($O$3,$Q$1:$AN$1,Q47:AN47,"-",0,1)<>"",_xlfn.XLOOKUP($O$3,$Q$1:$AN$1,Q47:AN47,"-",0,1),"") -> 0.24 | O47: =IF(_xlfn.XLOOKUP($O$3,$Q$2:$AN$2,Q47:AN47,"-",0,1)<>"",_xlfn.XLOOKUP($O$3,$Q$2:$AN$2,Q47:AN47,"-",0,1),"") | P47: =IF(_xlfn.XLOOKUP($O$3,$Q$3:$AN$3,Q47:AN47,"-",0,1)<>"",_xlfn.XLOOKUP($O$3,$Q$3:$AN$3,Q47:AN47,"-",0,1),"") | Q47: 0.33 | T47: 0.33 | W47: 0.3 | Z47: =W47*0.8 -> 0.24 | AC47: 0.24 | AQ47: =_xlfn.TRANSLATE(A47,"de","en") -> PV electricity tariff ZEV | AU47: Für Anlagen ohne ZEV wird der Median des Strompreises H4 Total (Mai / 2025) von https://www.strompreis.elcom.admin.ch/ verwendet. Für den internen Stromverkauf in der ZEV wird 80% davon abzgl. den Abrechnungskosten ZEV verwendet. | AW47: =_xlfn.TRANSLATE(AU47,"de","en") -> For systems without ZEV, the median electricity price H4 Total (May / 2025) of https://www.strompreis.elcom.admin.ch/ is used. 80% of this is used for internal electricity sales in ZEV, minus ZEV billing costs. | AZ47: 0.8 | BA47: =$BA$45*AZ47 -> 12275.2 | BB47: -- | BC47: -- | BD47: -- | BE47: -- | BF47: --
A48: =IF(_ZEV=_NEIN,"Leistungstarif",IF(_ZEV=_JA,"Leistungstarif ZEV","Definiere die Eigenverbrauchsart beim Verbrauch")) -> Leistungstarif ZEV | C48: =IF(IF(B48="",IF(AND(_Debug_Modus=_JA,N48<>""),N48,I48),B48)<K48,K48,IF(IF(B48="",IF(AND(_Debug_Modus=_JA,N48<>""),N48,I48),B48)>L48,L48,IF(B48="",IF(AND(_Debug_Modus=_JA,N48<>""),N48,I48),B48))) -> 1.5 | D48: CHF/kW/Monat | E48: =IF(_MWStPflicht=_MWStpflichtig,"(exkl. MWSt.)","(inkl. MWSt.)") -> (exkl. MWSt.) | I48: =IF(_Gesamtverbrauch>50000,10,1.5) -> 1.5 | K48: 0 | L48: 100 | N48: =IF(_xlfn.XLOOKUP($O$3,$Q$1:$AN$1,Q48:AN48,"-",0,1)<>"",_xlfn.XLOOKUP($O$3,$Q$1:$AN$1,Q48:AN48,"-",0,1),"") -> 6 | O48: =IF(_xlfn.XLOOKUP($O$3,$Q$2:$AN$2,Q48:AN48,"-",0,1)<>"",_xlfn.XLOOKUP($O$3,$Q$2:$AN$2,Q48:AN48,"-",0,1),"") | P48: =IF(_xlfn.XLOOKUP($O$3,$Q$3:$AN$3,Q48:AN48,"-",0,1)<>"",_xlfn.XLOOKUP($O$3,$Q$3:$AN$3,Q48:AN48,"-",0,1),"") | Q48: 0 | T48: 0 | W48: 7.5 | Z48: =W48*0.8 -> 6 | AC48: 6 | AQ48: =_xlfn.TRANSLATE(A48,"de","en") -> ZEV service tariff | AU48: Für Verbraucher > 50MWh Verbrauch pro Jahr wird ein Leistungstarif von 10 CHF/kW verwendet, für kleinere Verbraucher 1.50 CHF/kW | AW48: =_xlfn.TRANSLATE(AU48,"de","en") -> For consumers > 50MWh consumption per year, a power tariff of 10 CHF/kW is used, for smaller consumers 1.50 CHF/kW
A49: Tariffestlegung basierend auf Stromprodukt | E49: (Angaben zum Stromprodukt für die Festlegung ersetzter Bezugstarif bzw. PV- Stromtarif ZEV) | N49: =IF(_xlfn.XLOOKUP($O$3,$Q$1:$AN$1,Q49:AN49,"-",0,1)<>"",_xlfn.XLOOKUP($O$3,$Q$1:$AN$1,Q49:AN49,"-",0,1),"") -> Stromprodukt G1 | O49: =IF(_xlfn.XLOOKUP($O$3,$Q$2:$AN$2,Q49:AN49,"-",0,1)<>"",_xlfn.XLOOKUP($O$3,$Q$2:$AN$2,Q49:AN49,"-",0,1),"") | P49: =IF(_xlfn.XLOOKUP($O$3,$Q$3:$AN$3,Q49:AN49,"-",0,1)<>"",_xlfn.XLOOKUP($O$3,$Q$3:$AN$3,Q49:AN49,"-",0,1),"") | Q49: Strom Privat Basic | T49: Strom Privat Basic | W49: Stromprodukt G1 | Z49: Stromprodukt G1 | AC49: Stromprodukt G1 | AQ49: =_xlfn.TRANSLATE(A49,"de","en") -> Tariff determination based on electricity product | AW49: =_xlfn.TRANSLATE(AU49,"de","en")
A50: Abrechnungskosten ZEV (pro kWh Eigenverbrauch) | C50: =IF(_ZEV="JA",IF(AND(_Debug_Modus=_JA,N50<>""),N50,IF(B50="",I50,B50)),J50) -> 0 | D50: CHF/kWh | E50: =IF(_MWStPflicht=_MWStpflichtig,"(exkl. MWSt.)","(inkl. MWSt.)") -> (exkl. MWSt.) | F50: (Einnahmen für die Abrechnung des Solarstroms in der ZEV) | I50: 0 | J50: 0 | N50: =IF(_xlfn.XLOOKUP($O$3,$Q$1:$AN$1,Q50:AN50,"-",0,1)<>"",_xlfn.XLOOKUP($O$3,$Q$1:$AN$1,Q50:AN50,"-",0,1),"") | O50: =IF(_xlfn.XLOOKUP($O$3,$Q$2:$AN$2,Q50:AN50,"-",0,1)<>"",_xlfn.XLOOKUP($O$3,$Q$2:$AN$2,Q50:AN50,"-",0,1),"") | P50: =IF(_xlfn.XLOOKUP($O$3,$Q$3:$AN$3,Q50:AN50,"-",0,1)<>"",_xlfn.XLOOKUP($O$3,$Q$3:$AN$3,Q50:AN50,"-",0,1),"") | AQ50: =_xlfn.TRANSLATE(A50,"de","en") -> Billing costs ZEV (per kWh self-consumption) | AU50: Es werden keine Abrechnungskosten pro kWh verwendet, sondern eine Grundgebühr | AW50: =_xlfn.TRANSLATE(AU50,"de","en") -> No billing costs per kWh are used, but a basic fee | AY50: Sensitivitätsanalyse Batteriespeicher
A51: Grundkosten Abrechnung ZEV pro Teilnehmer | C51: =IF(_ZEV="JA",IF(AND(_Debug_Modus=_JA,N51<>""),N51,IF(B51="",I51,B51)),J51) -> 8 | D51: CHF/Monat | E51: =IF(_MWStPflicht=_MWStpflichtig,"(exkl. MWSt.)","(inkl. MWSt.)") -> (exkl. MWSt.) | F51: (Einnahmen für die Abrechnung der ZEV pro Teilnehmer) | I51: =10*0.8 -> 8 | J51: 0 | N51: =IF(_xlfn.XLOOKUP($O$3,$Q$1:$AN$1,Q51:AN51,"-",0,1)<>"",_xlfn.XLOOKUP($O$3,$Q$1:$AN$1,Q51:AN51,"-",0,1),"") -> 6 | O51: =IF(_xlfn.XLOOKUP($O$3,$Q$2:$AN$2,Q51:AN51,"-",0,1)<>"",_xlfn.XLOOKUP($O$3,$Q$2:$AN$2,Q51:AN51,"-",0,1),"") | P51: =IF(_xlfn.XLOOKUP($O$3,$Q$3:$AN$3,Q51:AN51,"-",0,1)<>"",_xlfn.XLOOKUP($O$3,$Q$3:$AN$3,Q51:AN51,"-",0,1),"") | Z51: 6 | AC51: 6 | AQ51: =_xlfn.TRANSLATE(A51,"de","en") -> Basic costs for billing ZEV per participant | AU51: Es können 80% des Grundpreises EVU der einzelnen Teilnehmer verrechnet werden. Es wird von einem Grundpreis von 10 CHF/Monat ausgegangen | AW51: =_xlfn.TRANSLATE(AU51,"de","en") -> 80% of the basic price of the individual participants can be charged. A basic price of 10 CHF/month is assumed
A52: Hilfsrechnung Betriebskosten ZEV | B52: 0 | C52: CHF/Monat/Teilnehmer | E52: =B52*_Anzahl_Verbraucher*12 -> 0 | F52: CHF/Jahr | N52: =IF(_xlfn.XLOOKUP($O$3,$Q$1:$AN$1,Q52:AN52,"-",0,1)<>"",_xlfn.XLOOKUP($O$3,$Q$1:$AN$1,Q52:AN52,"-",0,1),"") | O52: =IF(_xlfn.XLOOKUP($O$3,$Q$2:$AN$2,Q52:AN52,"-",0,1)<>"",_xlfn.XLOOKUP($O$3,$Q$2:$AN$2,Q52:AN52,"-",0,1),"") | P52: =IF(_xlfn.XLOOKUP($O$3,$Q$3:$AN$3,Q52:AN52,"-",0,1)<>"",_xlfn.XLOOKUP($O$3,$Q$3:$AN$3,Q52:AN52,"-",0,1),"") | AQ52: =_xlfn.TRANSLATE(A52,"de","en") -> Auxiliary invoice operating costs ZEV | AU52: Es werden keine Annahmen für die Betriebskosten der ZEV berechnet. | AW52: =_xlfn.TRANSLATE(AU52,"de","en") -> No assumptions are calculated for the operating costs of the ZEV.
A53: Betriebskosten ZEV (Administration und Abrechnung) | C53: =IF(_ZEV=_NEIN,0,IF(B53="",IF(AND(_Debug_Modus=_JA,N53<>""),N53,I53),B53)) -> 0 | D53: CHF/Jahr | E53: =IF(_MWStPflicht=_MWStpflichtig,"(exkl. MWSt.)","(inkl. MWSt.)") -> (exkl. MWSt.) | F53: (wird als Rechenwert Betriebskosten ZEV übernommen) | I53: =E52 -> 0 | N53: =IF(_xlfn.XLOOKUP($O$3,$Q$1:$AN$1,Q53:AN53,"-",0,1)<>"",_xlfn.XLOOKUP($O$3,$Q$1:$AN$1,Q53:AN53,"-",0,1),"") -> 2160 | O53: =IF(_xlfn.XLOOKUP($O$3,$Q$2:$AN$2,Q53:AN53,"-",0,1)<>"",_xlfn.XLOOKUP($O$3,$Q$2:$AN$2,Q53:AN53,"-",0,1),"") | P53: =IF(_xlfn.XLOOKUP($O$3,$Q$3:$AN$3,Q53:AN53,"-",0,1)<>"",_xlfn.XLOOKUP($O$3,$Q$3:$AN$3,Q53:AN53,"-",0,1),"") | Z53: =4.5*Z42*12 -> 2160 | AC53: 2160 | AQ53: =_xlfn.TRANSLATE(A53,"de","en") -> Operating costs ZEV (administration and accounting) | AW53: =_xlfn.TRANSLATE(AU53,"de","en")
N54: =IF(_xlfn.XLOOKUP($O$3,$Q$1:$AN$1,Q54:AN54,"-",0,1)<>"",_xlfn.XLOOKUP($O$3,$Q$1:$AN$1,Q54:AN54,"-",0,1),"") | O54: =IF(_xlfn.XLOOKUP($O$3,$Q$2:$AN$2,Q54:AN54,"-",0,1)<>"",_xlfn.XLOOKUP($O$3,$Q$2:$AN$2,Q54:AN54,"-",0,1),"") | P54: =IF(_xlfn.XLOOKUP($O$3,$Q$3:$AN$3,Q54:AN54,"-",0,1)<>"",_xlfn.XLOOKUP($O$3,$Q$3:$AN$3,Q54:AN54,"-",0,1),"") | AQ54: =_xlfn.TRANSLATE(A54,"de","en") | AW54: =_xlfn.TRANSLATE(AU54,"de","en") | AY54: Projektrendite mit Batterie in % | BB54: ersetzter Bezugstarif / PV- Stromtarif ZEV [CHF/kWh]
A55: Lokale Elektrizitätsgemeinschaft | E55: (Es wird mit einem mittleren gewichteten LEG Tarif gerechnet) | N55: =IF(_xlfn.XLOOKUP($O$3,$Q$1:$AN$1,Q55:AN55,"-",0,1)<>"",_xlfn.XLOOKUP($O$3,$Q$1:$AN$1,Q55:AN55,"-",0,1),"") | O55: =IF(_xlfn.XLOOKUP($O$3,$Q$2:$AN$2,Q55:AN55,"-",0,1)<>"",_xlfn.XLOOKUP($O$3,$Q$2:$AN$2,Q55:AN55,"-",0,1),"") | P55: =IF(_xlfn.XLOOKUP($O$3,$Q$3:$AN$3,Q55:AN55,"-",0,1)<>"",_xlfn.XLOOKUP($O$3,$Q$3:$AN$3,Q55:AN55,"-",0,1),"") | AQ55: =_xlfn.TRANSLATE(A55,"de","en") -> Local Electricity Community | AW55: =_xlfn.TRANSLATE(AU55,"de","en") | BB55: 0.8 | BC55: 0.9 | BD55: 1 | BE55: 1.1 | BF55: 1.2
A56: LEG | B56: JA | C56: =IF(_Debug_Modus=_JA,N56,IF(B56="",I56,B56)) -> JA | I56: =_JA -> JA | J56: =_NEIN -> NEIN | N56: =IF(_xlfn.XLOOKUP($O$3,$Q$1:$AN$1,Q56:AN56,"-",0,1)<>"",_xlfn.XLOOKUP($O$3,$Q$1:$AN$1,Q56:AN56,"-",0,1),"") -> NEIN | O56: =IF(_xlfn.XLOOKUP($O$3,$Q$2:$AN$2,Q56:AN56,"-",0,1)<>"",_xlfn.XLOOKUP($O$3,$Q$2:$AN$2,Q56:AN56,"-",0,1),"") | P56: =IF(_xlfn.XLOOKUP($O$3,$Q$3:$AN$3,Q56:AN56,"-",0,1)<>"",_xlfn.XLOOKUP($O$3,$Q$3:$AN$3,Q56:AN56,"-",0,1),"") | Q56: NEIN | T56: NEIN | W56: NEIN | Z56: NEIN | AC56: JA | AQ56: =_xlfn.TRANSLATE(A56,"de","en") -> LEG | AW56: =_xlfn.TRANSLATE(AU56,"de","en") | BA56: =_Projektrendite_mit_Batterie -> -- | BB56: =$BD56*BB55 -> 0.1856 | BC56: =$BD56*BC55 -> 0.2088 | BD56: =IF(B47="",IF(AND(_Debug_Modus=_JA,N47<>""),N47,I47),B47) -> 0.232 | BE56: =$BD56*BE55 -> 0.2552 | BF56: =$BD56*BF55 -> 0.2784
A57: Nutzung der Netzebenen | B57: NE 5 & 7 | C57: =IF(_Debug_Modus=_JA,N57,IF(B57="",I57,B57)) -> NE 5 & 7 | E57: (Der Abschlag auf die Netzkosten ist abhängig davon, wieviele Netzebenen genutzt werden) | N57: NE 5 & 7 | O57: =IF(_xlfn.XLOOKUP($O$3,$Q$2:$AN$2,Q57:AN57,"-",0,1)<>"",_xlfn.XLOOKUP($O$3,$Q$2:$AN$2,Q57:AN57,"-",0,1),"") | P57: =IF(_xlfn.XLOOKUP($O$3,$Q$3:$AN$3,Q57:AN57,"-",0,1)<>"",_xlfn.XLOOKUP($O$3,$Q$3:$AN$3,Q57:AN57,"-",0,1),"") | Q57: NE 5 & 7 | T57: NE 5 & 7 | W57: NE 5 & 7 | Z57: NE 5 & 7 | AC57: NE 5 & 7 | AQ57: =_xlfn.TRANSLATE(A57,"de","en") -> Use of network levels | AW57: =_xlfn.TRANSLATE(AU57,"de","en") | AY57: Investitions-kosten Batterie-speicher [CHF] | AZ57: 1.2 | BA57: =$BA$59*AZ57 -> 0 | BB57: -- | BC57: -- | BD57: -- | BE57: -- | BF57: --
A58: Anteil Solarstrom an LEG in % | C58: =IF(_LEG=_NEIN,0,IF(IF(B58="",IF(AND(_Debug_Modus=_JA,N58<>""),N58,I58),B58)<K58,K58,IF(IF(B58="",IF(AND(_Debug_Modus=_JA,N58<>""),N58,I58),B58)>L58,L58,IF(B58="",IF(AND(_Debug_Modus=_JA,N58<>""),N58,I58),B58)))) -> 66.729576 | D58: % | E58: (konstant über die Lebensdauer) | I58: =L58 -> 66.729576 | K58: 0 | L58: =100-_Eigennutzungsgrad-_Erhöhung_Eigennutzungsgrad_Speicher -> 66.729576 | N58: =IF(_xlfn.XLOOKUP($O$3,$Q$1:$AN$1,Q58:AN58,"-",0,1)<>"",_xlfn.XLOOKUP($O$3,$Q$1:$AN$1,Q58:AN58,"-",0,1),"") | O58: =IF(_xlfn.XLOOKUP($O$3,$Q$2:$AN$2,Q58:AN58,"-",0,1)<>"",_xlfn.XLOOKUP($O$3,$Q$2:$AN$2,Q58:AN58,"-",0,1),"") | P58: =IF(_xlfn.XLOOKUP($O$3,$Q$3:$AN$3,Q58:AN58,"-",0,1)<>"",_xlfn.XLOOKUP($O$3,$Q$3:$AN$3,Q58:AN58,"-",0,1),"") | AQ58: =_xlfn.TRANSLATE(A58,"de","en") -> Share of solar power in LEG in % | AU58: Der Defaultwert wird so berechnet, dass der komplette Überschuss (ohne Eigenverbrauch und Eigenverbrauch Batterie) in der LEG verkauft wird. | AW58: =_xlfn.TRANSLATE(AU58,"de","en") -> The default value is calculated in such a way that the entire surplus (excluding self-consumption and self-consumption battery) is sold in the LEG. | AZ58: 1.1 | BA58: =$BA$59*AZ58 -> 0 | BB58: -- | BC58: -- | BD58: -- | BE58: -- | BF58: --
A59: Anteil Solarstrom an LEG in kWh | C59: =_Anteil_LEG/100*_Durchschnittlicher_Energieertrag -> 2828.6667 | D59: kWh | E59: (Ø Eigenverbrauch pro Jahr über Anlagenlebensdauer) | AQ59: =_xlfn.TRANSLATE(A59,"de","en") -> Share of solar power in LEG in kWh | AW59: =_xlfn.TRANSLATE(AU59,"de","en") | AZ59: 1 | BA59: =IF(B100="",IF(AND(_Debug_Modus=_JA,N100<>""),N100,I100),B100) -> 0 | BB59: -- | BC59: -- | BD59: -- | BE59: -- | BF59: --
A60: PV- Stromtarif LEG inkl. Abrechnung | C60: =IF(_LEG="JA",IF(AND(_Debug_Modus=_JA,N60<>""),N60,IF(B60="",I60,B60)),J60) -> 0.096666667 | D60: CHF/kWh | E60: =IF(_MWStPflicht=_MWStpflichtig,"(exkl. MWSt.)","(inkl. MWSt.)") -> (exkl. MWSt.) | F60: (Energiekosten für den Verbraucher in der LEG exkl. Netzkosten des VNB) | I60: =0.29*1/3 -> 0.096666667 | J60: 0 | N60: =IF(_xlfn.XLOOKUP($O$3,$Q$1:$AN$1,Q60:AN60,"-",0,1)<>"",_xlfn.XLOOKUP($O$3,$Q$1:$AN$1,Q60:AN60,"-",0,1),"") | O60: =IF(_xlfn.XLOOKUP($O$3,$Q$2:$AN$2,Q60:AN60,"-",0,1)<>"",_xlfn.XLOOKUP($O$3,$Q$2:$AN$2,Q60:AN60,"-",0,1),"") | P60: =IF(_xlfn.XLOOKUP($O$3,$Q$3:$AN$3,Q60:AN60,"-",0,1)<>"",_xlfn.XLOOKUP($O$3,$Q$3:$AN$3,Q60:AN60,"-",0,1),"") | AC60: 0.1 | AQ60: =_xlfn.TRANSLATE(A60,"de","en") -> PV electricity tariff LEG incl. billing | AU60: Als PV- Stromtarif in der LEG wird 1/3 des Strompreisees H4 Total (Mai / 2025) von https://www.strompreis.elcom.admin.ch/ verwendet. | AW60: =_xlfn.TRANSLATE(AU60,"de","en") -> The PV electricity tariff in the LEG is 1/3 of the electricity price H4 Total (May / 2025) of https://www.strompreis.elcom.admin.ch/. | AZ60: 0.9 | BA60: =$BA$59*AZ60 -> 0 | BB60: -- | BC60: -- | BD60: -- | BE60: -- | BF60: --
A61: Abrechnungskosten LEG | C61: =IF(_LEG="JA",IF(AND(_Debug_Modus=_JA,N61<>""),N61,IF(B61="",I61,B61)),J61) -> 0.015 | D61: CHF/kWh | E61: =IF(_MWStPflicht=_MWStpflichtig,"(exkl. MWSt.)","(inkl. MWSt.)") -> (exkl. MWSt.) | F61: (Aufwand für die Abrechung der LEG (Einnahmen)) | I61: 0.015 | J61: 0 | N61: =IF(_xlfn.XLOOKUP($O$3,$Q$1:$AN$1,Q61:AN61,"-",0,1)<>"",_xlfn.XLOOKUP($O$3,$Q$1:$AN$1,Q61:AN61,"-",0,1),"") | O61: =IF(_xlfn.XLOOKUP($O$3,$Q$2:$AN$2,Q61:AN61,"-",0,1)<>"",_xlfn.XLOOKUP($O$3,$Q$2:$AN$2,Q61:AN61,"-",0,1),"") | P61: =IF(_xlfn.XLOOKUP($O$3,$Q$3:$AN$3,Q61:AN61,"-",0,1)<>"",_xlfn.XLOOKUP($O$3,$Q$3:$AN$3,Q61:AN61,"-",0,1),"") | AC61: 0.02 | AQ61: =_xlfn.TRANSLATE(A61,"de","en") -> Billing costs LEG | AU61: Für die Abrechnungskosten der LEG werden 1.5 Rp./kWh angenommen. | AW61: =_xlfn.TRANSLATE(AU61,"de","en") -> The billing costs of the LEG are assumed to be 1.5 cents/kWh. | AZ61: 0.8 | BA61: =$BA$59*AZ61 -> 0 | BB61: -- | BC61: -- | BD61: -- | BE61: -- | BF61: --
A62: PV-Stromtarif LEG exkl. Abrechnung | C62: =I62 -> 0.081666667 | D62: CHF/kWh | E62: =IF(_MWStPflicht=_MWStpflichtig,"(exkl. MWSt.)","(inkl. MWSt.)") -> (exkl. MWSt.) | I62: =_PV_Tarif_LEG-_Abrechnungstarif_LEG -> 0.081666667 | N62: =IF(_xlfn.XLOOKUP($O$3,$Q$1:$AN$1,Q62:AN62,"-",0,1)<>"",_xlfn.XLOOKUP($O$3,$Q$1:$AN$1,Q62:AN62,"-",0,1),"") | O62: =IF(_xlfn.XLOOKUP($O$3,$Q$2:$AN$2,Q62:AN62,"-",0,1)<>"",_xlfn.XLOOKUP($O$3,$Q$2:$AN$2,Q62:AN62,"-",0,1),"") | P62: =IF(_xlfn.XLOOKUP($O$3,$Q$3:$AN$3,Q62:AN62,"-",0,1)<>"",_xlfn.XLOOKUP($O$3,$Q$3:$AN$3,Q62:AN62,"-",0,1),"") | AQ62: =_xlfn.TRANSLATE(A62,"de","en") -> PV electricity tariff LEG excl. billing | AW62: =_xlfn.TRANSLATE(AU62,"de","en")
D63: Hilfsberechnung Betriebskosten über Kosten pro kWh | AQ63: =_xlfn.TRANSLATE(A63,"de","en") | AW63: =_xlfn.TRANSLATE(AU63,"de","en") | AY63: Projektrendite nur Batterie in % | BB63: ersetzter Bezugstarif / PV- Stromtarif ZEV [CHF/kWh]
D64: Betriebskosten LEG | F64: Solarstrom an LEG | H64: (Resultat wird als Rechenwert für die Betriebskosten LEG übernommen) | AQ64: =_xlfn.TRANSLATE(A64,"de","en") | AW64: =_xlfn.TRANSLATE(AU64,"de","en") | BB64: 0.8 | BC64: 0.9 | BD64: 1 | BE64: 1.1 | BF64: 1.2
E65: CHF/kWh | F65: =_Anteil_LEG/100*_spez_Jahresenergieertrag*_Anlagenleistung -> 3002.8309 | G65: kWh | H65: =D65*_Anteil_LEG/100*_Anlagenleistung*_spez_Jahresenergieertrag -> 0 | N65: =IF(_xlfn.XLOOKUP($O$3,$Q$1:$AN$1,Q65:AN65,"-",0,1)<>"",_xlfn.XLOOKUP($O$3,$Q$1:$AN$1,Q65:AN65,"-",0,1),"") | O65: =IF(_xlfn.XLOOKUP($O$3,$Q$2:$AN$2,Q65:AN65,"-",0,1)<>"",_xlfn.XLOOKUP($O$3,$Q$2:$AN$2,Q65:AN65,"-",0,1),"") | P65: =IF(_xlfn.XLOOKUP($O$3,$Q$3:$AN$3,Q65:AN65,"-",0,1)<>"",_xlfn.XLOOKUP($O$3,$Q$3:$AN$3,Q65:AN65,"-",0,1),"") | AQ65: =_xlfn.TRANSLATE(A65,"de","en") | AW65: =_xlfn.TRANSLATE(AU65,"de","en") | BA65: =_Projektrendite_nur_Batterie -> -- | BB65: =$BD65*BB64 -> 0.1856 | BC65: =$BD65*BC64 -> 0.2088 | BD65: =IF(B47="",IF(AND(_Debug_Modus=_JA,N47<>""),N47,I47),B47) -> 0.232 | BE65: =$BD65*BE64 -> 0.2552 | BF65: =$BD65*BF64 -> 0.2784
A66: Betriebskosten LEG (Administration und Abrechnung) | C66: =IF(_LEG=_NEIN,0,IF(B66="",IF(AND(_Debug_Modus=_JA,N66<>""),N66,I66),B66)) -> 0 | D66: CHF/Jahr | E66: =IF(_MWStPflicht=_MWStpflichtig,"(exkl. MWSt.)","(inkl. MWSt.)") -> (exkl. MWSt.) | F66: (wird als Rechenwert Betriebskosten LEG übernommen) | I66: =H65 -> 0 | N66: =IF(_xlfn.XLOOKUP($O$3,$Q$1:$AN$1,Q66:AN66,"-",0,1)<>"",_xlfn.XLOOKUP($O$3,$Q$1:$AN$1,Q66:AN66,"-",0,1),"") | O66: =IF(_xlfn.XLOOKUP($O$3,$Q$2:$AN$2,Q66:AN66,"-",0,1)<>"",_xlfn.XLOOKUP($O$3,$Q$2:$AN$2,Q66:AN66,"-",0,1),"") | P66: =IF(_xlfn.XLOOKUP($O$3,$Q$3:$AN$3,Q66:AN66,"-",0,1)<>"",_xlfn.XLOOKUP($O$3,$Q$3:$AN$3,Q66:AN66,"-",0,1),"") | AC66: 430 | AQ66: =_xlfn.TRANSLATE(A66,"de","en") -> Operating costs LEG (administration and billing) | AU66: Es werden keine Annahmen für die Betriebskosten der LEG berechnet. | AW66: =_xlfn.TRANSLATE(AU66,"de","en") -> No assumptions are calculated for the operating costs of the LEG. | AY66: Investitions-kosten Batterie-speicher [CHF] | AZ66: 1.2 | BA66: =$BA$59*AZ66 -> 0 | BB66: -- | BC66: -- | BD66: -- | BE66: -- | BF66: --
N67: =IF(_xlfn.XLOOKUP($O$3,$Q$1:$AN$1,Q67:AN67,"-",0,1)<>"",_xlfn.XLOOKUP($O$3,$Q$1:$AN$1,Q67:AN67,"-",0,1),"") | O67: =IF(_xlfn.XLOOKUP($O$3,$Q$2:$AN$2,Q67:AN67,"-",0,1)<>"",_xlfn.XLOOKUP($O$3,$Q$2:$AN$2,Q67:AN67,"-",0,1),"") | P67: =IF(_xlfn.XLOOKUP($O$3,$Q$3:$AN$3,Q67:AN67,"-",0,1)<>"",_xlfn.XLOOKUP($O$3,$Q$3:$AN$3,Q67:AN67,"-",0,1),"") | AQ67: =_xlfn.TRANSLATE(A67,"de","en") | AW67: =_xlfn.TRANSLATE(AU67,"de","en") | AZ67: 1.1 | BA67: =$BA$59*AZ67 -> 0 | BB67: -- | BC67: -- | BD67: -- | BE67: -- | BF67: --
A68: Abnahmevergütung (feed-in- tariff) | E68: (Es wird mit einer mittleren gewichteten Abnahmevergütung gerechnet) | N68: =IF(_xlfn.XLOOKUP($O$3,$Q$1:$AN$1,Q68:AN68,"-",0,1)<>"",_xlfn.XLOOKUP($O$3,$Q$1:$AN$1,Q68:AN68,"-",0,1),"") | O68: =IF(_xlfn.XLOOKUP($O$3,$Q$2:$AN$2,Q68:AN68,"-",0,1)<>"",_xlfn.XLOOKUP($O$3,$Q$2:$AN$2,Q68:AN68,"-",0,1),"") | P68: =IF(_xlfn.XLOOKUP($O$3,$Q$3:$AN$3,Q68:AN68,"-",0,1)<>"",_xlfn.XLOOKUP($O$3,$Q$3:$AN$3,Q68:AN68,"-",0,1),"") | AQ68: =_xlfn.TRANSLATE(A68,"de","en") -> Purchase remuneration (feed-in tariff) | AW68: =_xlfn.TRANSLATE(AU68,"de","en") | AZ68: 1 | BA68: =IF(B100="",IF(AND(_Debug_Modus=_JA,N100<>""),N100,I100),B100) -> 0 | BB68: -- | BC68: -- | BD68: -- | BE68: -- | BF68: --
A69: Anteil Solarstrom mit Abnahmevergütung in % | C69: =(100-_Eigennutzungsgrad-_Anteil_LEG) -> 0 | D69: % | E69: (konstant über Lebensdauer) | AQ69: =_xlfn.TRANSLATE(A69,"de","en") -> Share of solar power with purchase remuneration in % | AW69: =_xlfn.TRANSLATE(AU69,"de","en") | AZ69: 0.9 | BA69: =$BA$59*AZ69 -> 0 | BB69: -- | BC69: -- | BD69: -- | BE69: -- | BF69: --
A70: Anteil Solarstrom mit Abnahmevergütung in kWh | C70: =(100-_Eigennutzungsgrad-_Anteil_LEG)/100*_Durchschnittlicher_Energieertrag -> 0 | D70: kWh | E70: (Ø Anteil Solarstrom mit Abnahmevergütung pro Jahr über Anlagenlebensdauer) | AQ70: =_xlfn.TRANSLATE(A70,"de","en") -> Share of solar power with purchase remuneration in kWh | AW70: =_xlfn.TRANSLATE(AU70,"de","en") | AZ70: 0.8 | BA70: =$BA$59*AZ70 -> 0 | BB70: -- | BC70: -- | BD70: -- | BE70: -- | BF70: --
A71: Abnahmevergütung Energie | C71: =IF(B71="",IF(AND(_Debug_Modus=_JA,N71<>""),N71,I71),B71) -> 0.06 | D71: CHF/kWh | E71: (inkl. MWSt.) | F71: =HYPERLINK("https://www.pvtarif.ch","aktuelle Tarife Abnahmevergütung: https://www.pvtarif.ch") -> aktuelle Tarife Abnahmevergütung: https://www.pvtarif.ch | I71: 0.06 | N71: =IF(_xlfn.XLOOKUP($O$3,$Q$1:$AN$1,Q71:AN71,"-",0,1)<>"",_xlfn.XLOOKUP($O$3,$Q$1:$AN$1,Q71:AN71,"-",0,1),"") -> 0.05 | O71: =IF(_xlfn.XLOOKUP($O$3,$Q$2:$AN$2,Q71:AN71,"-",0,1)<>"",_xlfn.XLOOKUP($O$3,$Q$2:$AN$2,Q71:AN71,"-",0,1),"") | P71: =IF(_xlfn.XLOOKUP($O$3,$Q$3:$AN$3,Q71:AN71,"-",0,1)<>"",_xlfn.XLOOKUP($O$3,$Q$3:$AN$3,Q71:AN71,"-",0,1),"") | Q71: 0.06 | T71: 0.06 | W71: 0.05 | Z71: 0.05 | AC71: 0.02 | AQ71: =_xlfn.TRANSLATE(A71,"de","en") -> Purchase remuneration for energy | AU71: Die Abnahmevergütung ist orts- und leistungsabhängig, es wird eine Mindestvergütung angenommen | AW71: =_xlfn.TRANSLATE(AU71,"de","en") -> The acceptance fee depends on location and performance, a minimum remuneration is assumed
A72: Herkunftsnachweis (HKN) | C72: =IF(B72="",IF(AND(_Debug_Modus=_JA,N72<>""),N72,I72),B72) -> 0.02 | D72: CHF/kWh | E72: (inkl. MWSt.) | I72: 0.02 | N72: =IF(_xlfn.XLOOKUP($O$3,$Q$1:$AN$1,Q72:AN72,"-",0,1)<>"",_xlfn.XLOOKUP($O$3,$Q$1:$AN$1,Q72:AN72,"-",0,1),"") -> 0.01 | O72: =IF(_xlfn.XLOOKUP($O$3,$Q$2:$AN$2,Q72:AN72,"-",0,1)<>"",_xlfn.XLOOKUP($O$3,$Q$2:$AN$2,Q72:AN72,"-",0,1),"") | P72: =IF(_xlfn.XLOOKUP($O$3,$Q$3:$AN$3,Q72:AN72,"-",0,1)<>"",_xlfn.XLOOKUP($O$3,$Q$3:$AN$3,Q72:AN72,"-",0,1),"") | Q72: 0.02 | T72: 0.01 | W72: 0.01 | Z72: 0.01 | AC72: 0.03 | AQ72: =_xlfn.TRANSLATE(A72,"de","en") -> Guarantee of Origin (HKN) | AU72: Der Herkunftsnachweis ist orts- und leistungsabhängig, es wird ein Mindest-HKN-Tarif angenommen | AW72: =_xlfn.TRANSLATE(AU72,"de","en") -> The proof of origin depends on location and performance, a minimum HKN tariff is assumed
A73: Abnahmevergütung Total | C73: =I73 -> 0.08 | D73: CHF/kWh | E73: (inkl. MWSt.) | I73: =_Rückliefertarif_Energie+_Herkunftsnachweis -> 0.08 | N73: =IF(_xlfn.XLOOKUP($O$3,$Q$1:$AN$1,Q73:AN73,"-",0,1)<>"",_xlfn.XLOOKUP($O$3,$Q$1:$AN$1,Q73:AN73,"-",0,1),"") | O73: =IF(_xlfn.XLOOKUP($O$3,$Q$2:$AN$2,Q73:AN73,"-",0,1)<>"",_xlfn.XLOOKUP($O$3,$Q$2:$AN$2,Q73:AN73,"-",0,1),"") | P73: =IF(_xlfn.XLOOKUP($O$3,$Q$3:$AN$3,Q73:AN73,"-",0,1)<>"",_xlfn.XLOOKUP($O$3,$Q$3:$AN$3,Q73:AN73,"-",0,1),"") | AQ73: =_xlfn.TRANSLATE(A73,"de","en") -> Total Purchase Fee | AW73: =_xlfn.TRANSLATE(AU73,"de","en")
N74: =IF(_xlfn.XLOOKUP($O$3,$Q$1:$AN$1,Q74:AN74,"-",0,1)<>"",_xlfn.XLOOKUP($O$3,$Q$1:$AN$1,Q74:AN74,"-",0,1),"") | O74: =IF(_xlfn.XLOOKUP($O$3,$Q$2:$AN$2,Q74:AN74,"-",0,1)<>"",_xlfn.XLOOKUP($O$3,$Q$2:$AN$2,Q74:AN74,"-",0,1),"") | P74: =IF(_xlfn.XLOOKUP($O$3,$Q$3:$AN$3,Q74:AN74,"-",0,1)<>"",_xlfn.XLOOKUP($O$3,$Q$3:$AN$3,Q74:AN74,"-",0,1),"") | AQ74: =_xlfn.TRANSLATE(A74,"de","en") | AW74: =_xlfn.TRANSLATE(AU74,"de","en")
A75: Förderung | E75: (aktuelle Berechnung der Fördermittel über Tarifrechner von Pronovo) | N75: =IF(_xlfn.XLOOKUP($O$3,$Q$1:$AN$1,Q75:AN75,"-",0,1)<>"",_xlfn.XLOOKUP($O$3,$Q$1:$AN$1,Q75:AN75,"-",0,1),"") | O75: =IF(_xlfn.XLOOKUP($O$3,$Q$2:$AN$2,Q75:AN75,"-",0,1)<>"",_xlfn.XLOOKUP($O$3,$Q$2:$AN$2,Q75:AN75,"-",0,1),"") | P75: =IF(_xlfn.XLOOKUP($O$3,$Q$3:$AN$3,Q75:AN75,"-",0,1)<>"",_xlfn.XLOOKUP($O$3,$Q$3:$AN$3,Q75:AN75,"-",0,1),"") | AQ75: =_xlfn.TRANSLATE(A75,"de","en") -> Promotion | AW75: =_xlfn.TRANSLATE(AU75,"de","en")
A76: Einmalvergütung (EIV) PVA | C76: =IF(B76="",IF(AND(_Debug_Modus=_JA,N76<>""),N76,I76),B76) -> 0 | D76: CHF | E76: https://pronovo.ch/de/services/tarifrechner/ | I76: 0 | N76: =IF(_xlfn.XLOOKUP($O$3,$Q$1:$AN$1,Q76:AN76,"-",0,1)<>"",_xlfn.XLOOKUP($O$3,$Q$1:$AN$1,Q76:AN76,"-",0,1),"") -> 28850 | O76: =IF(_xlfn.XLOOKUP($O$3,$Q$2:$AN$2,Q76:AN76,"-",0,1)<>"",_xlfn.XLOOKUP($O$3,$Q$2:$AN$2,Q76:AN76,"-",0,1),"") | P76: =IF(_xlfn.XLOOKUP($O$3,$Q$3:$AN$3,Q76:AN76,"-",0,1)<>"",_xlfn.XLOOKUP($O$3,$Q$3:$AN$3,Q76:AN76,"-",0,1),"") | Q76: 3603 | T76: 4004 | W76: 28850 | Z76: 28850 | AC76: 28850 | AQ76: =_xlfn.TRANSLATE(A76,"de","en") -> One-time remuneration (EIV) PVA | AU76: Es wird keine Förderung automatisch berechnet, es ist der Tarifrechner von Pronovo zu verwenden. | AW76: =_xlfn.TRANSLATE(AU76,"de","en") -> No subsidy is calculated automatically, the Pronovo tariff calculator is to be used.
A77: Fassadenbonus (FB) PVA | C77: =IF(B77="",IF(AND(_Debug_Modus=_JA,N77<>""),N77,I77),B77) -> 0 | D77: CHF | I77: 0 | N77: =IF(_xlfn.XLOOKUP($O$3,$Q$1:$AN$1,Q77:AN77,"-",0,1)<>"",_xlfn.XLOOKUP($O$3,$Q$1:$AN$1,Q77:AN77,"-",0,1),"") | O77: =IF(_xlfn.XLOOKUP($O$3,$Q$2:$AN$2,Q77:AN77,"-",0,1)<>"",_xlfn.XLOOKUP($O$3,$Q$2:$AN$2,Q77:AN77,"-",0,1),"") | P77: =IF(_xlfn.XLOOKUP($O$3,$Q$3:$AN$3,Q77:AN77,"-",0,1)<>"",_xlfn.XLOOKUP($O$3,$Q$3:$AN$3,Q77:AN77,"-",0,1),"") | AQ77: =_xlfn.TRANSLATE(A77,"de","en") -> Facade bonus (FB) PVA | AW77: =_xlfn.TRANSLATE(AU77,"de","en")
A78: Höhenbonus (HB) PVA | C78: =IF(B78="",IF(AND(_Debug_Modus=_JA,N78<>""),N78,I78),B78) -> 0 | D78: CHF | I78: 0 | N78: =IF(_xlfn.XLOOKUP($O$3,$Q$1:$AN$1,Q78:AN78,"-",0,1)<>"",_xlfn.XLOOKUP($O$3,$Q$1:$AN$1,Q78:AN78,"-",0,1),"") | O78: =IF(_xlfn.XLOOKUP($O$3,$Q$2:$AN$2,Q78:AN78,"-",0,1)<>"",_xlfn.XLOOKUP($O$3,$Q$2:$AN$2,Q78:AN78,"-",0,1),"") | P78: =IF(_xlfn.XLOOKUP($O$3,$Q$3:$AN$3,Q78:AN78,"-",0,1)<>"",_xlfn.XLOOKUP($O$3,$Q$3:$AN$3,Q78:AN78,"-",0,1),"") | AQ78: =_xlfn.TRANSLATE(A78,"de","en") -> Altitude Bonus (HB) PVA | AW78: =_xlfn.TRANSLATE(AU78,"de","en")
A79: Parkflächenbonus (PB) PVA | C79: =IF(B79="",IF(AND(_Debug_Modus=_JA,N79<>""),N79,I79),B79) -> 0 | D79: CHF | I79: 0 | N79: =IF(_xlfn.XLOOKUP($O$3,$Q$1:$AN$1,Q79:AN79,"-",0,1)<>"",_xlfn.XLOOKUP($O$3,$Q$1:$AN$1,Q79:AN79,"-",0,1),"") | O79: =IF(_xlfn.XLOOKUP($O$3,$Q$2:$AN$2,Q79:AN79,"-",0,1)<>"",_xlfn.XLOOKUP($O$3,$Q$2:$AN$2,Q79:AN79,"-",0,1),"") | P79: =IF(_xlfn.XLOOKUP($O$3,$Q$3:$AN$3,Q79:AN79,"-",0,1)<>"",_xlfn.XLOOKUP($O$3,$Q$3:$AN$3,Q79:AN79,"-",0,1),"") | AQ79: =_xlfn.TRANSLATE(A79,"de","en") -> Parking bonus (PB) PVA | AW79: =_xlfn.TRANSLATE(AU79,"de","en")
A80: Zahlungsfrist EIV, FB, HB und PB PVA | C80: =IF(IF(B80="",IF(AND(_Debug_Modus=_JA,N80<>""),N80,I80),B80)<K80,K80,IF(IF(B80="",IF(AND(_Debug_Modus=_JA,N80<>""),N80,I80),B80)>L80,L80,IF(B80="",IF(AND(_Debug_Modus=_JA,N80<>""),N80,I80),B80))) -> 1 | D80: Jahre | E80: (wird nur für die Förderungen von Pronovo berücksichtigt) | I80: 1 | K80: 1 | L80: =_Anlagenlebensdauer-1 -> 29 | N80: =IF(_xlfn.XLOOKUP($O$3,$Q$1:$AN$1,Q80:AN80,"-",0,1)<>"",_xlfn.XLOOKUP($O$3,$Q$1:$AN$1,Q80:AN80,"-",0,1),"") | O80: =IF(_xlfn.XLOOKUP($O$3,$Q$2:$AN$2,Q80:AN80,"-",0,1)<>"",_xlfn.XLOOKUP($O$3,$Q$2:$AN$2,Q80:AN80,"-",0,1),"") | P80: =IF(_xlfn.XLOOKUP($O$3,$Q$3:$AN$3,Q80:AN80,"-",0,1)<>"",_xlfn.XLOOKUP($O$3,$Q$3:$AN$3,Q80:AN80,"-",0,1),"") | AQ80: =_xlfn.TRANSLATE(A80,"de","en") -> Payment term EIV, FB, HB and PB PVA | AW80: =_xlfn.TRANSLATE(AU80,"de","en")
A81: sonstige Förderung PVA | C81: =IF(B81="",IF(AND(_Debug_Modus=_JA,N81<>""),N81,I81),B81) -> 0 | D81: CHF | E81: (wird direkt den Investitionskosten abgezogen) | I81: 0 | N81: =IF(_xlfn.XLOOKUP($O$3,$Q$1:$AN$1,Q81:AN81,"-",0,1)<>"",_xlfn.XLOOKUP($O$3,$Q$1:$AN$1,Q81:AN81,"-",0,1),"") | O81: =IF(_xlfn.XLOOKUP($O$3,$Q$2:$AN$2,Q81:AN81,"-",0,1)<>"",_xlfn.XLOOKUP($O$3,$Q$2:$AN$2,Q81:AN81,"-",0,1),"") | P81: =IF(_xlfn.XLOOKUP($O$3,$Q$3:$AN$3,Q81:AN81,"-",0,1)<>"",_xlfn.XLOOKUP($O$3,$Q$3:$AN$3,Q81:AN81,"-",0,1),"") | Q81: 1500 | T81: 2000 | AQ81: =_xlfn.TRANSLATE(A81,"de","en") -> Other Funding PVA | AW81: =_xlfn.TRANSLATE(AU81,"de","en")
A82: Steuereinsparungen PVA | C82: =IF(B82="",IF(AND(_Debug_Modus=_JA,N82<>""),N82,I82),B82) -> 0 | D82: CHF | E82: (Bei Privaten 20% der Investitionskosten nach Abzug Förderung; wird direkt den Investitionskosten abgezogen) | I82: 0 | N82: =IF(_xlfn.XLOOKUP($O$3,$Q$1:$AN$1,Q82:AN82,"-",0,1)<>"",_xlfn.XLOOKUP($O$3,$Q$1:$AN$1,Q82:AN82,"-",0,1),"") | O82: =IF(_xlfn.XLOOKUP($O$3,$Q$2:$AN$2,Q82:AN82,"-",0,1)<>"",_xlfn.XLOOKUP($O$3,$Q$2:$AN$2,Q82:AN82,"-",0,1),"") | P82: =IF(_xlfn.XLOOKUP($O$3,$Q$3:$AN$3,Q82:AN82,"-",0,1)<>"",_xlfn.XLOOKUP($O$3,$Q$3:$AN$3,Q82:AN82,"-",0,1),"") | Q82: 1000 | AQ82: =_xlfn.TRANSLATE(A82,"de","en") -> Tax Savings PVA | AW82: =_xlfn.TRANSLATE(AU82,"de","en")
A83: Förderung Batteriespeicher | C83: =IF(B83="",IF(AND(_Debug_Modus=_JA,N83<>""),N83,I83),B83) -> 0 | D83: CHF | E83: (wird direkt den Investitionskosten abgezogen) | I83: 0 | N83: =IF(_xlfn.XLOOKUP($O$3,$Q$1:$AN$1,Q83:AN83,"-",0,1)<>"",_xlfn.XLOOKUP($O$3,$Q$1:$AN$1,Q83:AN83,"-",0,1),"") | O83: =IF(_xlfn.XLOOKUP($O$3,$Q$2:$AN$2,Q83:AN83,"-",0,1)<>"",_xlfn.XLOOKUP($O$3,$Q$2:$AN$2,Q83:AN83,"-",0,1),"") | P83: =IF(_xlfn.XLOOKUP($O$3,$Q$3:$AN$3,Q83:AN83,"-",0,1)<>"",_xlfn.XLOOKUP($O$3,$Q$3:$AN$3,Q83:AN83,"-",0,1),"") | AQ83: =_xlfn.TRANSLATE(A83,"de","en") -> Funding for battery storage | AW83: =_xlfn.TRANSLATE(AU83,"de","en")
N84: =IF(_xlfn.XLOOKUP($O$3,$Q$1:$AN$1,Q84:AN84,"-",0,1)<>"",_xlfn.XLOOKUP($O$3,$Q$1:$AN$1,Q84:AN84,"-",0,1),"") | O84: =IF(_xlfn.XLOOKUP($O$3,$Q$2:$AN$2,Q84:AN84,"-",0,1)<>"",_xlfn.XLOOKUP($O$3,$Q$2:$AN$2,Q84:AN84,"-",0,1),"") | P84: =IF(_xlfn.XLOOKUP($O$3,$Q$3:$AN$3,Q84:AN84,"-",0,1)<>"",_xlfn.XLOOKUP($O$3,$Q$3:$AN$3,Q84:AN84,"-",0,1),"") | AQ84: =_xlfn.TRANSLATE(A84,"de","en") | AW84: =_xlfn.TRANSLATE(AU84,"de","en")
A85: Investition und Kapitalstruktur PVA | N85: =IF(_xlfn.XLOOKUP($O$3,$Q$1:$AN$1,Q85:AN85,"-",0,1)<>"",_xlfn.XLOOKUP($O$3,$Q$1:$AN$1,Q85:AN85,"-",0,1),"") | O85: =IF(_xlfn.XLOOKUP($O$3,$Q$2:$AN$2,Q85:AN85,"-",0,1)<>"",_xlfn.XLOOKUP($O$3,$Q$2:$AN$2,Q85:AN85,"-",0,1),"") | P85: =IF(_xlfn.XLOOKUP($O$3,$Q$3:$AN$3,Q85:AN85,"-",0,1)<>"",_xlfn.XLOOKUP($O$3,$Q$3:$AN$3,Q85:AN85,"-",0,1),"") | AQ85: =_xlfn.TRANSLATE(A85,"de","en") -> Investment and Capital Structure PVA | AW85: =_xlfn.TRANSLATE(AU85,"de","en")
A86: Investitionssumme PVA | C86: =IF(B86="",IF(AND(_Debug_Modus=_JA,N86<>""),N86,I86),B86) -> 15344 | D86: CHF | E86: (exkl. MWSt.) | I86: =IF(_Anlagenleistung=0,0,IF(_Anlagenleistung<10,2034*_Anlagenleistung+6191,IF(_Anlagenleistung<30, 1177*_Anlagenleistung+14762,IF(_Anlagenleistung<100,1464*_Anlagenleistung+6148,758*_Anlagenleistung+76754)))) -> 15344 | N86: =IF(_xlfn.XLOOKUP($O$3,$Q$1:$AN$1,Q86:AN86,"-",0,1)<>"",_xlfn.XLOOKUP($O$3,$Q$1:$AN$1,Q86:AN86,"-",0,1),"") | O86: =IF(_xlfn.XLOOKUP($O$3,$Q$2:$AN$2,Q86:AN86,"-",0,1)<>"",_xlfn.XLOOKUP($O$3,$Q$2:$AN$2,Q86:AN86,"-",0,1),"") | P86: =IF(_xlfn.XLOOKUP($O$3,$Q$3:$AN$3,Q86:AN86,"-",0,1)<>"",_xlfn.XLOOKUP($O$3,$Q$3:$AN$3,Q86:AN86,"-",0,1),"") | Q86: 22000 | T86: 35000 | W86: 160000 | AQ86: =_xlfn.TRANSLATE(A86,"de","en") -> Investment sum PVA | AU86: Es wird der Preis aus der Preisbeobachtungsstudie 2024 berechnet. Das ist der mittlere Preis für eine Aufdachanlage. | AW86: =_xlfn.TRANSLATE(AU86,"de","en") -> The price from the 2024 price observation study will be calculated. This is the average price for a rooftop system.
A87: Investitionskosten ZEV | C87: =IF(B87="",IF(AND(_Debug_Modus=_JA,N87<>""),N87,I87),B87) -> 0 | D87: CHF | I87: 0 | N87: =IF(_xlfn.XLOOKUP($O$3,$Q$1:$AN$1,Q87:AN87,"-",0,1)<>"",_xlfn.XLOOKUP($O$3,$Q$1:$AN$1,Q87:AN87,"-",0,1),"") -> 40000 | O87: =IF(_xlfn.XLOOKUP($O$3,$Q$2:$AN$2,Q87:AN87,"-",0,1)<>"",_xlfn.XLOOKUP($O$3,$Q$2:$AN$2,Q87:AN87,"-",0,1),"") | P87: =IF(_xlfn.XLOOKUP($O$3,$Q$3:$AN$3,Q87:AN87,"-",0,1)<>"",_xlfn.XLOOKUP($O$3,$Q$3:$AN$3,Q87:AN87,"-",0,1),"") | Q87: 0 | Z87: =Z42*1000 -> 40000 | AC87: 40000 | AQ87: =_xlfn.TRANSLATE(A87,"de","en") -> Investment costs ZEV | AU87: Es wird kein Rechenwert für die Kosten für "Investitionskosten ZEV" vorgeschlagen | AW87: =_xlfn.TRANSLATE(AU87,"de","en") -> No calculation value for the costs for "investment costs ZEV" is proposed
A88: Sonstige Aufwände PVA | C88: =IF(B88="",IF(AND(_Debug_Modus=_JA,N88<>""),N88,I88),B88) -> 0 | D88: CHF | I88: 0 | N88: =IF(_xlfn.XLOOKUP($O$3,$Q$1:$AN$1,Q88:AN88,"-",0,1)<>"",_xlfn.XLOOKUP($O$3,$Q$1:$AN$1,Q88:AN88,"-",0,1),"") | O88: =IF(_xlfn.XLOOKUP($O$3,$Q$2:$AN$2,Q88:AN88,"-",0,1)<>"",_xlfn.XLOOKUP($O$3,$Q$2:$AN$2,Q88:AN88,"-",0,1),"") | P88: =IF(_xlfn.XLOOKUP($O$3,$Q$3:$AN$3,Q88:AN88,"-",0,1)<>"",_xlfn.XLOOKUP($O$3,$Q$3:$AN$3,Q88:AN88,"-",0,1),"") | W88: 15000 | AQ88: =_xlfn.TRANSLATE(A88,"de","en") -> Other expenses PVA | AU88: Es werden keine Angaben zu den zusätzlichen Kosten der PVA gemacht. | AW88: =_xlfn.TRANSLATE(AU88,"de","en") -> No information is provided on the additional costs of the PVA.
A89: Wert Funktion Gebäudehülle | C89: =IF(B89="",IF(AND(_Debug_Modus=_JA,N89<>""),N89,I89),B89) -> 0 | D89: CHF/m2 | E89: (Sowieso- Kosten, exkl. MWSt.) | H89: (Fixed costs, excluding VAT) | I89: 0 | N89: =IF(_xlfn.XLOOKUP($O$3,$Q$1:$AN$1,Q89:AN89,"-",0,1)<>"",_xlfn.XLOOKUP($O$3,$Q$1:$AN$1,Q89:AN89,"-",0,1),"") | O89: =IF(_xlfn.XLOOKUP($O$3,$Q$2:$AN$2,Q89:AN89,"-",0,1)<>"",_xlfn.XLOOKUP($O$3,$Q$2:$AN$2,Q89:AN89,"-",0,1),"") | P89: =IF(_xlfn.XLOOKUP($O$3,$Q$3:$AN$3,Q89:AN89,"-",0,1)<>"",_xlfn.XLOOKUP($O$3,$Q$3:$AN$3,Q89:AN89,"-",0,1),"") | T89: 50 | AQ89: =_xlfn.TRANSLATE(A89,"de","en") -> Value Function Building envelope | AU89: Es werden keine Annahmen für die Funktion der Gebäudehülle gemacht. | AW89: =_xlfn.TRANSLATE(AU89,"de","en") -> No assumptions are made about the function of the building envelope.
A90: Abzug Funktion Gebäudehülle | C90: =-_PV_Fläche*_Kosten_Funktion_GH -> 0 | D90: CHF | N90: =IF(_xlfn.XLOOKUP($O$3,$Q$1:$AN$1,Q90:AN90,"-",0,1)<>"",_xlfn.XLOOKUP($O$3,$Q$1:$AN$1,Q90:AN90,"-",0,1),"") | O90: =IF(_xlfn.XLOOKUP($O$3,$Q$2:$AN$2,Q90:AN90,"-",0,1)<>"",_xlfn.XLOOKUP($O$3,$Q$2:$AN$2,Q90:AN90,"-",0,1),"") | P90: =IF(_xlfn.XLOOKUP($O$3,$Q$3:$AN$3,Q90:AN90,"-",0,1)<>"",_xlfn.XLOOKUP($O$3,$Q$3:$AN$3,Q90:AN90,"-",0,1),"") | AQ90: =_xlfn.TRANSLATE(A90,"de","en") -> Deduction function building envelope | AW90: =_xlfn.TRANSLATE(AU90,"de","en")
A91: MWSt. Investitionskosten | C91: =IF(_MWStPflicht=_nichtMWStpflichtig,(_Investitionssumme+_Investition_ZEV+_sonstige_Aufwände+_Abzug_Funktion_GH)*_MWStSatz/100,0) -> 0 | D91: CHF | N91: =IF(_xlfn.XLOOKUP($O$3,$Q$1:$AN$1,Q91:AN91,"-",0,1)<>"",_xlfn.XLOOKUP($O$3,$Q$1:$AN$1,Q91:AN91,"-",0,1),"") | O91: =IF(_xlfn.XLOOKUP($O$3,$Q$2:$AN$2,Q91:AN91,"-",0,1)<>"",_xlfn.XLOOKUP($O$3,$Q$2:$AN$2,Q91:AN91,"-",0,1),"") | P91: =IF(_xlfn.XLOOKUP($O$3,$Q$3:$AN$3,Q91:AN91,"-",0,1)<>"",_xlfn.XLOOKUP($O$3,$Q$3:$AN$3,Q91:AN91,"-",0,1),"") | AQ91: =_xlfn.TRANSLATE(A91,"de","en") -> VAT Investment costs | AW91: =_xlfn.TRANSLATE(AU91,"de","en")
A92: relevante Investitionskosten PVA | C92: =_Investitionssumme+_Investition_ZEV+_sonstige_Aufwände+_Abzug_Funktion_GH+_Vorsteuerabzug_Investitionskosten -> 15344 | D92: CHF | E92: (Investitionssumme abzgl. Sowieso- Kosten) | H92: (Investment amount minus fixed costs) | N92: =IF(_xlfn.XLOOKUP($O$3,$Q$1:$AN$1,Q92:AN92,"-",0,1)<>"",_xlfn.XLOOKUP($O$3,$Q$1:$AN$1,Q92:AN92,"-",0,1),"") | O92: =IF(_xlfn.XLOOKUP($O$3,$Q$2:$AN$2,Q92:AN92,"-",0,1)<>"",_xlfn.XLOOKUP($O$3,$Q$2:$AN$2,Q92:AN92,"-",0,1),"") | P92: =IF(_xlfn.XLOOKUP($O$3,$Q$3:$AN$3,Q92:AN92,"-",0,1)<>"",_xlfn.XLOOKUP($O$3,$Q$3:$AN$3,Q92:AN92,"-",0,1),"") | AQ92: =_xlfn.TRANSLATE(A92,"de","en") -> Relevant investment costs PVA | AW92: =_xlfn.TRANSLATE(AU92,"de","en")
A93: Investition netto PVA (abzgl. Förderung) | C93: =_relevante_Investitionskosten-_Einmalvergütung-_Fassadenbonus-_Höhenbonus-_Parkflächenbonus-_direkteFörderung-_Steuereinsparung -> 15344 | D93: CHF | E93: (abzgl. Fördergelder und Einsparungen) | H93: (abzgl. Fördergelder und Einsparungen) | N93: =IF(_xlfn.XLOOKUP($O$3,$Q$1:$AN$1,Q93:AN93,"-",0,1)<>"",_xlfn.XLOOKUP($O$3,$Q$1:$AN$1,Q93:AN93,"-",0,1),"") | O93: =IF(_xlfn.XLOOKUP($O$3,$Q$2:$AN$2,Q93:AN93,"-",0,1)<>"",_xlfn.XLOOKUP($O$3,$Q$2:$AN$2,Q93:AN93,"-",0,1),"") | P93: =IF(_xlfn.XLOOKUP($O$3,$Q$3:$AN$3,Q93:AN93,"-",0,1)<>"",_xlfn.XLOOKUP($O$3,$Q$3:$AN$3,Q93:AN93,"-",0,1),"") | AQ93: =_xlfn.TRANSLATE(A93,"de","en") -> Net investment PVA (less subsidy) | AW93: =_xlfn.TRANSLATE(AU93,"de","en")
E94: Zinssatz [%] | F94: Laufzeit [Jahre] | G94: Rechenwert Zinssatz [%] | H94: Rechenwert Laufzeit [Jahre] | N94: =IF(_xlfn.XLOOKUP($O$3,$Q$1:$AN$1,Q94:AN94,"-",0,1)<>"",_xlfn.XLOOKUP($O$3,$Q$1:$AN$1,Q94:AN94,"-",0,1),"") | O94: =IF(_xlfn.XLOOKUP($O$3,$Q$2:$AN$2,Q94:AN94,"-",0,1)<>"",_xlfn.XLOOKUP($O$3,$Q$2:$AN$2,Q94:AN94,"-",0,1),"") | P94: =IF(_xlfn.XLOOKUP($O$3,$Q$3:$AN$3,Q94:AN94,"-",0,1)<>"",_xlfn.XLOOKUP($O$3,$Q$3:$AN$3,Q94:AN94,"-",0,1),"") | AQ94: =_xlfn.TRANSLATE(A94,"de","en") | AW94: =_xlfn.TRANSLATE(AU94,"de","en")
A95: Eigenkapital PVA | C95: =I95 -> 15344 | D95: CHF | E95: 0 | G95: =IF(ISNUMBER(IF(_Debug_Modus=_JA,O95,E95)),IF(_Debug_Modus=_JA,O95,E95),0) -> 0 | H95: =_Anlagenlebensdauer -> 30 | I95: =_Investition_netto-C96-C97 -> 15344 | N95: =IF(_xlfn.XLOOKUP($O$3,$Q$1:$AN$1,Q95:AN95,"-",0,1)<>"",_xlfn.XLOOKUP($O$3,$Q$1:$AN$1,Q95:AN95,"-",0,1),"") | O95: =IF(_xlfn.XLOOKUP($O$3,$Q$2:$AN$2,Q95:AN95,"-",0,1)<>"",_xlfn.XLOOKUP($O$3,$Q$2:$AN$2,Q95:AN95,"-",0,1),"") | P95: =IF(_xlfn.XLOOKUP($O$3,$Q$3:$AN$3,Q95:AN95,"-",0,1)<>"",_xlfn.XLOOKUP($O$3,$Q$3:$AN$3,Q95:AN95,"-",0,1),"") | AQ95: =_xlfn.TRANSLATE(A95,"de","en") -> Equity PVA | AW95: =_xlfn.TRANSLATE(AU95,"de","en")
A96: Fremdkapital 1 PVA | C96: 0 | D96: CHF | G96: =IF(ISNUMBER(IF(_Debug_Modus=_JA,O96,E96)),IF(_Debug_Modus=_JA,O96,E96),0) -> 0 | H96: =IF(IF(F96="",IF(AND(_Debug_Modus=_JA,P96<>""),P96,I96),F96)<K96,K96,IF(IF(F96="",IF(AND(_Debug_Modus=_JA,P96<>""),P96,I96),F96)>L96,L96,IF(F96="",IF(AND(_Debug_Modus=_JA,P96<>""),P96,I96),F96))) -> 0 | I96: 0 | K96: 0 | L96: =H95 -> 30 | N96: =IF(_xlfn.XLOOKUP($O$3,$Q$1:$AN$1,Q96:AN96,"-",0,1)<>"",_xlfn.XLOOKUP($O$3,$Q$1:$AN$1,Q96:AN96,"-",0,1),"") | O96: =IF(_xlfn.XLOOKUP($O$3,$Q$2:$AN$2,Q96:AN96,"-",0,1)<>"",_xlfn.XLOOKUP($O$3,$Q$2:$AN$2,Q96:AN96,"-",0,1),"") | P96: =IF(_xlfn.XLOOKUP($O$3,$Q$3:$AN$3,Q96:AN96,"-",0,1)<>"",_xlfn.XLOOKUP($O$3,$Q$3:$AN$3,Q96:AN96,"-",0,1),"") | Q96: 10000 | R96: 1 | S96: 10 | T96: 15000 | U96: 1.5 | V96: 15 | AQ96: =_xlfn.TRANSLATE(A96,"de","en") -> Debt 1 PVA | AW96: =_xlfn.TRANSLATE(AU96,"de","en")
A97: Fremdkapital 2 PVA | C97: =IF(B97="",IF(AND(_Debug_Modus=_JA,N97<>""),N97,I97),B97) -> 0 | D97: CHF | G97: =IF(ISNUMBER(IF(_Debug_Modus=_JA,O97,E97)),IF(_Debug_Modus=_JA,O97,E97),0) -> 0 | H97: =IF(IF(F97="",IF(AND(_Debug_Modus=_JA,P97<>""),P97,I97),F97)<K97,K97,IF(IF(F97="",IF(AND(_Debug_Modus=_JA,P97<>""),P97,I97),F97)>L97,L97,IF(F97="",IF(AND(_Debug_Modus=_JA,P97<>""),P97,I97),F97))) -> 0 | I97: 0 | K97: 0 | L97: =H95 -> 30 | N97: =IF(_xlfn.XLOOKUP($O$3,$Q$1:$AN$1,Q97:AN97,"-",0,1)<>"",_xlfn.XLOOKUP($O$3,$Q$1:$AN$1,Q97:AN97,"-",0,1),"") | O97: =IF(_xlfn.XLOOKUP($O$3,$Q$2:$AN$2,Q97:AN97,"-",0,1)<>"",_xlfn.XLOOKUP($O$3,$Q$2:$AN$2,Q97:AN97,"-",0,1),"") | P97: =IF(_xlfn.XLOOKUP($O$3,$Q$3:$AN$3,Q97:AN97,"-",0,1)<>"",_xlfn.XLOOKUP($O$3,$Q$3:$AN$3,Q97:AN97,"-",0,1),"") | AQ97: =_xlfn.TRANSLATE(A97,"de","en") -> Debt capital 2 PVA | AW97: =_xlfn.TRANSLATE(AU97,"de","en")
N98: =IF(_xlfn.XLOOKUP($O$3,$Q$1:$AN$1,Q98:AN98,"-",0,1)<>"",_xlfn.XLOOKUP($O$3,$Q$1:$AN$1,Q98:AN98,"-",0,1),"") | O98: =IF(_xlfn.XLOOKUP($O$3,$Q$2:$AN$2,Q98:AN98,"-",0,1)<>"",_xlfn.XLOOKUP($O$3,$Q$2:$AN$2,Q98:AN98,"-",0,1),"") | P98: =IF(_xlfn.XLOOKUP($O$3,$Q$3:$AN$3,Q98:AN98,"-",0,1)<>"",_xlfn.XLOOKUP($O$3,$Q$3:$AN$3,Q98:AN98,"-",0,1),"") | AQ98: =_xlfn.TRANSLATE(A98,"de","en") | AW98: =_xlfn.TRANSLATE(AU98,"de","en")
A99: Investition und Kapitalstruktur Batterie | N99: =IF(_xlfn.XLOOKUP($O$3,$Q$1:$AN$1,Q99:AN99,"-",0,1)<>"",_xlfn.XLOOKUP($O$3,$Q$1:$AN$1,Q99:AN99,"-",0,1),"") | O99: =IF(_xlfn.XLOOKUP($O$3,$Q$2:$AN$2,Q99:AN99,"-",0,1)<>"",_xlfn.XLOOKUP($O$3,$Q$2:$AN$2,Q99:AN99,"-",0,1),"") | P99: =IF(_xlfn.XLOOKUP($O$3,$Q$3:$AN$3,Q99:AN99,"-",0,1)<>"",_xlfn.XLOOKUP($O$3,$Q$3:$AN$3,Q99:AN99,"-",0,1),"") | AQ99: =_xlfn.TRANSLATE(A99,"de","en") -> Investment and Capital Structure Battery | AW99: =_xlfn.TRANSLATE(AU99,"de","en")
A100: Investitionssumme Batterie | C100: =IF(B100="",IF(AND(_Debug_Modus=_JA,N100<>""),N100,I100),B100) -> 0 | D100: CHF | E100: (exkl. MWSt.) | I100: =_Speicherkapazität*700 -> 0 | N100: =IF(_xlfn.XLOOKUP($O$3,$Q$1:$AN$1,Q100:AN100,"-",0,1)<>"",_xlfn.XLOOKUP($O$3,$Q$1:$AN$1,Q100:AN100,"-",0,1),"") | O100: =IF(_xlfn.XLOOKUP($O$3,$Q$2:$AN$2,Q100:AN100,"-",0,1)<>"",_xlfn.XLOOKUP($O$3,$Q$2:$AN$2,Q100:AN100,"-",0,1),"") | P100: =IF(_xlfn.XLOOKUP($O$3,$Q$3:$AN$3,Q100:AN100,"-",0,1)<>"",_xlfn.XLOOKUP($O$3,$Q$3:$AN$3,Q100:AN100,"-",0,1),"") | Q100: 5000 | W100: 50000 | AQ100: =_xlfn.TRANSLATE(A100,"de","en") -> Investment sum battery | AU100: Der Defaultwert wird mit durchschnittlichen Kosten von 700 CHF/kWh berechnet. | AW100: =_xlfn.TRANSLATE(AU100,"de","en") -> The default value is calculated with an average cost of 700 CHF/kWh.
...

Sheet Berechnungen
A1: Geldflusstabelle | C1: HS | E1: HS | F1: HS | G1: HS | H1: HS | J1: HS | L1: HS | O1: HS | P1: HS | R1: HS | T1: HS | V1: HS | X1: HS | Z1: HS | AA1: HS | AF1: HS | AG1: HS | AH1: HS | AI1: HS | AJ1: HS | AK1: HS | AL1: HS | AM1: HS | AN1: HS | AO1: HS | AQ1: HS | AR1: HS | AS1: HS | AT1: HS | AU1: HS | AV1: HS | AW1: HS | BF1: HS | BG1: HS | BN1: HS | BR1: HS | BT1: HS | BX1: HS | BZ1: HS | CD1: HS
AF2: =Eingaben!A114 -> Kontrollgänge | AG2: =Eingaben!A115 -> Audits / Sicherheitsnachweise | AH2: =Eingaben!A116 -> Überwachung | AI2: =Eingaben!A117 -> Administration | AJ2: =Eingaben!A118 -> Datenverbindung | AK2: =Eingaben!A53 -> Betriebskosten ZEV (Administration und Abrechnung) | AL2: =Eingaben!A66 -> Betriebskosten LEG (Administration und Abrechnung) | AM2: =Eingaben!A119 -> Versicherung | AN2: =Eingaben!A120 -> Reparaturen | AO2: =Eingaben!A121 -> Reinigung Anlage | AP2: =Eingaben!A122 -> Grünbewuchs Pflege | AQ2: =Eingaben!A123 -> Transformator | AR2: =Eingaben!A124 -> Dach- / Raummiete | AS2: =Eingaben!A125 -> Wechselrichteraustausch | AT2: =Eingaben!A130 -> Ersatz Batteriespeicher | AU2: =Eingaben!A129 -> Unterhaltskosten Batteriespeicher
A3: Projektnummer: | M3: =IF(_Projektnummer<>"",_Projektnummer,"") | AF3: =VLOOKUP(AF2,Eingaben!$A$114:$H$125,3,FALSE) -> 830.688 | AG3: =VLOOKUP(AG2,Eingaben!$A$114:$H$125,3,FALSE) -> 0 | AH3: =VLOOKUP(AH2,Eingaben!$A$114:$H$125,3,FALSE) -> 69 | AI3: =VLOOKUP(AI2,Eingaben!$A$114:$H$125,3,FALSE) -> 99 | AJ3: =VLOOKUP(AJ2,Eingaben!$A$114:$H$125,3,FALSE) -> 120 | AK3: =VLOOKUP(AK2,Eingaben!$A$53:$H$133,3,FALSE) -> 0 | AL3: =VLOOKUP(AL2,Eingaben!$A$53:$H$133,3,FALSE) -> 0 | AM3: =VLOOKUP(AM2,Eingaben!$A$114:$H$125,3,FALSE) -> 49.1008 | AN3: =VLOOKUP(AN2,Eingaben!$A$114:$H$125,3,FALSE) -> 1215.344 | AO3: =VLOOKUP(AO2,Eingaben!$A$114:$H$125,3,FALSE) -> 1056.25 | AP3: =VLOOKUP(AP2,Eingaben!$A$114:$H$125,3,FALSE) -> 0 | AQ3: =VLOOKUP(AQ2,Eingaben!$A$114:$H$125,3,FALSE) -> 0 | AR3: =VLOOKUP(AR2,Eingaben!$A$114:$H$125,3,FALSE) -> 0 | AS3: =VLOOKUP(AS2,Eingaben!$A$114:$H$125,3,FALSE) -> 1175 | AT3: =VLOOKUP(AT2,Eingaben!$A$129:$F$130,3,FALSE) -> 0 | AU3: =VLOOKUP(AU2,Eingaben!$A$129:$F$130,3,FALSE) -> 0
A4: Projektbezeichnung: | M4: =_Projektbezeichnung&", "&_Standort -> , | AF4: =VLOOKUP(AF2,Eingaben!$A$114:$H$125,6,FALSE) -> 5 | AG4: =VLOOKUP(AG2,Eingaben!$A$114:$H$125,6,FALSE) -> 20 | AH4: =VLOOKUP(AH2,Eingaben!$A$114:$H$125,6,FALSE) -> 1 | AI4: =VLOOKUP(AI2,Eingaben!$A$114:$H$125,6,FALSE) -> 1 | AJ4: =VLOOKUP(AJ2,Eingaben!$A$114:$H$125,6,FALSE) -> 1 | AK4: 1 | AL4: 1 | AM4: =VLOOKUP(AM2,Eingaben!$A$114:$H$125,6,FALSE) -> 1 | AN4: =VLOOKUP(AN2,Eingaben!$A$114:$H$125,6,FALSE) -> 8 | AO4: =VLOOKUP(AO2,Eingaben!$A$114:$H$125,6,FALSE) -> 8 | AP4: =VLOOKUP(AP2,Eingaben!$A$114:$H$125,6,FALSE) -> 1 | AQ4: =VLOOKUP(AQ2,Eingaben!$A$114:$H$125,6,FALSE) -> 1 | AR4: =VLOOKUP(AR2,Eingaben!$A$114:$H$125,6,FALSE) -> 1 | AS4: =VLOOKUP(AS2,Eingaben!$A$114:$H$125,6,FALSE) -> 16 | AT4: =VLOOKUP(AT2,Eingaben!$A$129:$F$130,6,FALSE) -> 16 | AU4: =VLOOKUP(AU2,Eingaben!$A$129:$F$130,6,FALSE) -> 1 | BM4: =_xlfn.TRANSLATE(BM5,"de","en") -> Cost-effectiveness without battery storage | BS4: =_xlfn.TRANSLATE(BS5,"de","en") -> Cost-effectiveness with battery storage | BY4: =_xlfn.TRANSLATE(BY5,"de","en") -> Cost-effectiveness only battery storage
C5: =_xlfn.TRANSLATE(C6,"de","en") -> Year with lifetime | D5: =_xlfn.TRANSLATE(D6,"de","en") -> Year with battery life | E5: =_xlfn.TRANSLATE(E6,"de","en") -> Year of battery renewal | F5: =_xlfn.TRANSLATE(F6,"de","en") -> Year Payment Remuneration | G5: =_xlfn.TRANSLATE(G6,"de","en") -> Year of debt 1 PVA | H5: =_xlfn.TRANSLATE(H6,"de","en") -> Year of debt 2 PVA | I5: =_xlfn.TRANSLATE(I6,"de","en") -> Year of Debt Battery | J5: =_xlfn.TRANSLATE(J6,"de","en") -> Degradation PV system [% of new output] | ... BL5: =_xlfn.TRANSLATE(BL6,"de","en") -> Debt capital 1 battery Annuity [CHF] | BM5: Wirtschaftlichkeit ohne Batteriespeicher | BS5: Wirtschaftlichkeit mit Batteriespeicher | BY5: Wirtschaftlichkeit nur Batteriespeicher
B6: Jahr | C6: Jahr mit Lebensdauer | D6: Jahr mit Lebensdauer Batterie | E6: Jahr mit Erneuerung Batterie | F6: Jahr Auszahlung Vergütung | G6: Jahr Fremdkapital 1 PVA | H6: Jahr Fremdkapital 2 PVA | I6: Jahr Fremdkapital Batterie | J6: Degradation PV- Anlage [% der Neuleistung] | K6: Energieertrag [kWh] | L6: Degradation Batterie [% der Neukapazität] | M6: Batteriekapazität [kWh] | N6: Erhöhung EV mit Batterie [%] | O6: Eingelagerter Strom EV Batterie [kWh] | P6: Verluste Speicher [kWh] | Q6: Energie aus Speicher [kWh] | R6: Rückliefertarif mit Teuerung [CHF/kWh] | S6: Abnahme-vergütung [CHF] | T6: Tarif LEG mit Teuerung [CHF/kWh] | U6: Vergütung Stromverkauf LEG inkl. Abrechnunggebühr [CHF] | V6: eingesparter Bezug mit Teuerung [CHF/kWh] | W6: eingesparter Bezug / Stromverkauf ZEV [CHF] | X6: Leistungstarif mit Teuerung [CHF/kW/m] | Y6: Einsparung / PV Kosten ZEV Leistung [CHF] | Z6: Abrechnungsgebühren ZEV [CHF/kWh] | AA6: Grundkosten ZEV [CHF/Monat] | AB6: Abrechnungsgebühr ZEV mit Grundkosten [CHF] | AC6: eingesparter Bezug / Stromverkauf ZEV Batterie [CHF] | AD6: Einsparung / PV Kosten ZEV Leistung Batterie [CHF] | AE6: Kosten Energie für Ladung Batteriespeicher [CHF] | AF6: Unterhaltskosten nach Wartungstabelle [CHF] | AG6: Unterhaltskosten nach Wartungstabelle [CHF] | AH6: Unterhaltskosten nach Wartungstabelle [CHF] | AI6: Unterhaltskosten nach Wartungstabelle [CHF] | AJ6: Unterhaltskosten nach Wartungstabelle [CHF] | AK6: Unterhaltskosten nach Wartungstabelle [CHF] | AL6: Unterhaltskosten nach Wartungstabelle [CHF] | AM6: Unterhaltskosten nach Wartungstabelle [CHF] | AN6: Unterhaltskosten nach Wartungstabelle [CHF] | AO6: Unterhaltskosten nach Wartungstabelle [CHF] | AP6: Unterhaltskosten nach Wartungstabelle [CHF] | AQ6: Unterhaltskosten nach Wartungstabelle [CHF] | AR6: Unterhaltskosten nach Wartungstabelle [CHF] | AS6: Unterhaltskosten nach Wartungstabelle [CHF] | AT6: Unterhaltskosten nach Wartungstabelle [CHF] | AU6: Unterhaltskosten nach Wartungstabelle [CHF] | AV6: Unterhaltskosten nach Wartungstabelle Summe [CHF] | AW6: Faktor Teuerung Unterhaltskosten [CHF] | AX6: Betrieb und Unterhalts- Kosten PVA [CHF] | AY6: Betriebs- und Abrechungs-kosten ZEV [CHF] | AZ6: Betriebs- und Abrechungs-kosten LEG [CHF] | BA6: Betrieb und Unterhalts- Batteriespeicher [CHF] | BB6: MWSt- Umsatzsteuer [CHF] | BC6: MWSt- Abzug PVA Betrieb und Unterhalt [CHF] | BD6: MWSt- Abzug Batterie Betrieb und Unterhalt [CHF] | BE6: Auszahlung Vergütung [CHF] | BF6: Kapital EIV Für Verzinsung [CHF] | BG6: Verzinsung EIV [CHF] | BH6: Eigenkapitalkosten PVA (Verzinsung jährlich) Annuität [CHF] | BI6: Fremdkapital 1 PVA Annuität [CHF] | BJ6: Fremdkapital 2 PVA Annuität [CHF] | BK6: Eigenkapitalkosten Batterie (Verzinsung jährlich) Annuität [CHF] | BL6: Fremdkapital 1 Batterie Annuität [CHF] | BM6: Cash Flow netto [CHF] | BN6: Cash Flow netto ohne Fremdk. [CHF] | BO6: Kapitalentwicklung Cash Flow netto [CHF] | BP6: Barwert Cash Flow netto NPV [CHF] | BQ6: Kapitalentwicklung NPV [CHF] | BR6: Amortisationszeit ohne Speicher | BS6: Cash Flow netto [CHF] | BT6: Cash Flow netto ohne Fremdk. [CHF] | BU6: Kapitalentwicklung Cash Flow netto [CHF] | BV6: Barwert Cash Flow netto NPV [CHF] | BW6: Kapitalentwicklung NPV [CHF] | BX6: Amortisationszeit mit Speicher | BY6: Cash Flow netto [CHF] | BZ6: Cash Flow netto ohne Fremdk. [CHF] | CA6: Kapitalentwicklung Cash Flow netto [CHF] | CB6: Barwert Cash Flow netto NPV [CHF] | CC6: Kapitalentwicklung NPV [CHF] | CD6: Amortisationszeit nur Speicher
B7: 0 | M7: =_Speicherkapazität -> 0 | R7: =_Rückliefertarif -> 0.08 | T7: =IF(_LEG="JA",_Tarif_LEG,0) -> 0.096666667 | V7: =_ersetzterBezugstarifZEV -> 0.232 | X7: =_Leistungskosten_ZEV -> 1.5 | Z7: =IF(_ZEV="JA",_Tarif_Abrechnung_ZEV,0) -> 0 | AA7: =IF(_ZEV="JA",_Grundkosten_Abrechnung_ZEV,0) -> 8 | BM7: =-1*(_relevante_Investitionskosten-_direkteFörderung-_Steuereinsparung-_Fremdkapital1-_Fremdkapital2) -> -15344 | BN7: =-1*(_relevante_Investitionskosten-_direkteFörderung-_Steuereinsparung) -> -15344 | BP7: =BM7 -> -15344 | BS7: =-1*(_relevante_Investitionskosten+_relevante_Investitionskosten_Batterie-_direkteFörderung-_Steuereinsparung-_Förderung_Batterie-_Fremdkapital1-_Fremdkapital2-_Fremdkapital_Batterie) -> -15344 | BT7: =-1*(_relevante_Investitionskosten+_relevante_Investitionskosten_Batterie-_direkteFörderung-_Förderung_Batterie-_Steuereinsparung) -> -15344 | BV7: =BS7 -> -15344 | BY7: =-1*(_relevante_Investitionskosten_Batterie-_Förderung_Batterie-_Fremdkapital_Batterie) -> 0 | BZ7: =-1*(_relevante_Investitionskosten_Batterie-_Förderung_Batterie) -> 0 | CB7: =BY7 -> 0
B8: 1 | C8: =IF(B8<=_Anlagenlebensdauer,TRUE,FALSE) -> TRUE | D8: =IF(AND(_Batterie=_JA,B8<=_Lebensdauer_Speicher),TRUE,FALSE) -> FALSE | E8: =IF(AND(_Batterie=_JA,_Kosten_Ersatz_Speicher>0),IF(AND(B8<=_Jahr_Ersatz_Speicher-1+_Lebensdauer_Speicher,C8),TRUE,FALSE),IF(AND(_Batterie=_JA,B8<=_Lebensdauer_Speicher,C8),TRUE,FALSE)) -> FALSE | F8: =IF(B8=_ZahlungsfristEIVFB,TRUE,FALSE) -> TRUE | G8: =IF(B8<=_Laufzeit_Fremdkapital1,TRUE,FALSE) -> FALSE | H8: =IF(B8<=_Laufzeit_Fremdkapital2,TRUE,FALSE) -> FALSE | I8: =IF(B8<=_Laufzeit_Fremdkapital_Batterie,TRUE,FALSE) -> FALSE | J8: =(1-((B8-1)*_Degradation)/100) -> 1 | K8: =IF(C8,_Anlagenleistung*J8*_spez_Jahresenergieertrag,"") -> 4500 | L8: 1 | M8: =IF(E8,_Speicherkapazität*L8,"") | N8: =IF(E8,_Erhöhung_Eigennutzungsgrad_Speicher,"") | O8: =IF(E8,N8/100*K8,"") | P8: =IF(E8,(O8)*(1-_Speicher_Wirkungsgrad/100),"") | Q8: =IF(E8,O8-P8,"") | R8: =IF(C8,R7,"") -> 0.08 | S8: =IF(C8,K8*(1-_Eigennutzungsgrad/100-_Anteil_LEG/100)*R8,"") -> -3.9968029e-14 | T8: =IF(C8,T7,"") -> 0.096666667 | U8: =IF(C8,K8*(_Anteil_LEG/100)*T8,"") -> 290.27366 | V8: =IF(C8,V7,"") -> 0.232 | W8: =IF(C8,K8*(_Eigennutzungsgrad/100)*V8,"") -> 347.34322 | X8: =IF(C8,X7,"") -> 1.5 | Y8: =IF(C8,_Summe_Leistungsspitzen*_Reduktion_Leistungsspitzen/100*J8*X8,"") -> 0 | Z8: =IF(C8,Z7,"") -> 0 | AA8: =IF(C8,AA7,"") -> 8 | AB8: =IF(C8,K8*(_Eigennutzungsgrad/100)*Z8+AA8*_Anzahl_Verbraucher*12,"") -> 0 | AC8: =IF(E8,Q8*V8,IF(C8,0,"")) -> 0 | AD8: =IF(E8,_Summe_Leistungsspitzen*_Reduktion_Leistungsspitzen_Batterie/100*L8*X8,IF(C8,0,"")) -> 0 | AE8: =IF(E8,-O8*R8,IF(C8,0,"")) -> 0 | AF8: =IF(INT($B8/AF$4)=$B8/AF$4,AF$3,0) -> 0 | AG8: =IF(INT($B8/AG$4)=$B8/AG$4,AG$3,0) -> 0 | AH8: =IF(INT($B8/AH$4)=$B8/AH$4,AH$3,0) -> 69 | AI8: =IF(INT($B8/AI$4)=$B8/AI$4,AI$3,0) -> 99 | AJ8: =IF(INT($B8/AJ$4)=$B8/AJ$4,AJ$3,0) -> 120 | AK8: =IF(INT($B8/AK$4)=$B8/AK$4,AK$3,0) -> 0 | AL8: =IF(INT($B8/AL$4)=$B8/AL$4,AL$3,0) -> 0 | AM8: =IF(INT($B8/AM$4)=$B8/AM$4,AM$3,0) -> 49.1008 | ... AU8: =IF(INT($B8/AU$4)=$B8/AU$4,AU$3,0) -> 0 | AV8: =SUM(AF8:AJ8,AM8:AS8) -> 337.1008 | AW8: 1 | AX8: =IF(C8,(-IF(_Berechnungsart_Unterhaltskosten=_Unterhalt_Preis_pro_kWh,K8*_spez_Unterhaltskosten,AV8))*AW8,"") -> -337.1008 | AY8: =IF(C8,(-AK8)*AW8,"") -> 0 | AZ8: =IF(C8,(-AL8)*AW8,"") -> 0 | BA8: =IF(E8,-(AT8+AU8)*AW8,IF((C8),0,"")) -> 0 | BB8: =IF(C8,-IF(_MWStPflicht=_MWStpflichtig,(S8)*_MWStSatz/100,0),"") -> 3.2374103e-15 | BC8: =IF(C8,-IF(_MWStPflicht=_MWStpflichtig,(AX8)*_MWStSatz/100,0),"") -> 27.305165 | BD8: =IF(E8,-IF(_MWStPflicht=_MWStpflichtig,(BA8)*_MWStSatz/100,0),IF(C8,0,"")) -> 0 | BE8: =IF(C8,IF(F8,_Einmalvergütung+_Fassadenbonus+_Höhenbonus+_Fassadenbonus,0),"") -> 0 | BF8: =_Einmalvergütung+_Fassadenbonus -> 0 | BG8: =IF(C8,PMT(_Zins_Eigenkapital/100,_ZahlungsfristEIVFB,BF8)+BF8/_ZahlungsfristEIVFB,"") -> 0 | BH8: =IF(C8,PMT(_Zins_Eigenkapital/100,_Anlagenlebensdauer,_Eigenkapital)+BG8,"") -> -511.46667 | BI8: =IF(C8,IF(G8,PMT(_Zins_Fremdkapital1/100,_Laufzeit_Fremdkapital1,_Fremdkapital1),0),"") -> 0 | BJ8: =IF(C8,IF(H8,PMT(_Zins_Fremdkapital2/100,_Laufzeit_Fremdkapital2,_Fremdkapital2),0),"") -> 0 | BK8: =IF(D8,PMT(_Zins_Eigenkapital_Batterie/100,_Lebensdauer_Speicher,_Eigenkapital_Batterie)+BJ8,IF(C8,0,"")) -> 0 | BL8: =IF(D8,IF(I8,PMT(_Zins_Fremdkapital_Batterie/100,_Laufzeit_Fremdkapital_Batterie,_Fremdkapital_Batterie),0),IF(C8,0,"")) -> 0 | BM8: =IF(C8,S8+U8+W8+AB8+Y8+AX8+AY8+AZ8+BB8+BC8+BE8+BI8+BJ8,"") -> 327.82125 | BN8: =IF($C8,BM8-BI8-BJ8,"") -> 327.82125 | BO8: =IF($C8,IF($C8,BM7+BM8,0),"") -> -15016.179 | BP8: =IF(C8,BM8*(1+_Zins_Eigenkapital/100)^-B8,"") -> 327.82125 | BQ8: =IF($C8,BP7+BP8,"") -> -15016.179 | BR8: =IF($C8,IF(AND(BQ7<0,BQ8>=0),B8,""),"") | BS8: =IF(C8,BM8+BA8+AC8+AD8+AE8+BD8+BL8,"") -> 327.82125 | BT8: =IF($C8,BS8-BI8-BJ8-BL8,"") -> 327.82125 | BU8: =IF($C8,IF($C8,BS7+BS8,0),"") -> -15016.179 | BV8: =IF(C8,BS8*(1+_Zins_Eigenkapital/100)^-B8,"") -> 327.82125 | BW8: =IF($C8,BV7+BV8,"") -> -15016.179 | BX8: =IF($C8,IF(AND(BW7<0,BW8>=0),B8,""),"") | BY8: =IF(E8,AC8+AD8+BL8+BA8+BD8+AE8,"") | BZ8: =IF(E8,BY8-BL8,"") | CA8: =IF($E8,IF($C8,BY7+BY8,0),"") | CB8: =IF(E8,BY8*(1+_Zins_Eigenkapital/100)^-I8,"") | CC8: =IF($E8,CB7+CB8,"") | CD8: =IF($E8,IF(AND(CC7<0,CC8>=0),B8,""),"")
B9: =B8+1 -> 2 | C9: =IF(B9<=_Anlagenlebensdauer,TRUE,FALSE) -> TRUE | D9: =IF(AND(_Batterie=_JA,B9<=_Lebensdauer_Speicher),TRUE,FALSE) -> FALSE | E9: =IF(AND(_Batterie=_JA,_Kosten_Ersatz_Speicher>0),IF(AND(B9<=_Jahr_Ersatz_Speicher-1+_Lebensdauer_Speicher,C9),TRUE,FALSE),IF(AND(_Batterie=_JA,B9<=_Lebensdauer_Speicher,C9),TRUE,FALSE)) -> FALSE | F9: =IF(B9=_ZahlungsfristEIVFB,TRUE,FALSE) -> FALSE | G9: =IF(B9<=_Laufzeit_Fremdkapital1,TRUE,FALSE) -> FALSE | H9: =IF(B9<=_Laufzeit_Fremdkapital2,TRUE,FALSE) -> FALSE | I9: =IF(B9<=_Laufzeit_Fremdkapital_Batterie,TRUE,FALSE) -> FALSE | J9: =(1-((B9-1)*_Degradation)/100) -> 0.996 | K9: =IF(C9,_Anlagenleistung*J9*_spez_Jahresenergieertrag,"") -> 4482 | L9: =IF(B9=_Jahr_Ersatz_Speicher,1,IF((L8-_Degradation_Speicher_Jahr/100)<0,0,L8-_Degradation_Speicher_Jahr/100)) -> 0.98666667 | M9: =IF(E9,_Speicherkapazität*L9,"") | N9: =IF(E9,_Erhöhung_Eigennutzungsgrad_Speicher*L9,"") | O9: =IF(E9,N9/100*K9,"") | P9: =IF(E9,(O9)*(1-_Speicher_Wirkungsgrad/100),"") | Q9: =IF(E9,O9-P9,"") | R9: =IF(C9,R8*(1+_Teuerungsrate/100),"") -> 0.0804 | S9: =IF(C9,K9*(1-_Eigennutzungsgrad/100-_Anteil_LEG/100)*R9,"") -> -4.0007198e-14 | T9: =IF(C9,T8*(1+_Teuerungsrate/100),"") -> 0.09715 | U9: =IF(C9,K9*(_Anteil_LEG/100)*T9,"") -> 290.55813 | V9: =IF(C9,V8*(1+_Teuerungsrate/100),"") -> 0.23316 | W9: =IF(C9,K9*(_Eigennutzungsgrad/100)*V9,"") -> 347.68362 | X9: =IF(C9,X8*(1+_Teuerungsrate/100),"") -> 1.5075 | Y9: =IF(C9,_Summe_Leistungsspitzen*_Reduktion_Leistungsspitzen/100*J9*X9,"") -> 0 | Z9: =IF(C9,Z8*(1+_Teuerungsrate/100),"") -> 0 | AA9: =IF(C9,AA8*(1+_Teuerungsrate/100),"") -> 8.04 | AB9: =IF(C9,K9*(_Eigennutzungsgrad/100)*Z9+AA9*_Anzahl_Verbraucher*12,"") -> 0 | AC9: =IF(E9,Q9*V9,IF(C9,0,"")) -> 0 | AD9: =IF(E9,_Summe_Leistungsspitzen*_Reduktion_Leistungsspitzen_Batterie/100*L9*X9,IF(C9,0,"")) -> 0 | AE9: =IF(E9,-O9*R9,IF(C9,0,"")) -> 0 | AF9: =IF(INT($B9/AF$4)=$B9/AF$4,AF$3,0) -> 0 | AG9: =IF(INT($B9/AG$4)=$B9/AG$4,AG$3,0) -> 0 | AH9: =IF(INT($B9/AH$4)=$B9/AH$4,AH$3,0) -> 69 | AI9: =IF(INT($B9/AI$4)=$B9/AI$4,AI$3,0) -> 99 | AJ9: =IF(INT($B9/AJ$4)=$B9/AJ$4,AJ$3,0) -> 120 | AK9: =IF(INT($B9/AK$4)=$B9/AK$4,AK$3,0) -> 0 | AL9: =IF(INT($B9/AL$4)=$B9/AL$4,AL$3,0) -> 0 | AM9: =IF(INT($B9/AM$4)=$B9/AM$4,AM$3,0) -> 49.1008 | ... AU9: =IF(INT($B9/AU$4)=$B9/AU$4,AU$3,0) -> 0 | AV9: =SUM(AF9:AJ9,AM9:AS9) -> 337.1008 | AW9: =IF(C9,AW8*(1+_Teuerungsrate/100),"") -> 1.005 | AX9: =IF(C9,(-IF(_Berechnungsart_Unterhaltskosten=_Unterhalt_Preis_pro_kWh,K9*_spez_Unterhaltskosten,AV9))*AW9,"") -> -338.7863 | AY9: =IF(C9,(-AK9)*AW9,"") -> 0 | AZ9: =IF(C9,(-AL9)*AW9,"") -> 0 | BA9: =IF(E9,-(AT9+AU9)*AW9,IF((C9),0,"")) -> 0 | BB9: =IF(C9,-IF(_MWStPflicht=_MWStpflichtig,(S9)*_MWStSatz/100,0),"") -> 3.240583e-15 | BC9: =IF(C9,-IF(_MWStPflicht=_MWStpflichtig,(AX9)*_MWStSatz/100,0),"") -> 27.441691 | BD9: =IF(E9,-IF(_MWStPflicht=_MWStpflichtig,(BA9)*_MWStSatz/100,0),IF(C9,0,"")) -> 0 | BE9: =IF(C9,IF(F9,_Einmalvergütung+_Fassadenbonus+_Höhenbonus+_Fassadenbonus,0),"") -> 0 | BF9: =IF(C8,IF(F8,0,BF8),"") -> 0 | BG9: =IF(C9,PMT(_Zins_Eigenkapital/100,_ZahlungsfristEIVFB,BF9)+BF9/_ZahlungsfristEIVFB,"") -> 0 | BH9: =IF(C9,PMT(_Zins_Eigenkapital/100,_Anlagenlebensdauer,_Eigenkapital)+BG9,"") -> -511.46667 | BI9: =IF(C9,IF(G9,PMT(_Zins_Fremdkapital1/100,_Laufzeit_Fremdkapital1,_Fremdkapital1),0),"") -> 0 | BJ9: =IF(C9,IF(H9,PMT(_Zins_Fremdkapital2/100,_Laufzeit_Fremdkapital2,_Fremdkapital2),0),"") -> 0 | BK9: =IF(D9,PMT(_Zins_Eigenkapital_Batterie/100,_Lebensdauer_Speicher,_Eigenkapital_Batterie)+BJ9,IF(C9,0,"")) -> 0 | BL9: =IF(D9,IF(I9,PMT(_Zins_Fremdkapital_Batterie/100,_Laufzeit_Fremdkapital_Batterie,_Fremdkapital_Batterie),0),IF(C9,0,"")) -> 0 | BM9: =IF(C9,S9+U9+W9+AB9+Y9+AX9+AY9+AZ9+BB9+BC9+BE9+BI9+BJ9,"") -> 326.89713 | BN9: =IF($C9,BM9-BI9-BJ9,"") -> 326.89713 | BO9: =IF($C9,BO8+BM9,"") -> -14689.282 | BP9: =IF(C9,BM9*(1+_Zins_Eigenkapital/100)^-B9,"") -> 326.89713 | BQ9: =IF($C9,BQ8+BP9,"") -> -14689.282 | BR9: =IF($C9,IF(AND(BQ8<0,BQ9>=0),B9,""),"") | BS9: =IF(C9,BM9+BA9+AC9+AD9+AE9+BD9+BL9,"") -> 326.89713 | BT9: =IF($C9,BS9-BI9-BJ9-BL9,"") -> 326.89713 | BU9: =IF($C9,BU8+BS9,"") -> -14689.282 | BV9: =IF(C9,BS9*(1+_Zins_Eigenkapital/100)^-B9,"") -> 326.89713 | BW9: =IF($C9,BW8+BV9,"") -> -14689.282 | BX9: =IF($C9,IF(AND(BW8<0,BW9>=0),B9,""),"") | BY9: =IF(E9,AC9+AD9+BL9+BA9+BD9+AE9,"") | BZ9: =IF(E9,BY9-BL9,"") | CA9: =IF($E9,CA8+BY9,"") | CB9: =IF(E9,BY9*(1+_Zins_Eigenkapital/100)^-I9,"") | CC9: =IF($E9,CC8+CB9,"") | CD9: =IF($E9,IF(AND(CC8<0,CC9>=0),B9,""),"")
B10: =B9+1 -> 3 | C10: =IF(B10<=_Anlagenlebensdauer,TRUE,FALSE) -> TRUE | D10: =IF(AND(_Batterie=_JA,B10<=_Lebensdauer_Speicher),TRUE,FALSE) -> FALSE | E10: =IF(AND(_Batterie=_JA,_Kosten_Ersatz_Speicher>0),IF(AND(B10<=_Jahr_Ersatz_Speicher-1+_Lebensdauer_Speicher,C10),TRUE,FALSE),IF(AND(_Batterie=_JA,B10<=_Lebensdauer_Speicher,C10),TRUE,FALSE)) -> FALSE | F10: =IF(B10=_ZahlungsfristEIVFB,TRUE,FALSE) -> FALSE | G10: =IF(B10<=_Laufzeit_Fremdkapital1,TRUE,FALSE) -> FALSE | H10: =IF(B10<=_Laufzeit_Fremdkapital2,TRUE,FALSE) -> FALSE | I10: =IF(B10<=_Laufzeit_Fremdkapital_Batterie,TRUE,FALSE) -> FALSE | J10: =(1-((B10-1)*_Degradation)/100) -> 0.992 | K10: =IF(C10,_Anlagenleistung*J10*_spez_Jahresenergieertrag,"") -> 4464 | L10: =IF(B10=_Jahr_Ersatz_Speicher,1,IF((L9-_Degradation_Speicher_Jahr/100)<0,0,L9-_Degradation_Speicher_Jahr/100)) -> 0.97333333 | M10: =IF(E10,_Speicherkapazität*L10,"") | N10: =IF(E10,_Erhöhung_Eigennutzungsgrad_Speicher*L10,"") | O10: =IF(E10,N10/100*K10,"") | P10: =IF(E10,(O10)*(1-_Speicher_Wirkungsgrad/100),"") | Q10: =IF(E10,O10-P10,"") | R10: =IF(C10,R9*(1+_Teuerungsrate/100),"") -> 0.080802 | S10: =IF(C10,K10*(1-_Eigennutzungsgrad/100-_Anteil_LEG/100)*R10,"") -> -4.0045759e-14 | T10: =IF(C10,T9*(1+_Teuerungsrate/100),"") -> 0.09763575 | U10: =IF(C10,K10*(_Anteil_LEG/100)*T10,"") -> 290.83818 | V10: =IF(C10,V9*(1+_Teuerungsrate/100),"") -> 0.2343258 | W10: =IF(C10,K10*(_Eigennutzungsgrad/100)*V10,"") -> 348.01874 | X10: =IF(C10,X9*(1+_Teuerungsrate/100),"") -> 1.5150375 | Y10: =IF(C10,_Summe_Leistungsspitzen*_Reduktion_Leistungsspitzen/100*J10*X10,"") -> 0 | Z10: =IF(C10,Z9*(1+_Teuerungsrate/100),"") -> 0 | AA10: =IF(C10,AA9*(1+_Teuerungsrate/100),"") -> 8.0802 | AB10: =IF(C10,K10*(_Eigennutzungsgrad/100)*Z10+AA10*_Anzahl_Verbraucher*12,"") -> 0 | AC10: =IF(E10,Q10*V10,IF(C10,0,"")) -> 0 | AD10: =IF(E10,_Summe_Leistungsspitzen*_Reduktion_Leistungsspitzen_Batterie/100*L10*X10,IF(C10,0,"")) -> 0 | AE10: =IF(E10,-O10*R10,IF(C10,0,"")) -> 0 | AF10: =IF(INT($B10/AF$4)=$B10/AF$4,AF$3,0) -> 0 | AG10: =IF(INT($B10/AG$4)=$B10/AG$4,AG$3,0) -> 0 | AH10: =IF(INT($B10/AH$4)=$B10/AH$4,AH$3,0) -> 69 | AI10: =IF(INT($B10/AI$4)=$B10/AI$4,AI$3,0) -> 99 | AJ10: =IF(INT($B10/AJ$4)=$B10/AJ$4,AJ$3,0) -> 120 | AK10: =IF(INT($B10/AK$4)=$B10/AK$4,AK$3,0) -> 0 | AL10: =IF(INT($B10/AL$4)=$B10/AL$4,AL$3,0) -> 0 | AM10: =IF(INT($B10/AM$4)=$B10/AM$4,AM$3,0) -> 49.1008 | ... AU10: =IF(INT($B10/AU$4)=$B10/AU$4,AU$3,0) -> 0 | AV10: =SUM(AF10:AJ10,AM10:AS10) -> 337.1008 | AW10: =IF(C10,AW9*(1+_Teuerungsrate/100),"") -> 1.010025 | AX10: =IF(C10,(-IF(_Berechnungsart_Unterhaltskosten=_Unterhalt_Preis_pro_kWh,K10*_spez_Unterhaltskosten,AV10))*AW10,"") -> -340.48024 | AY10: =IF(C10,(-AK10)*AW10,"") -> 0 | AZ10: =IF(C10,(-AL10)*AW10,"") -> 0 | BA10: =IF(E10,-(AT10+AU10)*AW10,IF((C10),0,"")) -> 0 | BB10: =IF(C10,-IF(_MWStPflicht=_MWStpflichtig,(S10)*_MWStSatz/100,0),"") -> 3.2437065e-15 | BC10: =IF(C10,-IF(_MWStPflicht=_MWStpflichtig,(AX10)*_MWStSatz/100,0),"") -> 27.578899 | BD10: =IF(E10,-IF(_MWStPflicht=_MWStpflichtig,(BA10)*_MWStSatz/100,0),IF(C10,0,"")) -> 0 | BE10: =IF(C10,IF(F10,_Einmalvergütung+_Fassadenbonus+_Höhenbonus+_Fassadenbonus,0),"") -> 0 | BF10: =IF(C9,IF(F9,0,BF9),"") -> 0 | BG10: =IF(C10,PMT(_Zins_Eigenkapital/100,_ZahlungsfristEIVFB,BF10)+BF10/_ZahlungsfristEIVFB,"") -> 0 | BH10: =IF(C10,PMT(_Zins_Eigenkapital/100,_Anlagenlebensdauer,_Eigenkapital)+BG10,"") -> -511.46667 | BI10: =IF(C10,IF(G10,PMT(_Zins_Fremdkapital1/100,_Laufzeit_Fremdkapital1,_Fremdkapital1),0),"") -> 0 | BJ10: =IF(C10,IF(H10,PMT(_Zins_Fremdkapital2/100,_Laufzeit_Fremdkapital2,_Fremdkapital2),0),"") -> 0 | BK10: =IF(D10,PMT(_Zins_Eigenkapital_Batterie/100,_Lebensdauer_Speicher,_Eigenkapital_Batterie)+BJ10,IF(C10,0,"")) -> 0 | BL10: =IF(D10,IF(I10,PMT(_Zins_Fremdkapital_Batterie/100,_Laufzeit_Fremdkapital_Batterie,_Fremdkapital_Batterie),0),IF(C10,0,"")) -> 0 | BM10: =IF(C10,S10+U10+W10+AB10+Y10+AX10+AY10+AZ10+BB10+BC10+BE10+BI10+BJ10,"") -> 325.95558 | BN10: =IF($C10,BM10-BI10-BJ10,"") -> 325.95558 | BO10: =IF($C10,BO9+BM10,"") -> -14363.326 | BP10: =IF(C10,BM10*(1+_Zins_Eigenkapital/100)^-B10,"") -> 325.95558 | BQ10: =IF($C10,BQ9+BP10,"") -> -14363.326 | BR10: =IF($C10,IF(AND(BQ9<0,BQ10>=0),B10,""),"") | BS10: =IF(C10,BM10+BA10+AC10+AD10+AE10+BD10+BL10,"") -> 325.95558 | BT10: =IF($C10,BS10-BI10-BJ10-BL10,"") -> 325.95558 | BU10: =IF($C10,BU9+BS10,"") -> -14363.326 | BV10: =IF(C10,BS10*(1+_Zins_Eigenkapital/100)^-B10,"") -> 325.95558 | BW10: =IF($C10,BW9+BV10,"") -> -14363.326 | BX10: =IF($C10,IF(AND(BW9<0,BW10>=0),B10,""),"") | BY10: =IF(E10,AC10+AD10+BL10+BA10+BD10+AE10,"") | BZ10: =IF(E10,BY10-BL10,"") | CA10: =IF($E10,CA9+BY10,"") | CB10: =IF(E10,BY10*(1+_Zins_Eigenkapital/100)^-I10,"") | CC10: =IF($E10,CC9+CB10,"") | CD10: =IF($E10,IF(AND(CC9<0,CC10>=0),B10,""),"")
B11: =B10+1 -> 4 | C11: =IF(B11<=_Anlagenlebensdauer,TRUE,FALSE) -> TRUE | D11: =IF(AND(_Batterie=_JA,B11<=_Lebensdauer_Speicher),TRUE,FALSE) -> FALSE | E11: =IF(AND(_Batterie=_JA,_Kosten_Ersatz_Speicher>0),IF(AND(B11<=_Jahr_Ersatz_Speicher-1+_Lebensdauer_Speicher,C11),TRUE,FALSE),IF(AND(_Batterie=_JA,B11<=_Lebensdauer_Speicher,C11),TRUE,FALSE)) -> FALSE | F11: =IF(B11=_ZahlungsfristEIVFB,TRUE,FALSE) -> FALSE | G11: =IF(B11<=_Laufzeit_Fremdkapital1,TRUE,FALSE) -> FALSE | H11: =IF(B11<=_Laufzeit_Fremdkapital2,TRUE,FALSE) -> FALSE | I11: =IF(B11<=_Laufzeit_Fremdkapital_Batterie,TRUE,FALSE) -> FALSE | J11: =(1-((B11-1)*_Degradation)/100) -> 0.988 | K11: =IF(C11,_Anlagenleistung*J11*_spez_Jahresenergieertrag,"") -> 4446 | L11: =IF(B11=_Jahr_Ersatz_Speicher,1,IF((L10-_Degradation_Speicher_Jahr/100)<0,0,L10-_Degradation_Speicher_Jahr/100)) -> 0.96 | M11: =IF(E11,_Speicherkapazität*L11,"") | N11: =IF(E11,_Erhöhung_Eigennutzungsgrad_Speicher*L11,"") | O11: =IF(E11,N11/100*K11,"") | P11: =IF(E11,(O11)*(1-_Speicher_Wirkungsgrad/100),"") | Q11: =IF(E11,O11-P11,"") | R11: =IF(C11,R10*(1+_Teuerungsrate/100),"") -> 0.08120601 | S11: =IF(C11,K11*(1-_Eigennutzungsgrad/100-_Anteil_LEG/100)*R11,"") -> -4.0083705e-14 | T11: =IF(C11,T10*(1+_Teuerungsrate/100),"") -> 0.098123929 | U11: =IF(C11,K11*(_Anteil_LEG/100)*T11,"") -> 291.11377 | V11: =IF(C11,V10*(1+_Teuerungsrate/100),"") -> 0.23549743 | W11: =IF(C11,K11*(_Eigennutzungsgrad/100)*V11,"") -> 348.34851 | X11: =IF(C11,X10*(1+_Teuerungsrate/100),"") -> 1.5226127 | Y11: =IF(C11,_Summe_Leistungsspitzen*_Reduktion_Leistungsspitzen/100*J11*X11,"") -> 0 | Z11: =IF(C11,Z10*(1+_Teuerungsrate/100),"") -> 0 | AA11: =IF(C11,AA10*(1+_Teuerungsrate/100),"") -> 8.120601 | AB11: =IF(C11,K11*(_Eigennutzungsgrad/100)*Z11+AA11*_Anzahl_Verbraucher*12,"") -> 0 | AC11: =IF(E11,Q11*V11,IF(C11,0,"")) -> 0 | AD11: =IF(E11,_Summe_Leistungsspitzen*_Reduktion_Leistungsspitzen_Batterie/100*L11*X11,IF(C11,0,"")) -> 0 | AE11: =IF(E11,-O11*R11,IF(C11,0,"")) -> 0 | AF11: =IF(INT($B11/AF$4)=$B11/AF$4,AF$3,0) -> 0 | AG11: =IF(INT($B11/AG$4)=$B11/AG$4,AG$3,0) -> 0 | AH11: =IF(INT($B11/AH$4)=$B11/AH$4,AH$3,0) -> 69 | AI11: =IF(INT($B11/AI$4)=$B11/AI$4,AI$3,0) -> 99 | AJ11: =IF(INT($B11/AJ$4)=$B11/AJ$4,AJ$3,0) -> 120 | AK11: =IF(INT($B11/AK$4)=$B11/AK$4,AK$3,0) -> 0 | AL11: =IF(INT($B11/AL$4)=$B11/AL$4,AL$3,0) -> 0 | AM11: =IF(INT($B11/AM$4)=$B11/AM$4,AM$3,0) -> 49.1008 | ... AU11: =IF(INT($B11/AU$4)=$B11/AU$4,AU$3,0) -> 0 | AV11: =SUM(AF11:AJ11,AM11:AS11) -> 337.1008 | AW11: =IF(C11,AW10*(1+_Teuerungsrate/100),"") -> 1.0150751 | AX11: =IF(C11,(-IF(_Berechnungsart_Unterhaltskosten=_Unterhalt_Preis_pro_kWh,K11*_spez_Unterhaltskosten,AV11))*AW11,"") -> -342.18264 | AY11: =IF(C11,(-AK11)*AW11,"") -> 0 | AZ11: =IF(C11,(-AL11)*AW11,"") -> 0 | BA11: =IF(E11,-(AT11+AU11)*AW11,IF((C11),0,"")) -> 0 | BB11: =IF(C11,-IF(_MWStPflicht=_MWStpflichtig,(S11)*_MWStSatz/100,0),"") -> 3.2467801e-15 | BC11: =IF(C11,-IF(_MWStPflicht=_MWStpflichtig,(AX11)*_MWStSatz/100,0),"") -> 27.716794 | BD11: =IF(E11,-IF(_MWStPflicht=_MWStpflichtig,(BA11)*_MWStSatz/100,0),IF(C11,0,"")) -> 0 | BE11: =IF(C11,IF(F11,_Einmalvergütung+_Fassadenbonus+_Höhenbonus+_Fassadenbonus,0),"") -> 0 | BF11: =IF(C10,IF(F10,0,BF10),"") -> 0 | BG11: =IF(C11,PMT(_Zins_Eigenkapital/100,_ZahlungsfristEIVFB,BF11)+BF11/_ZahlungsfristEIVFB,"") -> 0 | BH11: =IF(C11,PMT(_Zins_Eigenkapital/100,_Anlagenlebensdauer,_Eigenkapital)+BG11,"") -> -511.46667 | BI11: =IF(C11,IF(G11,PMT(_Zins_Fremdkapital1/100,_Laufzeit_Fremdkapital1,_Fremdkapital1),0),"") -> 0 | BJ11: =IF(C11,IF(H11,PMT(_Zins_Fremdkapital2/100,_Laufzeit_Fremdkapital2,_Fremdkapital2),0),"") -> 0 | BK11: =IF(D11,PMT(_Zins_Eigenkapital_Batterie/100,_Lebensdauer_Speicher,_Eigenkapital_Batterie)+BJ11,IF(C11,0,"")) -> 0 | BL11: =IF(D11,IF(I11,PMT(_Zins_Fremdkapital_Batterie/100,_Laufzeit_Fremdkapital_Batterie,_Fremdkapital_Batterie),0),IF(C11,0,"")) -> 0 | BM11: =IF(C11,S11+U11+W11+AB11+Y11+AX11+AY11+AZ11+BB11+BC11+BE11+BI11+BJ11,"") -> 324.99644 | BN11: =IF($C11,BM11-BI11-BJ11,"") -> 324.99644 | BO11: =IF($C11,BO10+BM11,"") -> -14038.33 | BP11: =IF(C11,BM11*(1+_Zins_Eigenkapital/100)^-B11,"") -> 324.99644 | BQ11: =IF($C11,BQ10+BP11,"") -> -14038.33 | BR11: =IF($C11,IF(AND(BQ10<0,BQ11>=0),B11,""),"") | BS11: =IF(C11,BM11+BA11+AC11+AD11+AE11+BD11+BL11,"") -> 324.99644 | BT11: =IF($C11,BS11-BI11-BJ11-BL11,"") -> 324.99644 | BU11: =IF($C11,BU10+BS11,"") -> -14038.33 | BV11: =IF(C11,BS11*(1+_Zins_Eigenkapital/100)^-B11,"") -> 324.99644 | BW11: =IF($C11,BW10+BV11,"") -> -14038.33 | BX11: =IF($C11,IF(AND(BW10<0,BW11>=0),B11,""),"") | BY11: =IF(E11,AC11+AD11+BL11+BA11+BD11+AE11,"") | BZ11: =IF(E11,BY11-BL11,"") | CA11: =IF($E11,CA10+BY11,"") | CB11: =IF(E11,BY11*(1+_Zins_Eigenkapital/100)^-I11,"") | CC11: =IF($E11,CC10+CB11,"") | CD11: =IF($E11,IF(AND(CC10<0,CC11>=0),B11,""),"")
B12: =B11+1 -> 5 | C12: =IF(B12<=_Anlagenlebensdauer,TRUE,FALSE) -> TRUE | D12: =IF(AND(_Batterie=_JA,B12<=_Lebensdauer_Speicher),TRUE,FALSE) -> FALSE | E12: =IF(AND(_Batterie=_JA,_Kosten_Ersatz_Speicher>0),IF(AND(B12<=_Jahr_Ersatz_Speicher-1+_Lebensdauer_Speicher,C12),TRUE,FALSE),IF(AND(_Batterie=_JA,B12<=_Lebensdauer_Speicher,C12),TRUE,FALSE)) -> FALSE | F12: =IF(B12=_ZahlungsfristEIVFB,TRUE,FALSE) -> FALSE | G12: =IF(B12<=_Laufzeit_Fremdkapital1,TRUE,FALSE) -> FALSE | H12: =IF(B12<=_Laufzeit_Fremdkapital2,TRUE,FALSE) -> FALSE | I12: =IF(B12<=_Laufzeit_Fremdkapital_Batterie,TRUE,FALSE) -> FALSE | J12: =(1-((B12-1)*_Degradation)/100) -> 0.984 | K12: =IF(C12,_Anlagenleistung*J12*_spez_Jahresenergieertrag,"") -> 4428 | L12: =IF(B12=_Jahr_Ersatz_Speicher,1,IF((L11-_Degradation_Speicher_Jahr/100)<0,0,L11-_Degradation_Speicher_Jahr/100)) -> 0.94666667 | M12: =IF(E12,_Speicherkapazität*L12,"") | N12: =IF(E12,_Erhöhung_Eigennutzungsgrad_Speicher*L12,"") | O12: =IF(E12,N12/100*K12,"") | P12: =IF(E12,(O12)*(1-_Speicher_Wirkungsgrad/100),"") | Q12: =IF(E12,O12-P12,"") | R12: =IF(C12,R11*(1+_Teuerungsrate/100),"") -> 0.08161204 | S12: =IF(C12,K12*(1-_Eigennutzungsgrad/100-_Anteil_LEG/100)*R12,"") -> -4.012103e-14 | T12: =IF(C12,T11*(1+_Teuerungsrate/100),"") -> 0.098614548 | U12: =IF(C12,K12*(_Anteil_LEG/100)*T12,"") -> 291.38485 | V12: =IF(C12,V11*(1+_Teuerungsrate/100),"") -> 0.23667492 | W12: =IF(C12,K12*(_Eigennutzungsgrad/100)*V12,"") -> 348.67289 | X12: =IF(C12,X11*(1+_Teuerungsrate/100),"") -> 1.5302258 | Y12: =IF(C12,_Summe_Leistungsspitzen*_Reduktion_Leistungsspitzen/100*J12*X12,"") -> 0 | Z12: =IF(C12,Z11*(1+_Teuerungsrate/100),"") -> 0 | AA12: =IF(C12,AA11*(1+_Teuerungsrate/100),"") -> 8.161204 | AB12: =IF(C12,K12*(_Eigennutzungsgrad/100)*Z12+AA12*_Anzahl_Verbraucher*12,"") -> 0 | AC12: =IF(E12,Q12*V12,IF(C12,0,"")) -> 0 | AD12: =IF(E12,_Summe_Leistungsspitzen*_Reduktion_Leistungsspitzen_Batterie/100*L12*X12,IF(C12,0,"")) -> 0 | AE12: =IF(E12,-O12*R12,IF(C12,0,"")) -> 0 | AF12: =IF(INT($B12/AF$4)=$B12/AF$4,AF$3,0) -> 830.688 | AG12: =IF(INT($B12/AG$4)=$B12/AG$4,AG$3,0) -> 0 | AH12: =IF(INT($B12/AH$4)=$B12/AH$4,AH$3,0) -> 69 | AI12: =IF(INT($B12/AI$4)=$B12/AI$4,AI$3,0) -> 99 | AJ12: =IF(INT($B12/AJ$4)=$B12/AJ$4,AJ$3,0) -> 120 | AK12: =IF(INT($B12/AK$4)=$B12/AK$4,AK$3,0) -> 0 | AL12: =IF(INT($B12/AL$4)=$B12/AL$4,AL$3,0) -> 0 | AM12: =IF(INT($B12/AM$4)=$B12/AM$4,AM$3,0) -> 49.1008 | ... AU12: =IF(INT($B12/AU$4)=$B12/AU$4,AU$3,0) -> 0 | AV12: =SUM(AF12:AJ12,AM12:AS12) -> 1167.7888 | AW12: =IF(C12,AW11*(1+_Teuerungsrate/100),"") -> 1.0201505 | AX12: =IF(C12,(-IF(_Berechnungsart_Unterhaltskosten=_Unterhalt_Preis_pro_kWh,K12*_spez_Unterhaltskosten,AV12))*AW12,"") -> -1191.3203 | AY12: =IF(C12,(-AK12)*AW12,"") -> 0 | AZ12: =IF(C12,(-AL12)*AW12,"") -> 0 | BA12: =IF(E12,-(AT12+AU12)*AW12,IF((C12),0,"")) -> 0 | BB12: =IF(C12,-IF(_MWStPflicht=_MWStpflichtig,(S12)*_MWStSatz/100,0),"") -> 3.2498034e-15 | BC12: =IF(C12,-IF(_MWStPflicht=_MWStpflichtig,(AX12)*_MWStSatz/100,0),"") -> 96.496947 | BD12: =IF(E12,-IF(_MWStPflicht=_MWStpflichtig,(BA12)*_MWStSatz/100,0),IF(C12,0,"")) -> 0 | BE12: =IF(C12,IF(F12,_Einmalvergütung+_Fassadenbonus+_Höhenbonus+_Fassadenbonus,0),"") -> 0 | BF12: =IF(C11,IF(F11,0,BF11),"") -> 0 | BG12: =IF(C12,PMT(_Zins_Eigenkapital/100,_ZahlungsfristEIVFB,BF12)+BF12/_ZahlungsfristEIVFB,"") -> 0 | BH12: =IF(C12,PMT(_Zins_Eigenkapital/100,_Anlagenlebensdauer,_Eigenkapital)+BG12,"") -> -511.46667 | BI12: =IF(C12,IF(G12,PMT(_Zins_Fremdkapital1/100,_Laufzeit_Fremdkapital1,_Fremdkapital1),0),"") -> 0 | BJ12: =IF(C12,IF(H12,PMT(_Zins_Fremdkapital2/100,_Laufzeit_Fremdkapital2,_Fremdkapital2),0),"") -> 0 | BK12: =IF(D12,PMT(_Zins_Eigenkapital_Batterie/100,_Lebensdauer_Speicher,_Eigenkapital_Batterie)+BJ12,IF(C12,0,"")) -> 0 | BL12: =IF(D12,IF(I12,PMT(_Zins_Fremdkapital_Batterie/100,_Laufzeit_Fremdkapital_Batterie,_Fremdkapital_Batterie),0),IF(C12,0,"")) -> 0 | BM12: =IF(C12,S12+U12+W12+AB12+Y12+AX12+AY12+AZ12+BB12+BC12+BE12+BI12+BJ12,"") -> -454.76565 | BN12: =IF($C12,BM12-BI12-BJ12,"") -> -454.76565 | BO12: =IF($C12,BO11+BM12,"") -> -14493.095 | BP12: =IF(C12,BM12*(1+_Zins_Eigenkapital/100)^-B12,"") -> -454.76565 | BQ12: =IF($C12,BQ11+BP12,"") -> -14493.095 | BR12: =IF($C12,IF(AND(BQ11<0,BQ12>=0),B12,""),"") | BS12: =IF(C12,BM12+BA12+AC12+AD12+AE12+BD12+BL12,"") -> -454.76565 | BT12: =IF($C12,BS12-BI12-BJ12-BL12,"") -> -454.76565 | BU12: =IF($C12,BU11+BS12,"") -> -14493.095 | BV12: =IF(C12,BS12*(1+_Zins_Eigenkapital/100)^-B12,"") -> -454.76565 | BW12: =IF($C12,BW11+BV12,"") -> -14493.095 | BX12: =IF($C12,IF(AND(BW11<0,BW12>=0),B12,""),"") | BY12: =IF(E12,AC12+AD12+BL12+BA12+BD12+AE12,"") | BZ12: =IF(E12,BY12-BL12,"") | CA12: =IF($E12,CA11+BY12,"") | CB12: =IF(E12,BY12*(1+_Zins_Eigenkapital/100)^-I12,"") | CC12: =IF($E12,CC11+CB12,"") | CD12: =IF($E12,IF(AND(CC11<0,CC12>=0),B12,""),"")
B13: =B12+1 -> 6 | C13: =IF(B13<=_Anlagenlebensdauer,TRUE,FALSE) -> TRUE | D13: =IF(AND(_Batterie=_JA,B13<=_Lebensdauer_Speicher),TRUE,FALSE) -> FALSE | E13: =IF(AND(_Batterie=_JA,_Kosten_Ersatz_Speicher>0),IF(AND(B13<=_Jahr_Ersatz_Speicher-1+_Lebensdauer_Speicher,C13),TRUE,FALSE),IF(AND(_Batterie=_JA,B13<=_Lebensdauer_Speicher,C13),TRUE,FALSE)) -> FALSE | F13: =IF(B13=_ZahlungsfristEIVFB,TRUE,FALSE) -> FALSE | G13: =IF(B13<=_Laufzeit_Fremdkapital1,TRUE,FALSE) -> FALSE | H13: =IF(B13<=_Laufzeit_Fremdkapital2,TRUE,FALSE) -> FALSE | I13: =IF(B13<=_Laufzeit_Fremdkapital_Batterie,TRUE,FALSE) -> FALSE | J13: =(1-((B13-1)*_Degradation)/100) -> 0.98 | K13: =IF(C13,_Anlagenleistung*J13*_spez_Jahresenergieertrag,"") -> 4410 | L13: =IF(B13=_Jahr_Ersatz_Speicher,1,IF((L12-_Degradation_Speicher_Jahr/100)<0,0,L12-_Degradation_Speicher_Jahr/100)) -> 0.93333333 | M13: =IF(E13,_Speicherkapazität*L13,"") | N13: =IF(E13,_Erhöhung_Eigennutzungsgrad_Speicher*L13,"") | O13: =IF(E13,N13/100*K13,"") | P13: =IF(E13,(O13)*(1-_Speicher_Wirkungsgrad/100),"") | Q13: =IF(E13,O13-P13,"") | R13: =IF(C13,R12*(1+_Teuerungsrate/100),"") -> 0.0820201 | S13: =IF(C13,K13*(1-_Eigennutzungsgrad/100-_Anteil_LEG/100)*R13,"") -> -4.0157726e-14 | T13: =IF(C13,T12*(1+_Teuerungsrate/100),"") -> 0.099107621 | U13: =IF(C13,K13*(_Anteil_LEG/100)*T13,"") -> 291.65136 | V13: =IF(C13,V12*(1+_Teuerungsrate/100),"") -> 0.23785829 | W13: =IF(C13,K13*(_Eigennutzungsgrad/100)*V13,"") -> 348.99179 | X13: =IF(C13,X12*(1+_Teuerungsrate/100),"") -> 1.5378769 | Y13: =IF(C13,_Summe_Leistungsspitzen*_Reduktion_Leistungsspitzen/100*J13*X13,"") -> 0 | Z13: =IF(C13,Z12*(1+_Teuerungsrate/100),"") -> 0 | AA13: =IF(C13,AA12*(1+_Teuerungsrate/100),"") -> 8.20201 | AB13: =IF(C13,K13*(_Eigennutzungsgrad/100)*Z13+AA13*_Anzahl_Verbraucher*12,"") -> 0 | AC13: =IF(E13,Q13*V13,IF(C13,0,"")) -> 0 | AD13: =IF(E13,_Summe_Leistungsspitzen*_Reduktion_Leistungsspitzen_Batterie/100*L13*X13,IF(C13,0,"")) -> 0 | AE13: =IF(E13,-O13*R13,IF(C13,0,"")) -> 0 | AF13: =IF(INT($B13/AF$4)=$B13/AF$4,AF$3,0) -> 0 | AG13: =IF(INT($B13/AG$4)=$B13/AG$4,AG$3,0) -> 0 | AH13: =IF(INT($B13/AH$4)=$B13/AH$4,AH$3,0) -> 69 | AI13: =IF(INT($B13/AI$4)=$B13/AI$4,AI$3,0) -> 99 | AJ13: =IF(INT($B13/AJ$4)=$B13/AJ$4,AJ$3,0) -> 120 | AK13: =IF(INT($B13/AK$4)=$B13/AK$4,AK$3,0) -> 0 | AL13: =IF(INT($B13/AL$4)=$B13/AL$4,AL$3,0) -> 0 | AM13: =IF(INT($B13/AM$4)=$B13/AM$4,AM$3,0) -> 49.1008 | ... AU13: =IF(INT($B13/AU$4)=$B13/AU$4,AU$3,0) -> 0 | AV13: =SUM(AF13:AJ13,AM13:AS13) -> 337.1008 | AW13: =IF(C13,AW12*(1+_Teuerungsrate/100),"") -> 1.0252513 | AX13: =IF(C13,(-IF(_Berechnungsart_Unterhaltskosten=_Unterhalt_Preis_pro_kWh,K13*_spez_Unterhaltskosten,AV13))*AW13,"") -> -345.61302 | AY13: =IF(C13,(-AK13)*AW13,"") -> 0 | AZ13: =IF(C13,(-AL13)*AW13,"") -> 0 | BA13: =IF(E13,-(AT13+AU13)*AW13,IF((C13),0,"")) -> 0 | BB13: =IF(C13,-IF(_MWStPflicht=_MWStpflichtig,(S13)*_MWStSatz/100,0),"") -> 3.2527758e-15 | BC13: =IF(C13,-IF(_MWStPflicht=_MWStpflichtig,(AX13)*_MWStSatz/100,0),"") -> 27.994654 | BD13: =IF(E13,-IF(_MWStPflicht=_MWStpflichtig,(BA13)*_MWStSatz/100,0),IF(C13,0,"")) -> 0 | BE13: =IF(C13,IF(F13,_Einmalvergütung+_Fassadenbonus+_Höhenbonus+_Fassadenbonus,0),"") -> 0 | BF13: =IF(C12,IF(F12,0,BF12),"") -> 0 | BG13: =IF(C13,PMT(_Zins_Eigenkapital/100,_ZahlungsfristEIVFB,BF13)+BF13/_ZahlungsfristEIVFB,"") -> 0 | BH13: =IF(C13,PMT(_Zins_Eigenkapital/100,_Anlagenlebensdauer,_Eigenkapital)+BG13,"") -> -511.46667 | BI13: =IF(C13,IF(G13,PMT(_Zins_Fremdkapital1/100,_Laufzeit_Fremdkapital1,_Fremdkapital1),0),"") -> 0 | BJ13: =IF(C13,IF(H13,PMT(_Zins_Fremdkapital2/100,_Laufzeit_Fremdkapital2,_Fremdkapital2),0),"") -> 0 | BK13: =IF(D13,PMT(_Zins_Eigenkapital_Batterie/100,_Lebensdauer_Speicher,_Eigenkapital_Batterie)+BJ13,IF(C13,0,"")) -> 0 | BL13: =IF(D13,IF(I13,PMT(_Zins_Fremdkapital_Batterie/100,_Laufzeit_Fremdkapital_Batterie,_Fremdkapital_Batterie),0),IF(C13,0,"")) -> 0 | BM13: =IF(C13,S13+U13+W13+AB13+Y13+AX13+AY13+AZ13+BB13+BC13+BE13+BI13+BJ13,"") -> 323.02479 | BN13: =IF($C13,BM13-BI13-BJ13,"") -> 323.02479 | BO13: =IF($C13,BO12+BM13,"") -> -14170.07 | BP13: =IF(C13,BM13*(1+_Zins_Eigenkapital/100)^-B13,"") -> 323.02479 | BQ13: =IF($C13,BQ12+BP13,"") -> -14170.07 | BR13: =IF($C13,IF(AND(BQ12<0,BQ13>=0),B13,""),"") | BS13: =IF(C13,BM13+BA13+AC13+AD13+AE13+BD13+BL13,"") -> 323.02479 | BT13: =IF($C13,BS13-BI13-BJ13-BL13,"") -> 323.02479 | BU13: =IF($C13,BU12+BS13,"") -> -14170.07 | BV13: =IF(C13,BS13*(1+_Zins_Eigenkapital/100)^-B13,"") -> 323.02479 | BW13: =IF($C13,BW12+BV13,"") -> -14170.07 | BX13: =IF($C13,IF(AND(BW12<0,BW13>=0),B13,""),"") | BY13: =IF(E13,AC13+AD13+BL13+BA13+BD13+AE13,"") | BZ13: =IF(E13,BY13-BL13,"") | CA13: =IF($E13,CA12+BY13,"") | CB13: =IF(E13,BY13*(1+_Zins_Eigenkapital/100)^-I13,"") | CC13: =IF($E13,CC12+CB13,"") | CD13: =IF($E13,IF(AND(CC12<0,CC13>=0),B13,""),"")
B14: =B13+1 -> 7 | C14: =IF(B14<=_Anlagenlebensdauer,TRUE,FALSE) -> TRUE | D14: =IF(AND(_Batterie=_JA,B14<=_Lebensdauer_Speicher),TRUE,FALSE) -> FALSE | E14: =IF(AND(_Batterie=_JA,_Kosten_Ersatz_Speicher>0),IF(AND(B14<=_Jahr_Ersatz_Speicher-1+_Lebensdauer_Speicher,C14),TRUE,FALSE),IF(AND(_Batterie=_JA,B14<=_Lebensdauer_Speicher,C14),TRUE,FALSE)) -> FALSE | F14: =IF(B14=_ZahlungsfristEIVFB,TRUE,FALSE) -> FALSE | G14: =IF(B14<=_Laufzeit_Fremdkapital1,TRUE,FALSE) -> FALSE | H14: =IF(B14<=_Laufzeit_Fremdkapital2,TRUE,FALSE) -> FALSE | I14: =IF(B14<=_Laufzeit_Fremdkapital_Batterie,TRUE,FALSE) -> FALSE | J14: =(1-((B14-1)*_Degradation)/100) -> 0.976 | K14: =IF(C14,_Anlagenleistung*J14*_spez_Jahresenergieertrag,"") -> 4392 | L14: =IF(B14=_Jahr_Ersatz_Speicher,1,IF((L13-_Degradation_Speicher_Jahr/100)<0,0,L13-_Degradation_Speicher_Jahr/100)) -> 0.92 | M14: =IF(E14,_Speicherkapazität*L14,"") | N14: =IF(E14,_Erhöhung_Eigennutzungsgrad_Speicher*L14,"") | O14: =IF(E14,N14/100*K14,"") | P14: =IF(E14,(O14)*(1-_Speicher_Wirkungsgrad/100),"") | Q14: =IF(E14,O14-P14,"") | R14: =IF(C14,R13*(1+_Teuerungsrate/100),"") -> 0.082430201 | S14: =IF(C14,K14*(1-_Eigennutzungsgrad/100-_Anteil_LEG/100)*R14,"") -> -4.0193786e-14 | T14: =IF(C14,T13*(1+_Teuerungsrate/100),"") -> 0.099603159 | U14: =IF(C14,K14*(_Anteil_LEG/100)*T14,"") -> 291.91325 | V14: =IF(C14,V13*(1+_Teuerungsrate/100),"") -> 0.23904758 | W14: =IF(C14,K14*(_Eigennutzungsgrad/100)*V14,"") -> 349.30517 | X14: =IF(C14,X13*(1+_Teuerungsrate/100),"") -> 1.5455663 | Y14: =IF(C14,_Summe_Leistungsspitzen*_Reduktion_Leistungsspitzen/100*J14*X14,"") -> 0 | Z14: =IF(C14,Z13*(1+_Teuerungsrate/100),"") -> 0 | AA14: =IF(C14,AA13*(1+_Teuerungsrate/100),"") -> 8.2430201 | AB14: =IF(C14,K14*(_Eigennutzungsgrad/100)*Z14+AA14*_Anzahl_Verbraucher*12,"") -> 0 | AC14: =IF(E14,Q14*V14,IF(C14,0,"")) -> 0 | AD14: =IF(E14,_Summe_Leistungsspitzen*_Reduktion_Leistungsspitzen_Batterie/100*L14*X14,IF(C14,0,"")) -> 0 | AE14: =IF(E14,-O14*R14,IF(C14,0,"")) -> 0 | AF14: =IF(INT($B14/AF$4)=$B14/AF$4,AF$3,0) -> 0 | AG14: =IF(INT($B14/AG$4)=$B14/AG$4,AG$3,0) -> 0 | AH14: =IF(INT($B14/AH$4)=$B14/AH$4,AH$3,0) -> 69 | AI14: =IF(INT($B14/AI$4)=$B14/AI$4,AI$3,0) -> 99 | AJ14: =IF(INT($B14/AJ$4)=$B14/AJ$4,AJ$3,0) -> 120 | AK14: =IF(INT($B14/AK$4)=$B14/AK$4,AK$3,0) -> 0 | AL14: =IF(INT($B14/AL$4)=$B14/AL$4,AL$3,0) -> 0 | AM14: =IF(INT($B14/AM$4)=$B14/AM$4,AM$3,0) -> 49.1008 | ... AU14: =IF(INT($B14/AU$4)=$B14/AU$4,AU$3,0) -> 0 | AV14: =SUM(AF14:AJ14,AM14:AS14) -> 337.1008 | AW14: =IF(C14,AW13*(1+_Teuerungsrate/100),"") -> 1.0303775 | AX14: =IF(C14,(-IF(_Berechnungsart_Unterhaltskosten=_Unterhalt_Preis_pro_kWh,K14*_spez_Unterhaltskosten,AV14))*AW14,"") -> -347.34108 | AY14: =IF(C14,(-AK14)*AW14,"") -> 0 | AZ14: =IF(C14,(-AL14)*AW14,"") -> 0 | BA14: =IF(E14,-(AT14+AU14)*AW14,IF((C14),0,"")) -> 0 | BB14: =IF(C14,-IF(_MWStPflicht=_MWStpflichtig,(S14)*_MWStSatz/100,0),"") -> 3.2556967e-15 | BC14: =IF(C14,-IF(_MWStPflicht=_MWStpflichtig,(AX14)*_MWStSatz/100,0),"") -> 28.134628 | BD14: =IF(E14,-IF(_MWStPflicht=_MWStpflichtig,(BA14)*_MWStSatz/100,0),IF(C14,0,"")) -> 0 | BE14: =IF(C14,IF(F14,_Einmalvergütung+_Fassadenbonus+_Höhenbonus+_Fassadenbonus,0),"") -> 0 | BF14: =IF(C13,IF(F13,0,BF13),"") -> 0 | BG14: =IF(C14,PMT(_Zins_Eigenkapital/100,_ZahlungsfristEIVFB,BF14)+BF14/_ZahlungsfristEIVFB,"") -> 0 | BH14: =IF(C14,PMT(_Zins_Eigenkapital/100,_Anlagenlebensdauer,_Eigenkapital)+BG14,"") -> -511.46667 | BI14: =IF(C14,IF(G14,PMT(_Zins_Fremdkapital1/100,_Laufzeit_Fremdkapital1,_Fremdkapital1),0),"") -> 0 | BJ14: =IF(C14,IF(H14,PMT(_Zins_Fremdkapital2/100,_Laufzeit_Fremdkapital2,_Fremdkapital2),0),"") -> 0 | BK14: =IF(D14,PMT(_Zins_Eigenkapital_Batterie/100,_Lebensdauer_Speicher,_Eigenkapital_Batterie)+BJ14,IF(C14,0,"")) -> 0 | BL14: =IF(D14,IF(I14,PMT(_Zins_Fremdkapital_Batterie/100,_Laufzeit_Fremdkapital_Batterie,_Fremdkapital_Batterie),0),IF(C14,0,"")) -> 0 | BM14: =IF(C14,S14+U14+W14+AB14+Y14+AX14+AY14+AZ14+BB14+BC14+BE14+BI14+BJ14,"") -> 322.01197 | BN14: =IF($C14,BM14-BI14-BJ14,"") -> 322.01197 | BO14: =IF($C14,BO13+BM14,"") -> -13848.058 | BP14: =IF(C14,BM14*(1+_Zins_Eigenkapital/100)^-B14,"") -> 322.01197 | BQ14: =IF($C14,BQ13+BP14,"") -> -13848.058 | BR14: =IF($C14,IF(AND(BQ13<0,BQ14>=0),B14,""),"") | BS14: =IF(C14,BM14+BA14+AC14+AD14+AE14+BD14+BL14,"") -> 322.01197 | BT14: =IF($C14,BS14-BI14-BJ14-BL14,"") -> 322.01197 | BU14: =IF($C14,BU13+BS14,"") -> -13848.058 | BV14: =IF(C14,BS14*(1+_Zins_Eigenkapital/100)^-B14,"") -> 322.01197 | BW14: =IF($C14,BW13+BV14,"") -> -13848.058 | BX14: =IF($C14,IF(AND(BW13<0,BW14>=0),B14,""),"") | BY14: =IF(E14,AC14+AD14+BL14+BA14+BD14+AE14,"") | BZ14: =IF(E14,BY14-BL14,"") | CA14: =IF($E14,CA13+BY14,"") | CB14: =IF(E14,BY14*(1+_Zins_Eigenkapital/100)^-I14,"") | CC14: =IF($E14,CC13+CB14,"") | CD14: =IF($E14,IF(AND(CC13<0,CC14>=0),B14,""),"")
B15: =B14+1 -> 8 | C15: =IF(B15<=_Anlagenlebensdauer,TRUE,FALSE) -> TRUE | D15: =IF(AND(_Batterie=_JA,B15<=_Lebensdauer_Speicher),TRUE,FALSE) -> FALSE | E15: =IF(AND(_Batterie=_JA,_Kosten_Ersatz_Speicher>0),IF(AND(B15<=_Jahr_Ersatz_Speicher-1+_Lebensdauer_Speicher,C15),TRUE,FALSE),IF(AND(_Batterie=_JA,B15<=_Lebensdauer_Speicher,C15),TRUE,FALSE)) -> FALSE | F15: =IF(B15=_ZahlungsfristEIVFB,TRUE,FALSE) -> FALSE | G15: =IF(B15<=_Laufzeit_Fremdkapital1,TRUE,FALSE) -> FALSE | H15: =IF(B15<=_Laufzeit_Fremdkapital2,TRUE,FALSE) -> FALSE | I15: =IF(B15<=_Laufzeit_Fremdkapital_Batterie,TRUE,FALSE) -> FALSE | J15: =(1-((B15-1)*_Degradation)/100) -> 0.972 | K15: =IF(C15,_Anlagenleistung*J15*_spez_Jahresenergieertrag,"") -> 4374 | L15: =IF(B15=_Jahr_Ersatz_Speicher,1,IF((L14-_Degradation_Speicher_Jahr/100)<0,0,L14-_Degradation_Speicher_Jahr/100)) -> 0.90666667 | M15: =IF(E15,_Speicherkapazität*L15,"") | N15: =IF(E15,_Erhöhung_Eigennutzungsgrad_Speicher*L15,"") | O15: =IF(E15,N15/100*K15,"") | P15: =IF(E15,(O15)*(1-_Speicher_Wirkungsgrad/100),"") | Q15: =IF(E15,O15-P15,"") | R15: =IF(C15,R14*(1+_Teuerungsrate/100),"") -> 0.082842352 | S15: =IF(C15,K15*(1-_Eigennutzungsgrad/100-_Anteil_LEG/100)*R15,"") -> -4.0229203e-14 | T15: =IF(C15,T14*(1+_Teuerungsrate/100),"") -> 0.10010118 | U15: =IF(C15,K15*(_Anteil_LEG/100)*T15,"") -> 292.17047 | V15: =IF(C15,V14*(1+_Teuerungsrate/100),"") -> 0.24024282 | W15: =IF(C15,K15*(_Eigennutzungsgrad/100)*V15,"") -> 349.61296 | X15: =IF(C15,X14*(1+_Teuerungsrate/100),"") -> 1.5532941 | Y15: =IF(C15,_Summe_Leistungsspitzen*_Reduktion_Leistungsspitzen/100*J15*X15,"") -> 0 | Z15: =IF(C15,Z14*(1+_Teuerungsrate/100),"") -> 0 | AA15: =IF(C15,AA14*(1+_Teuerungsrate/100),"") -> 8.2842352 | AB15: =IF(C15,K15*(_Eigennutzungsgrad/100)*Z15+AA15*_Anzahl_Verbraucher*12,"") -> 0 | AC15: =IF(E15,Q15*V15,IF(C15,0,"")) -> 0 | AD15: =IF(E15,_Summe_Leistungsspitzen*_Reduktion_Leistungsspitzen_Batterie/100*L15*X15,IF(C15,0,"")) -> 0 | AE15: =IF(E15,-O15*R15,IF(C15,0,"")) -> 0 | AF15: =IF(INT($B15/AF$4)=$B15/AF$4,AF$3,0) -> 0 | AG15: =IF(INT($B15/AG$4)=$B15/AG$4,AG$3,0) -> 0 | AH15: =IF(INT($B15/AH$4)=$B15/AH$4,AH$3,0) -> 69 | AI15: =IF(INT($B15/AI$4)=$B15/AI$4,AI$3,0) -> 99 | AJ15: =IF(INT($B15/AJ$4)=$B15/AJ$4,AJ$3,0) -> 120 | AK15: =IF(INT($B15/AK$4)=$B15/AK$4,AK$3,0) -> 0 | AL15: =IF(INT($B15/AL$4)=$B15/AL$4,AL$3,0) -> 0 | AM15: =IF(INT($B15/AM$4)=$B15/AM$4,AM$3,0) -> 49.1008 | ... AU15: =IF(INT($B15/AU$4)=$B15/AU$4,AU$3,0) -> 0 | AV15: =SUM(AF15:AJ15,AM15:AS15) -> 2608.6948 | AW15: =IF(C15,AW14*(1+_Teuerungsrate/100),"") -> 1.0355294 | AX15: =IF(C15,(-IF(_Berechnungsart_Unterhaltskosten=_Unterhalt_Preis_pro_kWh,K15*_spez_Unterhaltskosten,AV15))*AW15,"") -> -2701.3802 | AY15: =IF(C15,(-AK15)*AW15,"") -> 0 | AZ15: =IF(C15,(-AL15)*AW15,"") -> 0 | BA15: =IF(E15,-(AT15+AU15)*AW15,IF((C15),0,"")) -> 0 | BB15: =IF(C15,-IF(_MWStPflicht=_MWStpflichtig,(S15)*_MWStSatz/100,0),"") -> 3.2585654e-15 | BC15: =IF(C15,-IF(_MWStPflicht=_MWStpflichtig,(AX15)*_MWStSatz/100,0),"") -> 218.81179 | BD15: =IF(E15,-IF(_MWStPflicht=_MWStpflichtig,(BA15)*_MWStSatz/100,0),IF(C15,0,"")) -> 0 | BE15: =IF(C15,IF(F15,_Einmalvergütung+_Fassadenbonus+_Höhenbonus+_Fassadenbonus,0),"") -> 0 | BF15: =IF(C14,IF(F14,0,BF14),"") -> 0 | BG15: =IF(C15,PMT(_Zins_Eigenkapital/100,_ZahlungsfristEIVFB,BF15)+BF15/_ZahlungsfristEIVFB,"") -> 0 | BH15: =IF(C15,PMT(_Zins_Eigenkapital/100,_Anlagenlebensdauer,_Eigenkapital)+BG15,"") -> -511.46667 | BI15: =IF(C15,IF(G15,PMT(_Zins_Fremdkapital1/100,_Laufzeit_Fremdkapital1,_Fremdkapital1),0),"") -> 0 | BJ15: =IF(C15,IF(H15,PMT(_Zins_Fremdkapital2/100,_Laufzeit_Fremdkapital2,_Fremdkapital2),0),"") -> 0 | BK15: =IF(D15,PMT(_Zins_Eigenkapital_Batterie/100,_Lebensdauer_Speicher,_Eigenkapital_Batterie)+BJ15,IF(C15,0,"")) -> 0 | BL15: =IF(D15,IF(I15,PMT(_Zins_Fremdkapital_Batterie/100,_Laufzeit_Fremdkapital_Batterie,_Fremdkapital_Batterie),0),IF(C15,0,"")) -> 0 | BM15: =IF(C15,S15+U15+W15+AB15+Y15+AX15+AY15+AZ15+BB15+BC15+BE15+BI15+BJ15,"") -> -1840.7849 | BN15: =IF($C15,BM15-BI15-BJ15,"") -> -1840.7849 | BO15: =IF($C15,BO14+BM15,"") -> -15688.843 | BP15: =IF(C15,BM15*(1+_Zins_Eigenkapital/100)^-B15,"") -> -1840.7849 | BQ15: =IF($C15,BQ14+BP15,"") -> -15688.843 | BR15: =IF($C15,IF(AND(BQ14<0,BQ15>=0),B15,""),"") | BS15: =IF(C15,BM15+BA15+AC15+AD15+AE15+BD15+BL15,"") -> -1840.7849 | BT15: =IF($C15,BS15-BI15-BJ15-BL15,"") -> -1840.7849 | BU15: =IF($C15,BU14+BS15,"") -> -15688.843 | BV15: =IF(C15,BS15*(1+_Zins_Eigenkapital/100)^-B15,"") -> -1840.7849 | BW15: =IF($C15,BW14+BV15,"") -> -15688.843 | BX15: =IF($C15,IF(AND(BW14<0,BW15>=0),B15,""),"") | BY15: =IF(E15,AC15+AD15+BL15+BA15+BD15+AE15,"") | BZ15: =IF(E15,BY15-BL15,"") | CA15: =IF($E15,CA14+BY15,"") | CB15: =IF(E15,BY15*(1+_Zins_Eigenkapital/100)^-I15,"") | CC15: =IF($E15,CC14+CB15,"") | CD15: =IF($E15,IF(AND(CC14<0,CC15>=0),B15,""),"")
B16: =B15+1 -> 9 | C16: =IF(B16<=_Anlagenlebensdauer,TRUE,FALSE) -> TRUE | D16: =IF(AND(_Batterie=_JA,B16<=_Lebensdauer_Speicher),TRUE,FALSE) -> FALSE | E16: =IF(AND(_Batterie=_JA,_Kosten_Ersatz_Speicher>0),IF(AND(B16<=_Jahr_Ersatz_Speicher-1+_Lebensdauer_Speicher,C16),TRUE,FALSE),IF(AND(_Batterie=_JA,B16<=_Lebensdauer_Speicher,C16),TRUE,FALSE)) -> FALSE | F16: =IF(B16=_ZahlungsfristEIVFB,TRUE,FALSE) -> FALSE | G16: =IF(B16<=_Laufzeit_Fremdkapital1,TRUE,FALSE) -> FALSE | H16: =IF(B16<=_Laufzeit_Fremdkapital2,TRUE,FALSE) -> FALSE | I16: =IF(B16<=_Laufzeit_Fremdkapital_Batterie,TRUE,FALSE) -> FALSE | J16: =(1-((B16-1)*_Degradation)/100) -> 0.968 | K16: =IF(C16,_Anlagenleistung*J16*_spez_Jahresenergieertrag,"") -> 4356 | L16: =IF(B16=_Jahr_Ersatz_Speicher,1,IF((L15-_Degradation_Speicher_Jahr/100)<0,0,L15-_Degradation_Speicher_Jahr/100)) -> 0.89333333 | M16: =IF(E16,_Speicherkapazität*L16,"") | N16: =IF(E16,_Erhöhung_Eigennutzungsgrad_Speicher*L16,"") | O16: =IF(E16,N16/100*K16,"") | P16: =IF(E16,(O16)*(1-_Speicher_Wirkungsgrad/100),"") | Q16: =IF(E16,O16-P16,"") | R16: =IF(C16,R15*(1+_Teuerungsrate/100),"") -> 0.083256564 | S16: =IF(C16,K16*(1-_Eigennutzungsgrad/100-_Anteil_LEG/100)*R16,"") -> -4.0263969e-14 | T16: =IF(C16,T15*(1+_Teuerungsrate/100),"") -> 0.10060168 | U16: =IF(C16,K16*(_Anteil_LEG/100)*T16,"") -> 292.42296 | V16: =IF(C16,V15*(1+_Teuerungsrate/100),"") -> 0.24144403 | W16: =IF(C16,K16*(_Eigennutzungsgrad/100)*V16,"") -> 349.9151 | X16: =IF(C16,X15*(1+_Teuerungsrate/100),"") -> 1.5610606 | Y16: =IF(C16,_Summe_Leistungsspitzen*_Reduktion_Leistungsspitzen/100*J16*X16,"") -> 0 | Z16: =IF(C16,Z15*(1+_Teuerungsrate/100),"") -> 0 | AA16: =IF(C16,AA15*(1+_Teuerungsrate/100),"") -> 8.3256564 | AB16: =IF(C16,K16*(_Eigennutzungsgrad/100)*Z16+AA16*_Anzahl_Verbraucher*12,"") -> 0 | AC16: =IF(E16,Q16*V16,IF(C16,0,"")) -> 0 | AD16: =IF(E16,_Summe_Leistungsspitzen*_Reduktion_Leistungsspitzen_Batterie/100*L16*X16,IF(C16,0,"")) -> 0 | AE16: =IF(E16,-O16*R16,IF(C16,0,"")) -> 0 | AF16: =IF(INT($B16/AF$4)=$B16/AF$4,AF$3,0) -> 0 | AG16: =IF(INT($B16/AG$4)=$B16/AG$4,AG$3,0) -> 0 | AH16: =IF(INT($B16/AH$4)=$B16/AH$4,AH$3,0) -> 69 | AI16: =IF(INT($B16/AI$4)=$B16/AI$4,AI$3,0) -> 99 | AJ16: =IF(INT($B16/AJ$4)=$B16/AJ$4,AJ$3,0) -> 120 | AK16: =IF(INT($B16/AK$4)=$B16/AK$4,AK$3,0) -> 0 | AL16: =IF(INT($B16/AL$4)=$B16/AL$4,AL$3,0) -> 0 | AM16: =IF(INT($B16/AM$4)=$B16/AM$4,AM$3,0) -> 49.1008 | ... AU16: =IF(INT($B16/AU$4)=$B16/AU$4,AU$3,0) -> 0 | AV16: =SUM(AF16:AJ16,AM16:AS16) -> 337.1008 | AW16: =IF(C16,AW15*(1+_Teuerungsrate/100),"") -> 1.040707 | AX16: =IF(C16,(-IF(_Berechnungsart_Unterhaltskosten=_Unterhalt_Preis_pro_kWh,K16*_spez_Unterhaltskosten,AV16))*AW16,"") -> -350.82318 | AY16: =IF(C16,(-AK16)*AW16,"") -> 0 | AZ16: =IF(C16,(-AL16)*AW16,"") -> 0 | BA16: =IF(E16,-(AT16+AU16)*AW16,IF((C16),0,"")) -> 0 | BB16: =IF(C16,-IF(_MWStPflicht=_MWStpflichtig,(S16)*_MWStSatz/100,0),"") -> 3.2613815e-15 | BC16: =IF(C16,-IF(_MWStPflicht=_MWStpflichtig,(AX16)*_MWStSatz/100,0),"") -> 28.416677 | BD16: =IF(E16,-IF(_MWStPflicht=_MWStpflichtig,(BA16)*_MWStSatz/100,0),IF(C16,0,"")) -> 0 | BE16: =IF(C16,IF(F16,_Einmalvergütung+_Fassadenbonus+_Höhenbonus+_Fassadenbonus,0),"") -> 0 | BF16: =IF(C15,IF(F15,0,BF15),"") -> 0 | BG16: =IF(C16,PMT(_Zins_Eigenkapital/100,_ZahlungsfristEIVFB,BF16)+BF16/_ZahlungsfristEIVFB,"") -> 0 | BH16: =IF(C16,PMT(_Zins_Eigenkapital/100,_Anlagenlebensdauer,_Eigenkapital)+BG16,"") -> -511.46667 | BI16: =IF(C16,IF(G16,PMT(_Zins_Fremdkapital1/100,_Laufzeit_Fremdkapital1,_Fremdkapital1),0),"") -> 0 | BJ16: =IF(C16,IF(H16,PMT(_Zins_Fremdkapital2/100,_Laufzeit_Fremdkapital2,_Fremdkapital2),0),"") -> 0 | BK16: =IF(D16,PMT(_Zins_Eigenkapital_Batterie/100,_Lebensdauer_Speicher,_Eigenkapital_Batterie)+BJ16,IF(C16,0,"")) -> 0 | BL16: =IF(D16,IF(I16,PMT(_Zins_Fremdkapital_Batterie/100,_Laufzeit_Fremdkapital_Batterie,_Fremdkapital_Batterie),0),IF(C16,0,"")) -> 0 | BM16: =IF(C16,S16+U16+W16+AB16+Y16+AX16+AY16+AZ16+BB16+BC16+BE16+BI16+BJ16,"") -> 319.93156 | BN16: =IF($C16,BM16-BI16-BJ16,"") -> 319.93156 | BO16: =IF($C16,BO15+BM16,"") -> -15368.912 | BP16: =IF(C16,BM16*(1+_Zins_Eigenkapital/100)^-B16,"") -> 319.93156 | BQ16: =IF($C16,BQ15+BP16,"") -> -15368.912 | BR16: =IF($C16,IF(AND(BQ15<0,BQ16>=0),B16,""),"") | BS16: =IF(C16,BM16+BA16+AC16+AD16+AE16+BD16+BL16,"") -> 319.93156 | BT16: =IF($C16,BS16-BI16-BJ16-BL16,"") -> 319.93156 | BU16: =IF($C16,BU15+BS16,"") -> -15368.912 | BV16: =IF(C16,BS16*(1+_Zins_Eigenkapital/100)^-B16,"") -> 319.93156 | BW16: =IF($C16,BW15+BV16,"") -> -15368.912 | BX16: =IF($C16,IF(AND(BW15<0,BW16>=0),B16,""),"") | BY16: =IF(E16,AC16+AD16+BL16+BA16+BD16+AE16,"") | BZ16: =IF(E16,BY16-BL16,"") | CA16: =IF($E16,CA15+BY16,"") | CB16: =IF(E16,BY16*(1+_Zins_Eigenkapital/100)^-I16,"") | CC16: =IF($E16,CC15+CB16,"") | CD16: =IF($E16,IF(AND(CC15<0,CC16>=0),B16,""),"")
B17: =B16+1 -> 10 | C17: =IF(B17<=_Anlagenlebensdauer,TRUE,FALSE) -> TRUE | D17: =IF(AND(_Batterie=_JA,B17<=_Lebensdauer_Speicher),TRUE,FALSE) -> FALSE | E17: =IF(AND(_Batterie=_JA,_Kosten_Ersatz_Speicher>0),IF(AND(B17<=_Jahr_Ersatz_Speicher-1+_Lebensdauer_Speicher,C17),TRUE,FALSE),IF(AND(_Batterie=_JA,B17<=_Lebensdauer_Speicher,C17),TRUE,FALSE)) -> FALSE | F17: =IF(B17=_ZahlungsfristEIVFB,TRUE,FALSE) -> FALSE | G17: =IF(B17<=_Laufzeit_Fremdkapital1,TRUE,FALSE) -> FALSE | H17: =IF(B17<=_Laufzeit_Fremdkapital2,TRUE,FALSE) -> FALSE | I17: =IF(B17<=_Laufzeit_Fremdkapital_Batterie,TRUE,FALSE) -> FALSE | J17: =(1-((B17-1)*_Degradation)/100) -> 0.964 | K17: =IF(C17,_Anlagenleistung*J17*_spez_Jahresenergieertrag,"") -> 4338 | L17: =IF(B17=_Jahr_Ersatz_Speicher,1,IF((L16-_Degradation_Speicher_Jahr/100)<0,0,L16-_Degradation_Speicher_Jahr/100)) -> 0.88 | M17: =IF(E17,_Speicherkapazität*L17,"") | N17: =IF(E17,_Erhöhung_Eigennutzungsgrad_Speicher*L17,"") | O17: =IF(E17,N17/100*K17,"") | P17: =IF(E17,(O17)*(1-_Speicher_Wirkungsgrad/100),"") | Q17: =IF(E17,O17-P17,"") | R17: =IF(C17,R16*(1+_Teuerungsrate/100),"") -> 0.083672846 | S17: =IF(C17,K17*(1-_Eigennutzungsgrad/100-_Anteil_LEG/100)*R17,"") -> -4.0298077e-14 | T17: =IF(C17,T16*(1+_Teuerungsrate/100),"") -> 0.10110469 | U17: =IF(C17,K17*(_Anteil_LEG/100)*T17,"") -> 292.67068 | V17: =IF(C17,V16*(1+_Teuerungsrate/100),"") -> 0.24265125 | W17: =IF(C17,K17*(_Eigennutzungsgrad/100)*V17,"") -> 350.21151 | X17: =IF(C17,X16*(1+_Teuerungsrate/100),"") -> 1.5688659 | Y17: =IF(C17,_Summe_Leistungsspitzen*_Reduktion_Leistungsspitzen/100*J17*X17,"") -> 0 | Z17: =IF(C17,Z16*(1+_Teuerungsrate/100),"") -> 0 | AA17: =IF(C17,AA16*(1+_Teuerungsrate/100),"") -> 8.3672846 | AB17: =IF(C17,K17*(_Eigennutzungsgrad/100)*Z17+AA17*_Anzahl_Verbraucher*12,"") -> 0 | AC17: =IF(E17,Q17*V17,IF(C17,0,"")) -> 0 | AD17: =IF(E17,_Summe_Leistungsspitzen*_Reduktion_Leistungsspitzen_Batterie/100*L17*X17,IF(C17,0,"")) -> 0 | AE17: =IF(E17,-O17*R17,IF(C17,0,"")) -> 0 | AF17: =IF(INT($B17/AF$4)=$B17/AF$4,AF$3,0) -> 830.688 | AG17: =IF(INT($B17/AG$4)=$B17/AG$4,AG$3,0) -> 0 | AH17: =IF(INT($B17/AH$4)=$B17/AH$4,AH$3,0) -> 69 | AI17: =IF(INT($B17/AI$4)=$B17/AI$4,AI$3,0) -> 99 | AJ17: =IF(INT($B17/AJ$4)=$B17/AJ$4,AJ$3,0) -> 120 | AK17: =IF(INT($B17/AK$4)=$B17/AK$4,AK$3,0) -> 0 | AL17: =IF(INT($B17/AL$4)=$B17/AL$4,AL$3,0) -> 0 | AM17: =IF(INT($B17/AM$4)=$B17/AM$4,AM$3,0) -> 49.1008 | ... AU17: =IF(INT($B17/AU$4)=$B17/AU$4,AU$3,0) -> 0 | AV17: =SUM(AF17:AJ17,AM17:AS17) -> 1167.7888 | AW17: =IF(C17,AW16*(1+_Teuerungsrate/100),"") -> 1.0459106 | AX17: =IF(C17,(-IF(_Berechnungsart_Unterhaltskosten=_Unterhalt_Preis_pro_kWh,K17*_spez_Unterhaltskosten,AV17))*AW17,"") -> -1221.4027 | AY17: =IF(C17,(-AK17)*AW17,"") -> 0 | AZ17: =IF(C17,(-AL17)*AW17,"") -> 0 | BA17: =IF(E17,-(AT17+AU17)*AW17,IF((C17),0,"")) -> 0 | BB17: =IF(C17,-IF(_MWStPflicht=_MWStpflichtig,(S17)*_MWStSatz/100,0),"") -> 3.2641442e-15 | BC17: =IF(C17,-IF(_MWStPflicht=_MWStpflichtig,(AX17)*_MWStSatz/100,0),"") -> 98.933615 | BD17: =IF(E17,-IF(_MWStPflicht=_MWStpflichtig,(BA17)*_MWStSatz/100,0),IF(C17,0,"")) -> 0 | BE17: =IF(C17,IF(F17,_Einmalvergütung+_Fassadenbonus+_Höhenbonus+_Fassadenbonus,0),"") -> 0 | BF17: =IF(C16,IF(F16,0,BF16),"") -> 0 | BG17: =IF(C17,PMT(_Zins_Eigenkapital/100,_ZahlungsfristEIVFB,BF17)+BF17/_ZahlungsfristEIVFB,"") -> 0 | BH17: =IF(C17,PMT(_Zins_Eigenkapital/100,_Anlagenlebensdauer,_Eigenkapital)+BG17,"") -> -511.46667 | BI17: =IF(C17,IF(G17,PMT(_Zins_Fremdkapital1/100,_Laufzeit_Fremdkapital1,_Fremdkapital1),0),"") -> 0 | BJ17: =IF(C17,IF(H17,PMT(_Zins_Fremdkapital2/100,_Laufzeit_Fremdkapital2,_Fremdkapital2),0),"") -> 0 | BK17: =IF(D17,PMT(_Zins_Eigenkapital_Batterie/100,_Lebensdauer_Speicher,_Eigenkapital_Batterie)+BJ17,IF(C17,0,"")) -> 0 | BL17: =IF(D17,IF(I17,PMT(_Zins_Fremdkapital_Batterie/100,_Laufzeit_Fremdkapital_Batterie,_Fremdkapital_Batterie),0),IF(C17,0,"")) -> 0 | BM17: =IF(C17,S17+U17+W17+AB17+Y17+AX17+AY17+AZ17+BB17+BC17+BE17+BI17+BJ17,"") -> -479.58685 | BN17: =IF($C17,BM17-BI17-BJ17,"") -> -479.58685 | BO17: =IF($C17,BO16+BM17,"") -> -15848.499 | BP17: =IF(C17,BM17*(1+_Zins_Eigenkapital/100)^-B17,"") -> -479.58685 | BQ17: =IF($C17,BQ16+BP17,"") -> -15848.499 | BR17: =IF($C17,IF(AND(BQ16<0,BQ17>=0),B17,""),"") | BS17: =IF(C17,BM17+BA17+AC17+AD17+AE17+BD17+BL17,"") -> -479.58685 | BT17: =IF($C17,BS17-BI17-BJ17-BL17,"") -> -479.58685 | BU17: =IF($C17,BU16+BS17,"") -> -15848.499 | BV17: =IF(C17,BS17*(1+_Zins_Eigenkapital/100)^-B17,"") -> -479.58685 | BW17: =IF($C17,BW16+BV17,"") -> -15848.499 | BX17: =IF($C17,IF(AND(BW16<0,BW17>=0),B17,""),"") | BY17: =IF(E17,AC17+AD17+BL17+BA17+BD17+AE17,"") | BZ17: =IF(E17,BY17-BL17,"") | CA17: =IF($E17,CA16+BY17,"") | CB17: =IF(E17,BY17*(1+_Zins_Eigenkapital/100)^-I17,"") | CC17: =IF($E17,CC16+CB17,"") | CD17: =IF($E17,IF(AND(CC16<0,CC17>=0),B17,""),"")
B18: =B17+1 -> 11 | C18: =IF(B18<=_Anlagenlebensdauer,TRUE,FALSE) -> TRUE | D18: =IF(AND(_Batterie=_JA,B18<=_Lebensdauer_Speicher),TRUE,FALSE) -> FALSE | E18: =IF(AND(_Batterie=_JA,_Kosten_Ersatz_Speicher>0),IF(AND(B18<=_Jahr_Ersatz_Speicher-1+_Lebensdauer_Speicher,C18),TRUE,FALSE),IF(AND(_Batterie=_JA,B18<=_Lebensdauer_Speicher,C18),TRUE,FALSE)) -> FALSE | F18: =IF(B18=_ZahlungsfristEIVFB,TRUE,FALSE) -> FALSE | G18: =IF(B18<=_Laufzeit_Fremdkapital1,TRUE,FALSE) -> FALSE | H18: =IF(B18<=_Laufzeit_Fremdkapital2,TRUE,FALSE) -> FALSE | I18: =IF(B18<=_Laufzeit_Fremdkapital_Batterie,TRUE,FALSE) -> FALSE | J18: =(1-((B18-1)*_Degradation)/100) -> 0.96 | K18: =IF(C18,_Anlagenleistung*J18*_spez_Jahresenergieertrag,"") -> 4320 | L18: =IF(B18=_Jahr_Ersatz_Speicher,1,IF((L17-_Degradation_Speicher_Jahr/100)<0,0,L17-_Degradation_Speicher_Jahr/100)) -> 0.86666667 | M18: =IF(E18,_Speicherkapazität*L18,"") | N18: =IF(E18,_Erhöhung_Eigennutzungsgrad_Speicher*L18,"") | O18: =IF(E18,N18/100*K18,"") | P18: =IF(E18,(O18)*(1-_Speicher_Wirkungsgrad/100),"") | Q18: =IF(E18,O18-P18,"") | R18: =IF(C18,R17*(1+_Teuerungsrate/100),"") -> 0.084091211 | S18: =IF(C18,K18*(1-_Eigennutzungsgrad/100-_Anteil_LEG/100)*R18,"") -> -4.0331519e-14 | T18: =IF(C18,T17*(1+_Teuerungsrate/100),"") -> 0.10161021 | U18: =IF(C18,K18*(_Anteil_LEG/100)*T18,"") -> 292.91356 | V18: =IF(C18,V17*(1+_Teuerungsrate/100),"") -> 0.24386451 | W18: =IF(C18,K18*(_Eigennutzungsgrad/100)*V18,"") -> 350.50215 | X18: =IF(C18,X17*(1+_Teuerungsrate/100),"") -> 1.5767102 | Y18: =IF(C18,_Summe_Leistungsspitzen*_Reduktion_Leistungsspitzen/100*J18*X18,"") -> 0 | Z18: =IF(C18,Z17*(1+_Teuerungsrate/100),"") -> 0 | AA18: =IF(C18,AA17*(1+_Teuerungsrate/100),"") -> 8.4091211 | AB18: =IF(C18,K18*(_Eigennutzungsgrad/100)*Z18+AA18*_Anzahl_Verbraucher*12,"") -> 0 | AC18: =IF(E18,Q18*V18,IF(C18,0,"")) -> 0 | AD18: =IF(E18,_Summe_Leistungsspitzen*_Reduktion_Leistungsspitzen_Batterie/100*L18*X18,IF(C18,0,"")) -> 0 | AE18: =IF(E18,-O18*R18,IF(C18,0,"")) -> 0 | AF18: =IF(INT($B18/AF$4)=$B18/AF$4,AF$3,0) -> 0 | AG18: =IF(INT($B18/AG$4)=$B18/AG$4,AG$3,0) -> 0 | AH18: =IF(INT($B18/AH$4)=$B18/AH$4,AH$3,0) -> 69 | AI18: =IF(INT($B18/AI$4)=$B18/AI$4,AI$3,0) -> 99 | AJ18: =IF(INT($B18/AJ$4)=$B18/AJ$4,AJ$3,0) -> 120 | AK18: =IF(INT($B18/AK$4)=$B18/AK$4,AK$3,0) -> 0 | AL18: =IF(INT($B18/AL$4)=$B18/AL$4,AL$3,0) -> 0 | AM18: =IF(INT($B18/AM$4)=$B18/AM$4,AM$3,0) -> 49.1008 | ... AU18: =IF(INT($B18/AU$4)=$B18/AU$4,AU$3,0) -> 0 | AV18: =SUM(AF18:AJ18,AM18:AS18) -> 337.1008 | AW18: =IF(C18,AW17*(1+_Teuerungsrate/100),"") -> 1.0511401 | AX18: =IF(C18,(-IF(_Berechnungsart_Unterhaltskosten=_Unterhalt_Preis_pro_kWh,K18*_spez_Unterhaltskosten,AV18))*AW18,"") -> -354.34018 | AY18: =IF(C18,(-AK18)*AW18,"") -> 0 | AZ18: =IF(C18,(-AL18)*AW18,"") -> 0 | BA18: =IF(E18,-(AT18+AU18)*AW18,IF((C18),0,"")) -> 0 | BB18: =IF(C18,-IF(_MWStPflicht=_MWStpflichtig,(S18)*_MWStSatz/100,0),"") -> 3.2668531e-15 | BC18: =IF(C18,-IF(_MWStPflicht=_MWStpflichtig,(AX18)*_MWStSatz/100,0),"") -> 28.701555 | BD18: =IF(E18,-IF(_MWStPflicht=_MWStpflichtig,(BA18)*_MWStSatz/100,0),IF(C18,0,"")) -> 0 | BE18: =IF(C18,IF(F18,_Einmalvergütung+_Fassadenbonus+_Höhenbonus+_Fassadenbonus,0),"") -> 0 | BF18: =IF(C17,IF(F17,0,BF17),"") -> 0 | BG18: =IF(C18,PMT(_Zins_Eigenkapital/100,_ZahlungsfristEIVFB,BF18)+BF18/_ZahlungsfristEIVFB,"") -> 0 | BH18: =IF(C18,PMT(_Zins_Eigenkapital/100,_Anlagenlebensdauer,_Eigenkapital)+BG18,"") -> -511.46667 | BI18: =IF(C18,IF(G18,PMT(_Zins_Fremdkapital1/100,_Laufzeit_Fremdkapital1,_Fremdkapital1),0),"") -> 0 | BJ18: =IF(C18,IF(H18,PMT(_Zins_Fremdkapital2/100,_Laufzeit_Fremdkapital2,_Fremdkapital2),0),"") -> 0 | BK18: =IF(D18,PMT(_Zins_Eigenkapital_Batterie/100,_Lebensdauer_Speicher,_Eigenkapital_Batterie)+BJ18,IF(C18,0,"")) -> 0 | BL18: =IF(D18,IF(I18,PMT(_Zins_Fremdkapital_Batterie/100,_Laufzeit_Fremdkapital_Batterie,_Fremdkapital_Batterie),0),IF(C18,0,"")) -> 0 | BM18: =IF(C18,S18+U18+W18+AB18+Y18+AX18+AY18+AZ18+BB18+BC18+BE18+BI18+BJ18,"") -> 317.77708 | BN18: =IF($C18,BM18-BI18-BJ18,"") -> 317.77708 | BO18: =IF($C18,BO17+BM18,"") -> -15530.722 | BP18: =IF(C18,BM18*(1+_Zins_Eigenkapital/100)^-B18,"") -> 317.77708 | BQ18: =IF($C18,BQ17+BP18,"") -> -15530.722 | BR18: =IF($C18,IF(AND(BQ17<0,BQ18>=0),B18,""),"") | BS18: =IF(C18,BM18+BA18+AC18+AD18+AE18+BD18+BL18,"") -> 317.77708 | BT18: =IF($C18,BS18-BI18-BJ18-BL18,"") -> 317.77708 | BU18: =IF($C18,BU17+BS18,"") -> -15530.722 | BV18: =IF(C18,BS18*(1+_Zins_Eigenkapital/100)^-B18,"") -> 317.77708 | BW18: =IF($C18,BW17+BV18,"") -> -15530.722 | BX18: =IF($C18,IF(AND(BW17<0,BW18>=0),B18,""),"") | BY18: =IF(E18,AC18+AD18+BL18+BA18+BD18+AE18,"") | BZ18: =IF(E18,BY18-BL18,"") | CA18: =IF($E18,CA17+BY18,"") | CB18: =IF(E18,BY18*(1+_Zins_Eigenkapital/100)^-I18,"") | CC18: =IF($E18,CC17+CB18,"") | CD18: =IF($E18,IF(AND(CC17<0,CC18>=0),B18,""),"")
B19: =B18+1 -> 12 | C19: =IF(B19<=_Anlagenlebensdauer,TRUE,FALSE) -> TRUE | D19: =IF(AND(_Batterie=_JA,B19<=_Lebensdauer_Speicher),TRUE,FALSE) -> FALSE | E19: =IF(AND(_Batterie=_JA,_Kosten_Ersatz_Speicher>0),IF(AND(B19<=_Jahr_Ersatz_Speicher-1+_Lebensdauer_Speicher,C19),TRUE,FALSE),IF(AND(_Batterie=_JA,B19<=_Lebensdauer_Speicher,C19),TRUE,FALSE)) -> FALSE | F19: =IF(B19=_ZahlungsfristEIVFB,TRUE,FALSE) -> FALSE | G19: =IF(B19<=_Laufzeit_Fremdkapital1,TRUE,FALSE) -> FALSE | H19: =IF(B19<=_Laufzeit_Fremdkapital2,TRUE,FALSE) -> FALSE | I19: =IF(B19<=_Laufzeit_Fremdkapital_Batterie,TRUE,FALSE) -> FALSE | J19: =(1-((B19-1)*_Degradation)/100) -> 0.956 | K19: =IF(C19,_Anlagenleistung*J19*_spez_Jahresenergieertrag,"") -> 4302 | L19: =IF(B19=_Jahr_Ersatz_Speicher,1,IF((L18-_Degradation_Speicher_Jahr/100)<0,0,L18-_Degradation_Speicher_Jahr/100)) -> 0.85333333 | M19: =IF(E19,_Speicherkapazität*L19,"") | N19: =IF(E19,_Erhöhung_Eigennutzungsgrad_Speicher*L19,"") | O19: =IF(E19,N19/100*K19,"") | P19: =IF(E19,(O19)*(1-_Speicher_Wirkungsgrad/100),"") | Q19: =IF(E19,O19-P19,"") | R19: =IF(C19,R18*(1+_Teuerungsrate/100),"") -> 0.084511667 | S19: =IF(C19,K19*(1-_Eigennutzungsgrad/100-_Anteil_LEG/100)*R19,"") -> -4.0364289e-14 | T19: =IF(C19,T18*(1+_Teuerungsrate/100),"") -> 0.10211826 | U19: =IF(C19,K19*(_Anteil_LEG/100)*T19,"") -> 293.15155 | V19: =IF(C19,V18*(1+_Teuerungsrate/100),"") -> 0.24508383 | W19: =IF(C19,K19*(_Eigennutzungsgrad/100)*V19,"") -> 350.78693 | X19: =IF(C19,X18*(1+_Teuerungsrate/100),"") -> 1.5845937 | Y19: =IF(C19,_Summe_Leistungsspitzen*_Reduktion_Leistungsspitzen/100*J19*X19,"") -> 0 | Z19: =IF(C19,Z18*(1+_Teuerungsrate/100),"") -> 0 | AA19: =IF(C19,AA18*(1+_Teuerungsrate/100),"") -> 8.4511667 | AB19: =IF(C19,K19*(_Eigennutzungsgrad/100)*Z19+AA19*_Anzahl_Verbraucher*12,"") -> 0 | AC19: =IF(E19,Q19*V19,IF(C19,0,"")) -> 0 | AD19: =IF(E19,_Summe_Leistungsspitzen*_Reduktion_Leistungsspitzen_Batterie/100*L19*X19,IF(C19,0,"")) -> 0 | AE19: =IF(E19,-O19*R19,IF(C19,0,"")) -> 0 | AF19: =IF(INT($B19/AF$4)=$B19/AF$4,AF$3,0) -> 0 | AG19: =IF(INT($B19/AG$4)=$B19/AG$4,AG$3,0) -> 0 | AH19: =IF(INT($B19/AH$4)=$B19/AH$4,AH$3,0) -> 69 | AI19: =IF(INT($B19/AI$4)=$B19/AI$4,AI$3,0) -> 99 | AJ19: =IF(INT($B19/AJ$4)=$B19/AJ$4,AJ$3,0) -> 120 | AK19: =IF(INT($B19/AK$4)=$B19/AK$4,AK$3,0) -> 0 | AL19: =IF(INT($B19/AL$4)=$B19/AL$4,AL$3,0) -> 0 | AM19: =IF(INT($B19/AM$4)=$B19/AM$4,AM$3,0) -> 49.1008 | ... AU19: =IF(INT($B19/AU$4)=$B19/AU$4,AU$3,0) -> 0 | AV19: =SUM(AF19:AJ19,AM19:AS19) -> 337.1008 | AW19: =IF(C19,AW18*(1+_Teuerungsrate/100),"") -> 1.0563958 | AX19: =IF(C19,(-IF(_Berechnungsart_Unterhaltskosten=_Unterhalt_Preis_pro_kWh,K19*_spez_Unterhaltskosten,AV19))*AW19,"") -> -356.11188 | AY19: =IF(C19,(-AK19)*AW19,"") -> 0 | AZ19: =IF(C19,(-AL19)*AW19,"") -> 0 | BA19: =IF(E19,-(AT19+AU19)*AW19,IF((C19),0,"")) -> 0 | BB19: =IF(C19,-IF(_MWStPflicht=_MWStpflichtig,(S19)*_MWStSatz/100,0),"") -> 3.2695074e-15 | BC19: =IF(C19,-IF(_MWStPflicht=_MWStpflichtig,(AX19)*_MWStSatz/100,0),"") -> 28.845062 | BD19: =IF(E19,-IF(_MWStPflicht=_MWStpflichtig,(BA19)*_MWStSatz/100,0),IF(C19,0,"")) -> 0 | BE19: =IF(C19,IF(F19,_Einmalvergütung+_Fassadenbonus+_Höhenbonus+_Fassadenbonus,0),"") -> 0 | BF19: =IF(C18,IF(F18,0,BF18),"") -> 0 | BG19: =IF(C19,PMT(_Zins_Eigenkapital/100,_ZahlungsfristEIVFB,BF19)+BF19/_ZahlungsfristEIVFB,"") -> 0 | BH19: =IF(C19,PMT(_Zins_Eigenkapital/100,_Anlagenlebensdauer,_Eigenkapital)+BG19,"") -> -511.46667 | BI19: =IF(C19,IF(G19,PMT(_Zins_Fremdkapital1/100,_Laufzeit_Fremdkapital1,_Fremdkapital1),0),"") -> 0 | BJ19: =IF(C19,IF(H19,PMT(_Zins_Fremdkapital2/100,_Laufzeit_Fremdkapital2,_Fremdkapital2),0),"") -> 0 | BK19: =IF(D19,PMT(_Zins_Eigenkapital_Batterie/100,_Lebensdauer_Speicher,_Eigenkapital_Batterie)+BJ19,IF(C19,0,"")) -> 0 | BL19: =IF(D19,IF(I19,PMT(_Zins_Fremdkapital_Batterie/100,_Laufzeit_Fremdkapital_Batterie,_Fremdkapital_Batterie),0),IF(C19,0,"")) -> 0 | BM19: =IF(C19,S19+U19+W19+AB19+Y19+AX19+AY19+AZ19+BB19+BC19+BE19+BI19+BJ19,"") -> 316.67166 | BN19: =IF($C19,BM19-BI19-BJ19,"") -> 316.67166 | BO19: =IF($C19,BO18+BM19,"") -> -15214.05 | BP19: =IF(C19,BM19*(1+_Zins_Eigenkapital/100)^-B19,"") -> 316.67166 | BQ19: =IF($C19,BQ18+BP19,"") -> -15214.05 | BR19: =IF($C19,IF(AND(BQ18<0,BQ19>=0),B19,""),"") | BS19: =IF(C19,BM19+BA19+AC19+AD19+AE19+BD19+BL19,"") -> 316.67166 | BT19: =IF($C19,BS19-BI19-BJ19-BL19,"") -> 316.67166 | BU19: =IF($C19,BU18+BS19,"") -> -15214.05 | BV19: =IF(C19,BS19*(1+_Zins_Eigenkapital/100)^-B19,"") -> 316.67166 | BW19: =IF($C19,BW18+BV19,"") -> -15214.05 | BX19: =IF($C19,IF(AND(BW18<0,BW19>=0),B19,""),"") | BY19: =IF(E19,AC19+AD19+BL19+BA19+BD19+AE19,"") | BZ19: =IF(E19,BY19-BL19,"") | CA19: =IF($E19,CA18+BY19,"") | CB19: =IF(E19,BY19*(1+_Zins_Eigenkapital/100)^-I19,"") | CC19: =IF($E19,CC18+CB19,"") | CD19: =IF($E19,IF(AND(CC18<0,CC19>=0),B19,""),"")
B20: =B19+1 -> 13 | C20: =IF(B20<=_Anlagenlebensdauer,TRUE,FALSE) -> TRUE | D20: =IF(AND(_Batterie=_JA,B20<=_Lebensdauer_Speicher),TRUE,FALSE) -> FALSE | E20: =IF(AND(_Batterie=_JA,_Kosten_Ersatz_Speicher>0),IF(AND(B20<=_Jahr_Ersatz_Speicher-1+_Lebensdauer_Speicher,C20),TRUE,FALSE),IF(AND(_Batterie=_JA,B20<=_Lebensdauer_Speicher,C20),TRUE,FALSE)) -> FALSE | F20: =IF(B20=_ZahlungsfristEIVFB,TRUE,FALSE) -> FALSE | G20: =IF(B20<=_Laufzeit_Fremdkapital1,TRUE,FALSE) -> FALSE | H20: =IF(B20<=_Laufzeit_Fremdkapital2,TRUE,FALSE) -> FALSE | I20: =IF(B20<=_Laufzeit_Fremdkapital_Batterie,TRUE,FALSE) -> FALSE | J20: =(1-((B20-1)*_Degradation)/100) -> 0.952 | K20: =IF(C20,_Anlagenleistung*J20*_spez_Jahresenergieertrag,"") -> 4284 | L20: =IF(B20=_Jahr_Ersatz_Speicher,1,IF((L19-_Degradation_Speicher_Jahr/100)<0,0,L19-_Degradation_Speicher_Jahr/100)) -> 0.84 | M20: =IF(E20,_Speicherkapazität*L20,"") | N20: =IF(E20,_Erhöhung_Eigennutzungsgrad_Speicher*L20,"") | O20: =IF(E20,N20/100*K20,"") | P20: =IF(E20,(O20)*(1-_Speicher_Wirkungsgrad/100),"") | Q20: =IF(E20,O20-P20,"") | R20: =IF(C20,R19*(1+_Teuerungsrate/100),"") -> 0.084934225 | S20: =IF(C20,K20*(1-_Eigennutzungsgrad/100-_Anteil_LEG/100)*R20,"") -> -4.0396377e-14 | T20: =IF(C20,T19*(1+_Teuerungsrate/100),"") -> 0.10262886 | U20: =IF(C20,K20*(_Anteil_LEG/100)*T20,"") -> 293.3846 | V20: =IF(C20,V19*(1+_Teuerungsrate/100),"") -> 0.24630925 | W20: =IF(C20,K20*(_Eigennutzungsgrad/100)*V20,"") -> 351.0658 | X20: =IF(C20,X19*(1+_Teuerungsrate/100),"") -> 1.5925167 | Y20: =IF(C20,_Summe_Leistungsspitzen*_Reduktion_Leistungsspitzen/100*J20*X20,"") -> 0 | Z20: =IF(C20,Z19*(1+_Teuerungsrate/100),"") -> 0 | AA20: =IF(C20,AA19*(1+_Teuerungsrate/100),"") -> 8.4934225 | AB20: =IF(C20,K20*(_Eigennutzungsgrad/100)*Z20+AA20*_Anzahl_Verbraucher*12,"") -> 0 | AC20: =IF(E20,Q20*V20,IF(C20,0,"")) -> 0 | AD20: =IF(E20,_Summe_Leistungsspitzen*_Reduktion_Leistungsspitzen_Batterie/100*L20*X20,IF(C20,0,"")) -> 0 | AE20: =IF(E20,-O20*R20,IF(C20,0,"")) -> 0 | AF20: =IF(INT($B20/AF$4)=$B20/AF$4,AF$3,0) -> 0 | AG20: =IF(INT($B20/AG$4)=$B20/AG$4,AG$3,0) -> 0 | AH20: =IF(INT($B20/AH$4)=$B20/AH$4,AH$3,0) -> 69 | AI20: =IF(INT($B20/AI$4)=$B20/AI$4,AI$3,0) -> 99 | AJ20: =IF(INT($B20/AJ$4)=$B20/AJ$4,AJ$3,0) -> 120 | AK20: =IF(INT($B20/AK$4)=$B20/AK$4,AK$3,0) -> 0 | AL20: =IF(INT($B20/AL$4)=$B20/AL$4,AL$3,0) -> 0 | AM20: =IF(INT($B20/AM$4)=$B20/AM$4,AM$3,0) -> 49.1008 | ... AU20: =IF(INT($B20/AU$4)=$B20/AU$4,AU$3,0) -> 0 | AV20: =SUM(AF20:AJ20,AM20:AS20) -> 337.1008 | AW20: =IF(C20,AW19*(1+_Teuerungsrate/100),"") -> 1.0616778 | AX20: =IF(C20,(-IF(_Berechnungsart_Unterhaltskosten=_Unterhalt_Preis_pro_kWh,K20*_spez_Unterhaltskosten,AV20))*AW20,"") -> -357.89244 | AY20: =IF(C20,(-AK20)*AW20,"") -> 0 | AZ20: =IF(C20,(-AL20)*AW20,"") -> 0 | BA20: =IF(E20,-(AT20+AU20)*AW20,IF((C20),0,"")) -> 0 | BB20: =IF(C20,-IF(_MWStPflicht=_MWStpflichtig,(S20)*_MWStSatz/100,0),"") -> 3.2721066e-15 | BC20: =IF(C20,-IF(_MWStPflicht=_MWStpflichtig,(AX20)*_MWStSatz/100,0),"") -> 28.989288 | BD20: =IF(E20,-IF(_MWStPflicht=_MWStpflichtig,(BA20)*_MWStSatz/100,0),IF(C20,0,"")) -> 0 | BE20: =IF(C20,IF(F20,_Einmalvergütung+_Fassadenbonus+_Höhenbonus+_Fassadenbonus,0),"") -> 0 | BF20: =IF(C19,IF(F19,0,BF19),"") -> 0 | BG20: =IF(C20,PMT(_Zins_Eigenkapital/100,_ZahlungsfristEIVFB,BF20)+BF20/_ZahlungsfristEIVFB,"") -> 0 | BH20: =IF(C20,PMT(_Zins_Eigenkapital/100,_Anlagenlebensdauer,_Eigenkapital)+BG20,"") -> -511.46667 | BI20: =IF(C20,IF(G20,PMT(_Zins_Fremdkapital1/100,_Laufzeit_Fremdkapital1,_Fremdkapital1),0),"") -> 0 | BJ20: =IF(C20,IF(H20,PMT(_Zins_Fremdkapital2/100,_Laufzeit_Fremdkapital2,_Fremdkapital2),0),"") -> 0 | BK20: =IF(D20,PMT(_Zins_Eigenkapital_Batterie/100,_Lebensdauer_Speicher,_Eigenkapital_Batterie)+BJ20,IF(C20,0,"")) -> 0 | BL20: =IF(D20,IF(I20,PMT(_Zins_Fremdkapital_Batterie/100,_Laufzeit_Fremdkapital_Batterie,_Fremdkapital_Batterie),0),IF(C20,0,"")) -> 0 | BM20: =IF(C20,S20+U20+W20+AB20+Y20+AX20+AY20+AZ20+BB20+BC20+BE20+BI20+BJ20,"") -> 315.54724 | BN20: =IF($C20,BM20-BI20-BJ20,"") -> 315.54724 | BO20: =IF($C20,BO19+BM20,"") -> -14898.503 | BP20: =IF(C20,BM20*(1+_Zins_Eigenkapital/100)^-B20,"") -> 315.54724 | BQ20: =IF($C20,BQ19+BP20,"") -> -14898.503 | BR20: =IF($C20,IF(AND(BQ19<0,BQ20>=0),B20,""),"") | BS20: =IF(C20,BM20+BA20+AC20+AD20+AE20+BD20+BL20,"") -> 315.54724 | BT20: =IF($C20,BS20-BI20-BJ20-BL20,"") -> 315.54724 | BU20: =IF($C20,BU19+BS20,"") -> -14898.503 | BV20: =IF(C20,BS20*(1+_Zins_Eigenkapital/100)^-B20,"") -> 315.54724 | BW20: =IF($C20,BW19+BV20,"") -> -14898.503 | BX20: =IF($C20,IF(AND(BW19<0,BW20>=0),B20,""),"") | BY20: =IF(E20,AC20+AD20+BL20+BA20+BD20+AE20,"") | BZ20: =IF(E20,BY20-BL20,"") | CA20: =IF($E20,CA19+BY20,"") | CB20: =IF(E20,BY20*(1+_Zins_Eigenkapital/100)^-I20,"") | CC20: =IF($E20,CC19+CB20,"") | CD20: =IF($E20,IF(AND(CC19<0,CC20>=0),B20,""),"")
... B37: =B36+1 -> 30 | C37: =IF(B37<=_Anlagenlebensdauer,TRUE,FALSE) -> TRUE | D37: =IF(AND(_Batterie=_JA,B37<=_Lebensdauer_Speicher),TRUE,FALSE) -> FALSE | E37: =IF(AND(_Batterie=_JA,_Kosten_Ersatz_Speicher>0),IF(AND(B37<=_Jahr_Ersatz_Speicher-1+_Lebensdauer_Speicher,C37),TRUE,FALSE),IF(AND(_Batterie=_JA,B37<=_Lebensdauer_Speicher,C37),TRUE,FALSE)) -> FALSE | F37: =IF(B37=_ZahlungsfristEIVFB,TRUE,FALSE) -> FALSE | G37: =IF(B37<=_Laufzeit_Fremdkapital1,TRUE,FALSE) -> FALSE | H37: =IF(B37<=_Laufzeit_Fremdkapital2,TRUE,FALSE) -> FALSE | I37: =IF(B37<=_Laufzeit_Fremdkapital_Batterie,TRUE,FALSE) -> FALSE | J37: =(1-((B37-1)*_Degradation)/100) -> 0.884 | K37: =IF(C37,_Anlagenleistung*J37*_spez_Jahresenergieertrag,"") -> 3978 | L37: =IF(B37=_Jahr_Ersatz_Speicher,1,IF((L36-_Degradation_Speicher_Jahr/100)<0,0,L36-_Degradation_Speicher_Jahr/100)) -> 0.81333333 | M37: =IF(E37,_Speicherkapazität*L37,"") | N37: =IF(E37,_Erhöhung_Eigennutzungsgrad_Speicher*L37,"") | O37: =IF(E37,N37/100*K37,"") | P37: =IF(E37,(O37)*(1-_Speicher_Wirkungsgrad/100),"") | Q37: =IF(E37,O37-P37,"") | R37: =IF(C37,R36*(1+_Teuerungsrate/100),"") -> 0.092449758 | S37: =IF(C37,K37*(1-_Eigennutzungsgrad/100-_Anteil_LEG/100)*R37,"") -> -4.0830132e-14 | T37: =IF(C37,T36*(1+_Teuerungsrate/100),"") -> 0.11171012 | U37: =IF(C37,K37*(_Anteil_LEG/100)*T37,"") -> 296.53481 | V37: =IF(C37,V36*(1+_Teuerungsrate/100),"") -> 0.2681043 | W37: =IF(C37,K37*(_Eigennutzungsgrad/100)*V37,"") -> 354.83536 | X37: =IF(C37,X36*(1+_Teuerungsrate/100),"") -> 1.733433 | Y37: =IF(C37,_Summe_Leistungsspitzen*_Reduktion_Leistungsspitzen/100*J37*X37,"") -> 0 | Z37: =IF(C37,Z36*(1+_Teuerungsrate/100),"") -> 0 | AA37: =IF(C37,AA36*(1+_Teuerungsrate/100),"") -> 9.2449758 | AB37: =IF(C37,K37*(_Eigennutzungsgrad/100)*Z37+AA37*_Anzahl_Verbraucher*12,"") -> 0 | AC37: =IF(E37,Q37*V37,IF(C37,0,"")) -> 0 | AD37: =IF(E37,_Summe_Leistungsspitzen*_Reduktion_Leistungsspitzen_Batterie/100*L37*X37,IF(C37,0,"")) -> 0 | AE37: =IF(E37,-O37*R37,IF(C37,0,"")) -> 0 | AF37: =IF(INT($B37/AF$4)=$B37/AF$4,AF$3,0) -> 830.688 | AG37: =IF(INT($B37/AG$4)=$B37/AG$4,AG$3,0) -> 0 | AH37: =IF(INT($B37/AH$4)=$B37/AH$4,AH$3,0) -> 69 | AI37: =IF(INT($B37/AI$4)=$B37/AI$4,AI$3,0) -> 99 | AJ37: =IF(INT($B37/AJ$4)=$B37/AJ$4,AJ$3,0) -> 120 | AK37: =IF(INT($B37/AK$4)=$B37/AK$4,AK$3,0) -> 0 | AL37: =IF(INT($B37/AL$4)=$B37/AL$4,AL$3,0) -> 0 | AM37: =IF(INT($B37/AM$4)=$B37/AM$4,AM$3,0) -> 49.1008 | ... AU37: =IF(INT($B37/AU$4)=$B37/AU$4,AU$3,0) -> 0 | AV37: =SUM(AF37:AJ37,AM37:AS37) -> 1167.7888 | AW37: =IF(C37,AW36*(1+_Teuerungsrate/100),"") -> 1.155622 | AX37: =IF(C37,(-IF(_Berechnungsart_Unterhaltskosten=_Unterhalt_Preis_pro_kWh,K37*_spez_Unterhaltskosten,AV37))*AW37,"") -> -1349.5224 | AY37: =IF(C37,(-AK37)*AW37,"") -> 0 | AZ37: =IF(C37,(-AL37)*AW37,"") -> 0 | BA37: =IF(E37,-(AT37+AU37)*AW37,IF((C37),0,"")) -> 0 | BB37: =IF(C37,-IF(_MWStPflicht=_MWStpflichtig,(S37)*_MWStSatz/100,0),"") -> 3.3072407e-15 | BC37: =IF(C37,-IF(_MWStPflicht=_MWStpflichtig,(AX37)*_MWStSatz/100,0),"") -> 109.31131 | BD37: =IF(E37,-IF(_MWStPflicht=_MWStpflichtig,(BA37)*_MWStSatz/100,0),IF(C37,0,"")) -> 0 | BE37: =IF(C37,IF(F37,_Einmalvergütung+_Fassadenbonus+_Höhenbonus+_Fassadenbonus,0),"") -> 0 | BF37: =IF(C36,IF(F36,0,BF36),"") -> 0 | BG37: =IF(C37,PMT(_Zins_Eigenkapital/100,_ZahlungsfristEIVFB,BF37)+BF37/_ZahlungsfristEIVFB,"") -> 0 | BH37: =IF(C37,PMT(_Zins_Eigenkapital/100,_Anlagenlebensdauer,_Eigenkapital)+BG37,"") -> -511.46667 | BI37: =IF(C37,IF(G37,PMT(_Zins_Fremdkapital1/100,_Laufzeit_Fremdkapital1,_Fremdkapital1),0),"") -> 0 | BJ37: =IF(C37,IF(H37,PMT(_Zins_Fremdkapital2/100,_Laufzeit_Fremdkapital2,_Fremdkapital2),0),"") -> 0 | BK37: =IF(D37,PMT(_Zins_Eigenkapital_Batterie/100,_Lebensdauer_Speicher,_Eigenkapital_Batterie)+BJ37,IF(C37,0,"")) -> 0 | BL37: =IF(D37,IF(I37,PMT(_Zins_Fremdkapital_Batterie/100,_Laufzeit_Fremdkapital_Batterie,_Fremdkapital_Batterie),0),IF(C37,0,"")) -> 0 | BM37: =IF(C37,S37+U37+W37+AB37+Y37+AX37+AY37+AZ37+BB37+BC37+BE37+BI37+BJ37,"") -> -588.84092 | BN37: =IF($C37,BM37-BI37-BJ37,"") -> -588.84092 | BO37: =IF($C37,BO36+BM37,"") -> -18880.846 | BP37: =IF(C37,BM37*(1+_Zins_Eigenkapital/100)^-B37,"") -> -588.84092 | BQ37: =IF($C37,BQ36+BP37,"") -> -18880.846 | BR37: =IF($C37,IF(AND(BQ36<0,BQ37>=0),B37,""),"") | BS37: =IF(C37,BM37+BA37+AC37+AD37+AE37+BD37+BL37,"") -> -588.84092 | BT37: =IF($C37,BS37-BI37-BJ37-BL37,"") -> -588.84092 | BU37: =IF($C37,BU36+BS37,"") -> -18880.846 | BV37: =IF(C37,BS37*(1+_Zins_Eigenkapital/100)^-B37,"") -> -588.84092 | BW37: =IF($C37,BW36+BV37,"") -> -18880.846 | BX37: =IF($C37,IF(AND(BW36<0,BW37>=0),B37,""),"") | BY37: =IF(E37,AC37+AD37+BL37+BA37+BD37+AE37,"") | BZ37: =IF(E37,BY37-BL37,"") | CA37: =IF($E37,CA36+BY37,"") | CB37: =IF(E37,BY37*(1+_Zins_Eigenkapital/100)^-I37,"") | CC37: =IF($E37,CC36+CB37,"") | CD37: =IF($E37,IF(AND(CC36<0,CC37>=0),B37,""),"")
B38: =B37+1 -> 31 | C38: =IF(B38<=_Anlagenlebensdauer,TRUE,FALSE) -> FALSE | D38: =IF(AND(_Batterie=_JA,B38<=_Lebensdauer_Speicher),TRUE,FALSE) -> FALSE | E38: =IF(AND(_Batterie=_JA,_Kosten_Ersatz_Speicher>0),IF(AND(B38<=_Jahr_Ersatz_Speicher-1+_Lebensdauer_Speicher,C38),TRUE,FALSE),IF(AND(_Batterie=_JA,B38<=_Lebensdauer_Speicher,C38),TRUE,FALSE)) -> FALSE | F38: =IF(B38=_ZahlungsfristEIVFB,TRUE,FALSE) -> FALSE | G38: =IF(B38<=_Laufzeit_Fremdkapital1,TRUE,FALSE) -> FALSE | H38: =IF(B38<=_Laufzeit_Fremdkapital2,TRUE,FALSE) -> FALSE | I38: =IF(B38<=_Laufzeit_Fremdkapital_Batterie,TRUE,FALSE) -> FALSE | J38: =(1-((B38-1)*_Degradation)/100) -> 0.88 | K38: =IF(C38,_Anlagenleistung*J38*_spez_Jahresenergieertrag,"") | L38: =IF(B38=_Jahr_Ersatz_Speicher,1,IF((L37-_Degradation_Speicher_Jahr/100)<0,0,L37-_Degradation_Speicher_Jahr/100)) -> 0.8 | M38: =IF(E38,_Speicherkapazität*L38,"") | N38: =IF(E38,_Erhöhung_Eigennutzungsgrad_Speicher*L38,"") | O38: =IF(E38,N38/100*K38,"") | P38: =IF(E38,(O38)*(1-_Speicher_Wirkungsgrad/100),"") | Q38: =IF(E38,O38-P38,"") | R38: =IF(C38,R37*(1+_Teuerungsrate/100),"") | S38: =IF(C38,K38*(1-_Eigennutzungsgrad/100-_Anteil_LEG/100)*R38,"") | T38: =IF(C38,T37*(1+_Teuerungsrate/100),"") | U38: =IF(C38,K38*(_Anteil_LEG/100)*T38,"") | V38: =IF(C38,V37*(1+_Teuerungsrate/100),"") | W38: =IF(C38,K38*(_Eigennutzungsgrad/100)*V38,"") | X38: =IF(C38,X37*(1+_Teuerungsrate/100),"") | Y38: =IF(C38,_Summe_Leistungsspitzen*_Reduktion_Leistungsspitzen/100*J38*X38,"") | Z38: =IF(C38,Z37*(1+_Teuerungsrate/100),"") | AA38: =IF(C38,AA37*(1+_Teuerungsrate/100),"") | AB38: =IF(C38,K38*(_Eigennutzungsgrad/100)*Z38+AA38*_Anzahl_Verbraucher*12,"") | AC38: =IF(E38,Q38*V38,IF(C38,0,"")) | AD38: =IF(E38,_Summe_Leistungsspitzen*_Reduktion_Leistungsspitzen_Batterie/100*L38*X38,IF(C38,0,"")) | AE38: =IF(E38,-O38*R38,IF(C38,0,"")) | AF38: =IF(INT($B38/AF$4)=$B38/AF$4,AF$3,0) -> 0 | AG38: =IF(INT($B38/AG$4)=$B38/AG$4,AG$3,0) -> 0 | AH38: =IF(INT($B38/AH$4)=$B38/AH$4,AH$3,0) -> 69 | AI38: =IF(INT($B38/AI$4)=$B38/AI$4,AI$3,0) -> 99 | AJ38: =IF(INT($B38/AJ$4)=$B38/AJ$4,AJ$3,0) -> 120 | AK38: =IF(INT($B38/AK$4)=$B38/AK$4,AK$3,0) -> 0 | AL38: =IF(INT($B38/AL$4)=$B38/AL$4,AL$3,0) -> 0 | AM38: =IF(INT($B38/AM$4)=$B38/AM$4,AM$3,0) -> 49.1008 | ... AU38: =IF(INT($B38/AU$4)=$B38/AU$4,AU$3,0) -> 0 | AV38: =SUM(AF38:AJ38,AM38:AS38) -> 337.1008 | AW38: =IF(C38,AW37*(1+_Teuerungsrate/100),"") | AX38: =IF(C38,(-IF(_Berechnungsart_Unterhaltskosten=_Unterhalt_Preis_pro_kWh,K38*_spez_Unterhaltskosten,AV38))*AW38,"") | AY38: =IF(C38,(-AK38)*AW38,"") | AZ38: =IF(C38,(-AL38)*AW38,"") | BA38: =IF(E38,-(AT38+AU38)*AW38,IF((C38),0,"")) | BB38: =IF(C38,-IF(_MWStPflicht=_MWStpflichtig,(S38)*_MWStSatz/100,0),"") | BC38: =IF(C38,-IF(_MWStPflicht=_MWStpflichtig,(AX38)*_MWStSatz/100,0),"") | BD38: =IF(E38,-IF(_MWStPflicht=_MWStpflichtig,(BA38)*_MWStSatz/100,0),IF(C38,0,"")) | BE38: =IF(C38,IF(F38,_Einmalvergütung+_Fassadenbonus+_Höhenbonus+_Fassadenbonus,0),"") | BF38: =IF(C37,IF(F37,0,BF37),"") -> 0 | BG38: =IF(C38,PMT(_Zins_Eigenkapital/100,_ZahlungsfristEIVFB,BF38)+BF38/_ZahlungsfristEIVFB,"") | BH38: =IF(C38,PMT(_Zins_Eigenkapital/100,_Anlagenlebensdauer,_Eigenkapital)+BG38,"") | BI38: =IF(C38,IF(G38,PMT(_Zins_Fremdkapital1/100,_Laufzeit_Fremdkapital1,_Fremdkapital1),0),"") | BJ38: =IF(C38,IF(H38,PMT(_Zins_Fremdkapital2/100,_Laufzeit_Fremdkapital2,_Fremdkapital2),0),"") | BK38: =IF(D38,PMT(_Zins_Eigenkapital_Batterie/100,_Lebensdauer_Speicher,_Eigenkapital_Batterie)+BJ38,IF(C38,0,"")) | BL38: =IF(D38,IF(I38,PMT(_Zins_Fremdkapital_Batterie/100,_Laufzeit_Fremdkapital_Batterie,_Fremdkapital_Batterie),0),IF(C38,0,"")) | BM38: =IF(C38,S38+U38+W38+AB38+Y38+AX38+AY38+AZ38+BB38+BC38+BE38+BI38+BJ38,"") | BN38: =IF($C38,BM38-BI38-BJ38,"") | BO38: =IF($C38,BO37+BM38,"") | BP38: =IF(C38,BM38*(1+_Zins_Eigenkapital/100)^-B38,"") | BQ38: =IF($C38,BQ37+BP38,"") | BR38: =IF($C38,IF(AND(BQ37<0,BQ38>=0),B38,""),"") | BS38: =IF(C38,BM38+BA38+AC38+AD38+AE38+BD38+BL38,"") | BT38: =IF($C38,BM38-BI38-BJ38-BL38,"") | BU38: =IF($C38,IF($C38,BS37+BS38,0),"") | BV38: =IF(C38,BS38*(1+_Zins_Eigenkapital/100)^-B38,"") | BW38: =IF($C38,BW37+BV38,"") | BX38: =IF($C38,IF(AND(BW37<0,BW38>=0),B38,""),"") | BY38: =IF(E38,AC38+AD38+BL38+BA38+BD38+AE38,"") | BZ38: =IF(E38,BY38-BL38,"") | CA38: =IF($E38,CA37+BY38,"") | CB38: =IF(E38,BY38*(1+_Zins_Eigenkapital/100)^-I38,"") | CC38: =IF($E38,CC37+CB38,"") | CD38: =IF($E38,IF(AND(CC37<0,CC38>=0),B38,""),"")
B39: =B38+1 -> 32 | C39: =IF(B39<=_Anlagenlebensdauer,TRUE,FALSE) -> FALSE | D39: =IF(AND(_Batterie=_JA,B39<=_Lebensdauer_Speicher),TRUE,FALSE) -> FALSE | E39: =IF(AND(_Batterie=_JA,_Kosten_Ersatz_Speicher>0),IF(AND(B39<=_Jahr_Ersatz_Speicher-1+_Lebensdauer_Speicher,C39),TRUE,FALSE),IF(AND(_Batterie=_JA,B39<=_Lebensdauer_Speicher,C39),TRUE,FALSE)) -> FALSE | F39: =IF(B39=_ZahlungsfristEIVFB,TRUE,FALSE) -> FALSE | G39: =IF(B39<=_Laufzeit_Fremdkapital1,TRUE,FALSE) -> FALSE | H39: =IF(B39<=_Laufzeit_Fremdkapital2,TRUE,FALSE) -> FALSE | I39: =IF(B39<=_Laufzeit_Fremdkapital_Batterie,TRUE,FALSE) -> FALSE | J39: =(1-((B39-1)*_Degradation)/100) -> 0.876 | K39: =IF(C39,_Anlagenleistung*J39*_spez_Jahresenergieertrag,"") | L39: =IF(B39=_Jahr_Ersatz_Speicher,1,IF((L38-_Degradation_Speicher_Jahr/100)<0,0,L38-_Degradation_Speicher_Jahr/100)) -> 0.78666667 | M39: =IF(E39,_Speicherkapazität*L39,"") | N39: =IF(E39,_Erhöhung_Eigennutzungsgrad_Speicher*L39,"") | O39: =IF(E39,N39/100*K39,"") | P39: =IF(E39,(O39)*(1-_Speicher_Wirkungsgrad/100),"") | Q39: =IF(E39,O39-P39,"") | R39: =IF(C39,R38*(1+_Teuerungsrate/100),"") | S39: =IF(C39,K39*(1-_Eigennutzungsgrad/100-_Anteil_LEG/100)*R39,"") | T39: =IF(C39,T38*(1+_Teuerungsrate/100),"") | U39: =IF(C39,K39*(_Anteil_LEG/100)*T39,"") | V39: =IF(C39,V38*(1+_Teuerungsrate/100),"") | W39: =IF(C39,K39*(_Eigennutzungsgrad/100)*V39,"") | X39: =IF(C39,X38*(1+_Teuerungsrate/100),"") | Y39: =IF(C39,_Summe_Leistungsspitzen*_Reduktion_Leistungsspitzen/100*J39*X39,"") | Z39: =IF(C39,Z38*(1+_Teuerungsrate/100),"") | AA39: =IF(C39,AA38*(1+_Teuerungsrate/100),"") | AB39: =IF(C39,K39*(_Eigennutzungsgrad/100)*Z39+AA39*_Anzahl_Verbraucher*12,"") | AC39: =IF(E39,Q39*V39,IF(C39,0,"")) | AD39: =IF(E39,_Summe_Leistungsspitzen*_Reduktion_Leistungsspitzen_Batterie/100*L39*X39,IF(C39,0,"")) | AE39: =IF(E39,-O39*R39,IF(C39,0,"")) | AF39: =IF(INT($B39/AF$4)=$B39/AF$4,AF$3,0) -> 0 | AG39: =IF(INT($B39/AG$4)=$B39/AG$4,AG$3,0) -> 0 | AH39: =IF(INT($B39/AH$4)=$B39/AH$4,AH$3,0) -> 69 | AI39: =IF(INT($B39/AI$4)=$B39/AI$4,AI$3,0) -> 99 | AJ39: =IF(INT($B39/AJ$4)=$B39/AJ$4,AJ$3,0) -> 120 | AK39: =IF(INT($B39/AK$4)=$B39/AK$4,AK$3,0) -> 0 | AL39: =IF(INT($B39/AL$4)=$B39/AL$4,AL$3,0) -> 0 | AM39: =IF(INT($B39/AM$4)=$B39/AM$4,AM$3,0) -> 49.1008 | ... AU39: =IF(INT($B39/AU$4)=$B39/AU$4,AU$3,0) -> 0 | AV39: =SUM(AF39:AJ39,AM39:AS39) -> 3783.6948 | AW39: =IF(C39,AW38*(1+_Teuerungsrate/100),"") | AX39: =IF(C39,(-IF(_Berechnungsart_Unterhaltskosten=_Unterhalt_Preis_pro_kWh,K39*_spez_Unterhaltskosten,AV39))*AW39,"") | AY39: =IF(C39,(-AK39)*AW39,"") | AZ39: =IF(C39,(-AL39)*AW39,"") | BA39: =IF(E39,-(AT39+AU39)*AW39,IF((C39),0,"")) | BB39: =IF(C39,-IF(_MWStPflicht=_MWStpflichtig,(S39)*_MWStSatz/100,0),"") | BC39: =IF(C39,-IF(_MWStPflicht=_MWStpflichtig,(AX39)*_MWStSatz/100,0),"") | BD39: =IF(E39,-IF(_MWStPflicht=_MWStpflichtig,(BA39)*_MWStSatz/100,0),IF(C39,0,"")) | BE39: =IF(C39,IF(F39,_Einmalvergütung+_Fassadenbonus+_Höhenbonus+_Fassadenbonus,0),"") | BF39: =IF(C38,IF(F38,0,BF38),"") | BG39: =IF(C39,PMT(_Zins_Eigenkapital/100,_ZahlungsfristEIVFB,BF39)+BF39/_ZahlungsfristEIVFB,"") | BH39: =IF(C39,PMT(_Zins_Eigenkapital/100,_Anlagenlebensdauer,_Eigenkapital)+BG39,"") | BI39: =IF(C39,IF(G39,PMT(_Zins_Fremdkapital1/100,_Laufzeit_Fremdkapital1,_Fremdkapital1),0),"") | BJ39: =IF(C39,IF(H39,PMT(_Zins_Fremdkapital2/100,_Laufzeit_Fremdkapital2,_Fremdkapital2),0),"") | BK39: =IF(D39,PMT(_Zins_Eigenkapital_Batterie/100,_Lebensdauer_Speicher,_Eigenkapital_Batterie)+BJ39,IF(C39,0,"")) | BL39: =IF(D39,IF(I39,PMT(_Zins_Fremdkapital_Batterie/100,_Laufzeit_Fremdkapital_Batterie,_Fremdkapital_Batterie),0),IF(C39,0,"")) | BM39: =IF(C39,S39+U39+W39+AB39+Y39+AX39+AY39+AZ39+BB39+BC39+BE39+BI39+BJ39,"") | BN39: =IF($C39,BM39-BI39-BJ39,"") | BO39: =IF($C39,BO38+BM39,"") | BP39: =IF(C39,BM39*(1+_Zins_Eigenkapital/100)^-B39,"") | BQ39: =IF($C39,BQ38+BP39,"") | BR39: =IF($C39,IF(AND(BQ38<0,BQ39>=0),B39,""),"") | BS39: =IF(C39,BM39+BA39+AC39+AD39+AE39+BD39+BL39,"") | BT39: =IF($C39,BM39-BI39-BJ39-BL39,"") | BU39: =IF($C39,IF($C39,BS38+BS39,0),"") | BV39: =IF(C39,BS39*(1+_Zins_Eigenkapital/100)^-B39,"") | BW39: =IF($C39,BW38+BV39,"") | BX39: =IF($C39,IF(AND(BW38<0,BW39>=0),B39,""),"") | BY39: =IF(E39,AC39+AD39+BL39+BA39+BD39+AE39,"") | BZ39: =IF(E39,BY39-BL39,"") | CA39: =IF($E39,CA38+BY39,"") | CB39: =IF(E39,BY39*(1+_Zins_Eigenkapital/100)^-I39,"") | CC39: =IF($E39,CC38+CB39,"") | CD39: =IF($E39,IF(AND(CC38<0,CC39>=0),B39,""),"")
